Workbook

Sheet Base_Datos
A1: SISTEMA DE CONTROL DE INVENTARIO — DISTRIBUIDORA FMCG
A2: Base de Datos · 75 SKUs · Categorías: Alimentos Secos / Limpieza del Hogar / Higiene Personal · Período: Ene–Jun 2025
A4: SKU ID | B4: Descripción | C4: Categoría | D4: Cód. Proveedor | E4: Proveedor | F4: Precio Costo (USD) | G4: Stock Actual | H4: Stock Mínimo | I4: Ventas Ene-25 | J4: Ventas Feb-25 | K4: Ventas Mar-25 | L4: Ventas Abr-25 | M4: Ventas May-25 | N4: Ventas Jun-25 | O4: Total Ventas 6 meses | P4: Venta Prom. Mensual | Q4: Últ. Movimiento | R4: Días sin Movimiento | S4: Capital Inmovilizado (USD)
A5: ALIMENTOS SECOS
A6: SKU-001 | B6: Arroz Largo Fino 1kg | C6: Alimentos Secos | D6: PRV-001 | E6: Arrocera del Sur S.A. | F6: 3.2 | G6: 64 | H6: 14 | I6: 51 | J6: 61 | K6: 59 | L6: 78 | M6: 76 | N6: 84 | O6: =SUM(I6:N6) -> 409 | P6: =O6/6 -> 68.166667 | Q6: 45829 | R6: =DATE(2025,6,22)-Q6 -> 1 | S6: =G6*F6 -> 204.8
A7: SKU-002 | B7: Arroz Largo Fino 5kg | C7: Alimentos Secos | D7: PRV-001 | E7: Arrocera del Sur S.A. | F7: 14.5 | G7: 69 | H7: 14 | I7: 54 | J7: 64 | K7: 48 | L7: 54 | M7: 69 | N7: 66 | O7: =SUM(I7:N7) -> 355 | P7: =O7/6 -> 59.166667 | Q7: 45804 | R7: =DATE(2025,6,22)-Q7 -> 26 | S7: =G7*F7 -> 1000.5
A8: SKU-003 | B8: Fideos Spaghetti 500g | C8: Alimentos Secos | D8: PRV-002 | E8: Molinos Río de la Plata | F8: 1.8 | G8: 190 | H8: 8 | I8: 47 | J8: 34 | K8: 40 | L8: 37 | M8: 35 | N8: 47 | O8: =SUM(I8:N8) -> 240 | P8: =O8/6 -> 40 | Q8: 45818 | R8: =DATE(2025,6,22)-Q8 -> 12 | S8: =G8*F8 -> 342
A9: SKU-004 | B9: Fideos Moño 500g | C9: Alimentos Secos | D9: PRV-002 | E9: Molinos Río de la Plata | F9: 1.8 | G9: 248 | H9: 39 | I9: 138 | J9: 152 | K9: 147 | L9: 133 | M9: 164 | N9: 122 | O9: =SUM(I9:N9) -> 856 | P9: =O9/6 -> 142.66667 | Q9: 45810 | R9: =DATE(2025,6,22)-Q9 -> 20 | S9: =G9*F9 -> 446.4
A10: SKU-005 | B10: Harina 000 1kg | C10: Alimentos Secos | D10: PRV-003 | E10: Molinera Central S.R.L. | F10: 1.5 | G10: 24 | H10: 69 | I10: 460 | J10: 401 | K10: 427 | L10: 291 | M10: 329 | N10: 341 | O10: =SUM(I10:N10) -> 2249 | P10: =O10/6 -> 374.83333 | Q10: 45826 | R10: =DATE(2025,6,22)-Q10 -> 4 | S10: =G10*F10 -> 36
A11: SKU-006 | B11: Harina 0000 1kg | C11: Alimentos Secos | D11: PRV-003 | E11: Molinera Central S.R.L. | F11: 1.65 | G11: 308 | H11: 31 | I11: 123 | J11: 150 | K11: 130 | L11: 130 | M11: 118 | N11: 122 | O11: =SUM(I11:N11) -> 773 | P11: =O11/6 -> 128.83333 | Q11: 45810 | R11: =DATE(2025,6,22)-Q11 -> 20 | S11: =G11*F11 -> 508.2
A12: SKU-007 | B12: Azúcar Blanca 1kg | C12: Alimentos Secos | D12: PRV-004 | E12: Ingenio Azucarero Norte | F12: 1.4 | G12: 43 | H12: 6 | I12: 21 | J12: 28 | K12: 20 | L12: 23 | M12: 32 | N12: 27 | O12: =SUM(I12:N12) -> 151 | P12: =O12/6 -> 25.166667 | Q12: 45771 | R12: =DATE(2025,6,22)-Q12 -> 59 | S12: =G12*F12 -> 60.2
A13: SKU-008 | B13: Azúcar Morena 1kg | C13: Alimentos Secos | D13: PRV-004 | E13: Ingenio Azucarero Norte | F13: 1.6 | G13: 333 | H13: 9 | I13: 47 | J13: 41 | K13: 49 | L13: 48 | M13: 46 | N13: 68 | O13: =SUM(I13:N13) -> 299 | P13: =O13/6 -> 49.833333 | Q13: 45809 | R13: =DATE(2025,6,22)-Q13 -> 21 | S13: =G13*F13 -> 532.8
A14: SKU-009 | B14: Aceite de Girasol 900cc | C14: Alimentos Secos | D14: PRV-005 | E14: Aceites Nacionales S.A. | F14: 2.9 | G14: 209 | H14: 39 | I14: 161 | J14: 209 | K14: 167 | L14: 149 | M14: 147 | N14: 176 | O14: =SUM(I14:N14) -> 1009 | P14: =O14/6 -> 168.16667 | Q14: 45801 | R14: =DATE(2025,6,22)-Q14 -> 29 | S14: =G14*F14 -> 606.1
A15: SKU-010 | B15: Aceite de Girasol 1.8L | C15: Alimentos Secos | D15: PRV-005 | E15: Aceites Nacionales S.A. | F15: 5.5 | G15: 162 | H15: 26 | I15: 134 | J15: 184 | K15: 117 | L15: 145 | M15: 165 | N15: 173 | O15: =SUM(I15:N15) -> 918 | P15: =O15/6 -> 153 | Q15: 45808 | R15: =DATE(2025,6,22)-Q15 -> 22 | S15: =G15*F15 -> 891
A16: SKU-011 | B16: Aceite de Maíz 900cc | C16: Alimentos Secos | D16: PRV-005 | E16: Aceites Nacionales S.A. | F16: 3.2 | G16: 109 | H16: 5 | I16: 2 | J16: 2 | K16: 0 | L16: 2 | M16: 3 | N16: 1 | O16: =SUM(I16:N16) -> 10 | P16: =O16/6 -> 1.6666667 | Q16: 45722 | R16: =DATE(2025,6,22)-Q16 -> 108 | S16: =G16*F16 -> 348.8
A17: SKU-012 | B17: Sal Fina 1kg | C17: Alimentos Secos | D17: PRV-006 | E17: Salinera Patagónica | F17: 0.85 | G17: 88 | H17: 91 | I17: 428 | J17: 480 | K17: 437 | L17: 384 | M17: 302 | N17: 409 | O17: =SUM(I17:N17) -> 2440 | P17: =O17/6 -> 406.66667 | Q17: 45823 | R17: =DATE(2025,6,22)-Q17 -> 7 | S17: =G17*F17 -> 74.8
... A30: SKU-025 | B30: Porotos Negros 500g | C30: Alimentos Secos | D30: PRV-012 | E30: Legumbres del Norte | F30: 1.7 | G30: 304 | H30: 35 | I30: 159 | J30: 154 | K30: 193 | L30: 159 | M30: 155 | N30: 142 | O30: =SUM(I30:N30) -> 962 | P30: =O30/6 -> 160.33333 | Q30: 45800 | R30: =DATE(2025,6,22)-Q30 -> 30 | S30: =G30*F30 -> 516.8
A31: LIMPIEZA DEL HOGAR
A32: SKU-026 | B32: Lavandina Concentrada 1L | C32: Limpieza del Hogar | D32: PRV-013 | E32: Química Limpieza S.A. | F32: 1.2 | G32: 267 | H32: 11 | I32: 43 | J32: 63 | K32: 61 | L32: 46 | M32: 60 | N32: 59 | O32: =SUM(I32:N32) -> 332 | P32: =O32/6 -> 55.333333 | Q32: 45827 | R32: =DATE(2025,6,22)-Q32 -> 3 | S32: =G32*F32 -> 320.4
A33: SKU-027 | B33: Lavandina Clásica 2L | C33: Limpieza del Hogar | D33: PRV-013 | E33: Química Limpieza S.A. | F33: 1.8 | G33: 210 | H33: 16 | I33: 97 | J33: 85 | K33: 123 | L33: 115 | M33: 110 | N33: 131 | O33: =SUM(I33:N33) -> 661 | P33: =O33/6 -> 110.16667 | Q33: 45803 | R33: =DATE(2025,6,22)-Q33 -> 27 | S33: =G33*F33 -> 378
A34: SKU-028 | B34: Detergente Lavavajillas 500ml | C34: Limpieza del Hogar | D34: PRV-014 | E34: Unilever Argentina | F34: 2.4 | G34: 135 | H34: 24 | I34: 146 | J34: 93 | K34: 143 | L34: 103 | M34: 143 | N34: 134 | O34: =SUM(I34:N34) -> 762 | P34: =O34/6 -> 127 | Q34: 45823 | R34: =DATE(2025,6,22)-Q34 -> 7 | S34: =G34*F34 -> 324
A35: SKU-029 | B35: Detergente Lavavajillas 1L | C35: Limpieza del Hogar | D35: PRV-014 | E35: Unilever Argentina | F35: 4.2 | G35: 14 | H35: 5 | I35: 12 | J35: 16 | K35: 13 | L35: 15 | M35: 18 | N35: 18 | O35: =SUM(I35:N35) -> 92 | P35: =O35/6 -> 15.333333 | Q35: 45787 | R35: =DATE(2025,6,22)-Q35 -> 43 | S35: =G35*F35 -> 58.8
A36: SKU-030 | B36: Jabón en Polvo 1kg | C36: Limpieza del Hogar | D36: PRV-015 | E36: Procter & Gamble AR | F36: 4.8 | G36: 78 | H36: 7 | I36: 38 | J36: 59 | K36: 56 | L36: 45 | M36: 59 | N36: 53 | O36: =SUM(I36:N36) -> 310 | P36: =O36/6 -> 51.666667 | Q36: 45827 | R36: =DATE(2025,6,22)-Q36 -> 3 | S36: =G36*F36 -> 374.4
A37: SKU-031 | B37: Jabón en Polvo 3kg | C37: Limpieza del Hogar | D37: PRV-015 | E37: Procter & Gamble AR | F37: 13.5 | G37: 512 | H37: 20 | I37: 81 | J37: 94 | K37: 83 | L37: 64 | M37: 63 | N37: 71 | O37: =SUM(I37:N37) -> 456 | P37: =O37/6 -> 76 | Q37: 45802 | R37: =DATE(2025,6,22)-Q37 -> 28 | S37: =G37*F37 -> 6912
A38: SKU-032 | B38: Suavizante Ropa 800ml | C38: Limpieza del Hogar | D38: PRV-016 | E38: Henkel Argentina | F38: 3.6 | G38: 76 | H38: 12 | I38: 62 | J38: 43 | K38: 44 | L38: 40 | M38: 58 | N38: 61 | O38: =SUM(I38:N38) -> 308 | P38: =O38/6 -> 51.333333 | Q38: 45825 | R38: =DATE(2025,6,22)-Q38 -> 5 | S38: =G38*F38 -> 273.6
A39: SKU-033 | B39: Suavizante Ropa 1.5L | C39: Limpieza del Hogar | D39: PRV-016 | E39: Henkel Argentina | F39: 6.2 | G39: 185 | H39: 5 | I39: 1 | J39: 2 | K39: 1 | L39: 0 | M39: 3 | N39: 0 | O39: =SUM(I39:N39) -> 7 | P39: =O39/6 -> 1.1666667 | Q39: 45754 | R39: =DATE(2025,6,22)-Q39 -> 76 | S39: =G39*F39 -> 1147
A40: SKU-034 | B40: Limpiador Multiuso 500ml | C40: Limpieza del Hogar | D40: PRV-017 | E40: Reckitt Benckiser AR | F40: 2.9 | G40: 101 | H40: 17 | I40: 109 | J40: 91 | K40: 83 | L40: 108 | M40: 79 | N40: 69 | O40: =SUM(I40:N40) -> 539 | P40: =O40/6 -> 89.833333 | Q40: 45802 | R40: =DATE(2025,6,22)-Q40 -> 28 | S40: =G40*F40 -> 292.9
A41: SKU-035 | B41: Limpiador Piso 1L | C41: Limpieza del Hogar | D41: PRV-017 | E41: Reckitt Benckiser AR | F41: 3.1 | G41: 43 | H41: 30 | I41: 214 | J41: 150 | K41: 184 | L41: 161 | M41: 215 | N41: 174 | O41: =SUM(I41:N41) -> 1098 | P41: =O41/6 -> 183 | Q41: 45821 | R41: =DATE(2025,6,22)-Q41 -> 9 | S41: =G41*F41 -> 133.3
A42: SKU-036 | B42: Desengrasante 500ml | C42: Limpieza del Hogar | D42: PRV-018 | E42: Limpiadores del Sur | F42: 3.5 | G42: 137 | H42: 26 | I42: 90 | J42: 109 | K42: 65 | L42: 91 | M42: 79 | N42: 100 | O42: =SUM(I42:N42) -> 534 | P42: =O42/6 -> 89 | Q42: 45826 | R42: =DATE(2025,6,22)-Q42 -> 4 | S42: =G42*F42 -> 479.5
A43: SKU-037 | B43: Limpiavidrios 500ml | C43: Limpieza del Hogar | D43: PRV-018 | E43: Limpiadores del Sur | F43: 2.7 | G43: 274 | H43: 40 | I43: 171 | J43: 117 | K43: 106 | L43: 136 | M43: 142 | N43: 164 | O43: =SUM(I43:N43) -> 836 | P43: =O43/6 -> 139.33333 | Q43: 45806 | R43: =DATE(2025,6,22)-Q43 -> 24 | S43: =G43*F43 -> 739.8
... A56: SKU-050 | B56: Guantes de Látex Talle G | C56: Limpieza del Hogar | D56: PRV-024 | E56: Artículos del Hogar | F56: 2.6 | G56: 309 | H56: 42 | I56: 164 | J56: 173 | K56: 179 | L56: 184 | M56: 149 | N56: 178 | O56: =SUM(I56:N56) -> 1027 | P56: =O56/6 -> 171.16667 | Q56: 45827 | R56: =DATE(2025,6,22)-Q56 -> 3 | S56: =G56*F56 -> 803.4
A57: HIGIENE PERSONAL
A58: SKU-051 | B58: Jabón de Tocador x3 | C58: Higiene Personal | D58: PRV-025 | E58: Johnson & Johnson AR | F58: 3.2 | G58: 848 | H58: 27 | I58: 122 | J58: 149 | K58: 115 | L58: 142 | M58: 129 | N58: 138 | O58: =SUM(I58:N58) -> 795 | P58: =O58/6 -> 132.5 | Q58: 45805 | R58: =DATE(2025,6,22)-Q58 -> 25 | S58: =G58*F58 -> 2713.6
A59: SKU-052 | B59: Jabón Líquido 300ml | C59: Higiene Personal | D59: PRV-025 | E59: Johnson & Johnson AR | F59: 4.5 | G59: 31 | H59: 5 | I59: 15 | J59: 14 | K59: 13 | L59: 18 | M59: 23 | N59: 16 | O59: =SUM(I59:N59) -> 99 | P59: =O59/6 -> 16.5 | Q59: 45775 | R59: =DATE(2025,6,22)-Q59 -> 55 | S59: =G59*F59 -> 139.5
A60: SKU-053 | B60: Shampoo 400ml | C60: Higiene Personal | D60: PRV-026 | E60: L'Oréal Argentina | F60: 5.8 | G60: 91 | H60: 11 | I60: 58 | J60: 63 | K60: 42 | L60: 38 | M60: 41 | N60: 40 | O60: =SUM(I60:N60) -> 282 | P60: =O60/6 -> 47 | Q60: 45823 | R60: =DATE(2025,6,22)-Q60 -> 7 | S60: =G60*F60 -> 527.8
A61: SKU-054 | B61: Acondicionador 400ml | C61: Higiene Personal | D61: PRV-026 | E61: L'Oréal Argentina | F61: 5.8 | G61: 359 | H61: 48 | I61: 180 | J61: 186 | K61: 133 | L61: 172 | M61: 184 | N61: 129 | O61: =SUM(I61:N61) -> 984 | P61: =O61/6 -> 164 | Q61: 45826 | R61: =DATE(2025,6,22)-Q61 -> 4 | S61: =G61*F61 -> 2082.2
A62: SKU-055 | B62: Pasta Dental 90g | C62: Higiene Personal | D62: PRV-027 | E62: Colgate-Palmolive AR | F62: 2.4 | G62: 20 | H62: 77 | I62: 227 | J62: 274 | K62: 334 | L62: 380 | M62: 288 | N62: 340 | O62: =SUM(I62:N62) -> 1843 | P62: =O62/6 -> 307.16667 | Q62: 45809 | R62: =DATE(2025,6,22)-Q62 -> 21 | S62: =G62*F62 -> 48
A63: SKU-056 | B63: Pasta Dental 150g | C63: Higiene Personal | D63: PRV-027 | E63: Colgate-Palmolive AR | F63: 3.8 | G63: 230 | H63: 21 | I63: 82 | J63: 119 | K63: 124 | L63: 110 | M63: 83 | N63: 131 | O63: =SUM(I63:N63) -> 649 | P63: =O63/6 -> 108.16667 | Q63: 45816 | R63: =DATE(2025,6,22)-Q63 -> 14 | S63: =G63*F63 -> 874
A64: SKU-057 | B64: Cepillo de Dientes x2 | C64: Higiene Personal | D64: PRV-028 | E64: Oral-B Argentina | F64: 3.6 | G64: 678 | H64: 35 | I64: 105 | J64: 148 | K64: 101 | L64: 131 | M64: 136 | N64: 132 | O64: =SUM(I64:N64) -> 753 | P64: =O64/6 -> 125.5 | Q64: 45815 | R64: =DATE(2025,6,22)-Q64 -> 15 | S64: =G64*F64 -> 2440.8
A65: SKU-058 | B65: Desodorante Roll-On 65ml | C65: Higiene Personal | D65: PRV-029 | E65: Unilever Argentina | F65: 3.9 | G65: 139 | H65: 18 | I65: 78 | J65: 91 | K65: 101 | L65: 70 | M65: 94 | N65: 82 | O65: =SUM(I65:N65) -> 516 | P65: =O65/6 -> 86 | Q65: 45806 | R65: =DATE(2025,6,22)-Q65 -> 24 | S65: =G65*F65 -> 542.1
A66: SKU-059 | B66: Desodorante Aerosol 150ml | C66: Higiene Personal | D66: PRV-029 | E66: Unilever Argentina | F66: 5.2 | G66: 194 | H66: 27 | I66: 100 | J66: 95 | K66: 136 | L66: 97 | M66: 107 | N66: 125 | O66: =SUM(I66:N66) -> 660 | P66: =O66/6 -> 110 | Q66: 45819 | R66: =DATE(2025,6,22)-Q66 -> 11 | S66: =G66*F66 -> 1008.8
A67: SKU-060 | B67: Crema Corporal 200ml | C67: Higiene Personal | D67: PRV-030 | E67: Nivea Argentina | F67: 6.4 | G67: 7 | H67: 5 | I67: 5 | J67: 4 | K67: 5 | L67: 4 | M67: 4 | N67: 4 | O67: =SUM(I67:N67) -> 26 | P67: =O67/6 -> 4.3333333 | Q67: 45778 | R67: =DATE(2025,6,22)-Q67 -> 52 | S67: =G67*F67 -> 44.8
A68: SKU-061 | B68: Crema de Manos 100ml | C68: Higiene Personal | D68: PRV-030 | E68: Nivea Argentina | F68: 3.8 | G68: 205 | H68: 5 | I68: 3 | J68: 0 | K68: 0 | L68: 2 | M68: 1 | N68: 3 | O68: =SUM(I68:N68) -> 9 | P68: =O68/6 -> 1.5 | Q68: 45749 | R68: =DATE(2025,6,22)-Q68 -> 81 | S68: =G68*F68 -> 779
A69: SKU-062 | B69: Protector Solar FPS50 150ml | C69: Higiene Personal | D69: PRV-031 | E69: Suncare Labs S.A. | F69: 8.9 | G69: 175 | H69: 26 | I69: 135 | J69: 139 | K69: 131 | L69: 155 | M69: 124 | N69: 152 | O69: =SUM(I69:N69) -> 836 | P69: =O69/6 -> 139.33333 | Q69: 45826 | R69: =DATE(2025,6,22)-Q69 -> 4 | S69: =G69*F69 -> 1557.5
... A82: SKU-075 | B82: Repuestos Maquinilla x4 | C82: Higiene Personal | D82: PRV-037 | E82: Gillette Argentina | F82: 9.8 | G82: 206 | H82: 5 | I82: 2 | J82: 3 | K82: 0 | L82: 3 | M82: 0 | N82: 2 | O82: =SUM(I82:N82) -> 10 | P82: =O82/6 -> 1.6666667 | Q82: 45761 | R82: =DATE(2025,6,22)-Q82 -> 69 | S82: =G82*F82 -> 2018.8
A83: TOTALES | I83: =SUM(I5:I82) -> 8141 | J83: =SUM(J5:J82) -> 8507 | K83: =SUM(K5:K82) -> 8406 | L83: =SUM(L5:L82) -> 7999 | M83: =SUM(M5:M82) -> 7879 | N83: =SUM(N5:N82) -> 8391 | O83: =SUM(O5:O82) -> 49323 | P83: =O83/6 -> 8220.5 | S83: =SUM(S5:S82) -> 64825.2
A85: LEYENDA DE COLORES:
C86: Texto azul | D86: Datos de entrada (editables por el usuario)
C87: Texto negro | D87: Fórmulas calculadas automáticamente

Sheet Análisis
A1: ANÁLISIS DE INVENTARIO — KPIs Y CLASIFICACIÓN
A2: Motor de cálculo automático · Todos los valores se actualizan al modificar Base_Datos · Fórmulas referenciadas en verde
A4: SKU ID | B4: Descripción | C4: Categoría | D4: Stock Actual | E4: Venta Prom. Mensual | F4: Días de Cobertura | G4: Índice de Rotación (x/mes) | H4: Capital Inmovilizado | I4: Stock Mínimo | J4: Días sin Movimiento | K4: Estado Cobertura | L4: Alerta Quiebre | M4: Clasif. ABC | N4: % sobre Total Ventas | O4: Acción Recomendada | P4: Prioridad
A5: =Base_Datos!A6 -> SKU-001 | B5: =Base_Datos!B6 -> Arroz Largo Fino 1kg | C5: =Base_Datos!C6 -> Alimentos Secos | D5: =Base_Datos!G6 -> 64 | E5: =Base_Datos!P6 -> 68.166667 | F5: =IFERROR(Base_Datos!G6/(Base_Datos!P6/30),9999) -> 28.166259 | G5: =IFERROR(Base_Datos!O6/Base_Datos!G6,0) -> 6.390625 | H5: =Base_Datos!S6 -> 204.8 | I5: =Base_Datos!H6 -> 14 | J5: =Base_Datos!R6 -> 1 | K5: =IF(IFERROR(Base_Datos!G6/(Base_Datos!P6/30),9999)<7,"🔴 QUIEBRE",IF(IFERROR(Base_Datos!G6/(Base_Datos!P6/30),9999)<14,"🟡 CRÍTICO",IF(IFERROR(Base_Datos!G6/(Base_Datos!P6/30),9999)<=90,"🟢 NORMAL",IF(IFERROR(Base_Datos!G6/(Base_Datos!P6/30),9999)<=180,"🟡 SOBRESTOCK","🔴 STOCK MUERTO")))) -> 🟢 NORMAL | L5: =IF(F5<7,"⚠ SÍ","—") -> — | M5: =IF(E5>=PERCENTILE($E$5:$E$79,0.8),"A",IF(E5>=PERCENTILE($E$5:$E$79,0.5),"B","C")) -> C | N5: =IFERROR(Base_Datos!O6/Base_Datos!O83,0) -> 0.0082922774 | O5: =IF(F5<7,"REPOSICIÓN URGENTE",IF(F5<14,"Revisar orden de compra",IF(AND(F5>180,J5>60),"LIQUIDAR / DEVOLVER",IF(F5>90,"Reducir próxima compra","Stock en niveles óptimos")))) -> Stock en niveles óptimos | P5: =IF(F5<7,1,IF(AND(F5>180,J5>60),2,IF(F5<14,3,IF(F5>90,4,5)))) -> 5
A6: =Base_Datos!A7 -> SKU-002 | B6: =Base_Datos!B7 -> Arroz Largo Fino 5kg | C6: =Base_Datos!C7 -> Alimentos Secos | D6: =Base_Datos!G7 -> 69 | E6: =Base_Datos!P7 -> 59.166667 | F6: =IFERROR(Base_Datos!G7/(Base_Datos!P7/30),9999) -> 34.985915 | G6: =IFERROR(Base_Datos!O7/Base_Datos!G7,0) -> 5.1449275 | H6: =Base_Datos!S7 -> 1000.5 | I6: =Base_Datos!H7 -> 14 | J6: =Base_Datos!R7 -> 26 | K6: =IF(IFERROR(Base_Datos!G7/(Base_Datos!P7/30),9999)<7,"🔴 QUIEBRE",IF(IFERROR(Base_Datos!G7/(Base_Datos!P7/30),9999)<14,"🟡 CRÍTICO",IF(IFERROR(Base_Datos!G7/(Base_Datos!P7/30),9999)<=90,"🟢 NORMAL",IF(IFERROR(Base_Datos!G7/(Base_Datos!P7/30),9999)<=180,"🟡 SOBRESTOCK","🔴 STOCK MUERTO")))) -> 🟢 NORMAL | L6: =IF(F6<7,"⚠ SÍ","—") -> — | M6: =IF(E6>=PERCENTILE($E$5:$E$79,0.8),"A",IF(E6>=PERCENTILE($E$5:$E$79,0.5),"B","C")) -> C | N6: =IFERROR(Base_Datos!O7/Base_Datos!O83,0) -> 0.0071974535 | O6: =IF(F6<7,"REPOSICIÓN URGENTE",IF(F6<14,"Revisar orden de compra",IF(AND(F6>180,J6>60),"LIQUIDAR / DEVOLVER",IF(F6>90,"Reducir próxima compra","Stock en niveles óptimos")))) -> Stock en niveles óptimos | P6: =IF(F6<7,1,IF(AND(F6>180,J6>60),2,IF(F6<14,3,IF(F6>90,4,5)))) -> 5
A7: =Base_Datos!A8 -> SKU-003 | B7: =Base_Datos!B8 -> Fideos Spaghetti 500g | C7: =Base_Datos!C8 -> Alimentos Secos | D7: =Base_Datos!G8 -> 190 | E7: =Base_Datos!P8 -> 40 | F7: =IFERROR(Base_Datos!G8/(Base_Datos!P8/30),9999) -> 142.5 | G7: =IFERROR(Base_Datos!O8/Base_Datos!G8,0) -> 1.2631579 | H7: =Base_Datos!S8 -> 342 | I7: =Base_Datos!H8 -> 8 | J7: =Base_Datos!R8 -> 12 | K7: =IF(IFERROR(Base_Datos!G8/(Base_Datos!P8/30),9999)<7,"🔴 QUIEBRE",IF(IFERROR(Base_Datos!G8/(Base_Datos!P8/30),9999)<14,"🟡 CRÍTICO",IF(IFERROR(Base_Datos!G8/(Base_Datos!P8/30),9999)<=90,"🟢 NORMAL",IF(IFERROR(Base_Datos!G8/(Base_Datos!P8/30),9999)<=180,"🟡 SOBRESTOCK","🔴 STOCK MUERTO")))) -> 🟡 SOBRESTOCK | L7: =IF(F7<7,"⚠ SÍ","—") -> — | M7: =IF(E7>=PERCENTILE($E$5:$E$79,0.8),"A",IF(E7>=PERCENTILE($E$5:$E$79,0.5),"B","C")) -> C | N7: =IFERROR(Base_Datos!O8/Base_Datos!O83,0) -> 0.0048658841 | O7: =IF(F7<7,"REPOSICIÓN URGENTE",IF(F7<14,"Revisar orden de compra",IF(AND(F7>180,J7>60),"LIQUIDAR / DEVOLVER",IF(F7>90,"Reducir próxima compra","Stock en niveles óptimos")))) -> Reducir próxima compra | P7: =IF(F7<7,1,IF(AND(F7>180,J7>60),2,IF(F7<14,3,IF(F7>90,4,5)))) -> 4
A8: =Base_Datos!A9 -> SKU-004 | B8: =Base_Datos!B9 -> Fideos Moño 500g | C8: =Base_Datos!C9 -> Alimentos Secos | D8: =Base_Datos!G9 -> 248 | E8: =Base_Datos!P9 -> 142.66667 | F8: =IFERROR(Base_Datos!G9/(Base_Datos!P9/30),9999) -> 52.149533 | G8: =IFERROR(Base_Datos!O9/Base_Datos!G9,0) -> 3.4516129 | H8: =Base_Datos!S9 -> 446.4 | I8: =Base_Datos!H9 -> 39 | J8: =Base_Datos!R9 -> 20 | K8: =IF(IFERROR(Base_Datos!G9/(Base_Datos!P9/30),9999)<7,"🔴 QUIEBRE",IF(IFERROR(Base_Datos!G9/(Base_Datos!P9/30),9999)<14,"🟡 CRÍTICO",IF(IFERROR(Base_Datos!G9/(Base_Datos!P9/30),9999)<=90,"🟢 NORMAL",IF(IFERROR(Base_Datos!G9/(Base_Datos!P9/30),9999)<=180,"🟡 SOBRESTOCK","🔴 STOCK MUERTO")))) -> 🟢 NORMAL | L8: =IF(F8<7,"⚠ SÍ","—") -> — | M8: =IF(E8>=PERCENTILE($E$5:$E$79,0.8),"A",IF(E8>=PERCENTILE($E$5:$E$79,0.5),"B","C")) -> B | N8: =IFERROR(Base_Datos!O9/Base_Datos!O83,0) -> 0.017354987 | O8: =IF(F8<7,"REPOSICIÓN URGENTE",IF(F8<14,"Revisar orden de compra",IF(AND(F8>180,J8>60),"LIQUIDAR / DEVOLVER",IF(F8>90,"Reducir próxima compra","Stock en niveles óptimos")))) -> Stock en niveles óptimos | P8: =IF(F8<7,1,IF(AND(F8>180,J8>60),2,IF(F8<14,3,IF(F8>90,4,5)))) -> 5
A9: =Base_Datos!A10 -> SKU-005 | B9: =Base_Datos!B10 -> Harina 000 1kg | C9: =Base_Datos!C10 -> Alimentos Secos | D9: =Base_Datos!G10 -> 24 | E9: =Base_Datos!P10 -> 374.83333 | F9: =IFERROR(Base_Datos!G10/(Base_Datos!P10/30),9999) -> 1.9208537 | G9: =IFERROR(Base_Datos!O10/Base_Datos!G10,0) -> 93.708333 | H9: =Base_Datos!S10 -> 36 | I9: =Base_Datos!H10 -> 69 | J9: =Base_Datos!R10 -> 4 | K9: =IF(IFERROR(Base_Datos!G10/(Base_Datos!P10/30),9999)<7,"🔴 QUIEBRE",IF(IFERROR(Base_Datos!G10/(Base_Datos!P10/30),9999)<14,"🟡 CRÍTICO",IF(IFERROR(Base_Datos!G10/(Base_Datos!P10/30),9999)<=90,"🟢 NORMAL",IF(IFERROR(Base_Datos!G10/(Base_Datos!P10/30),9999)<=180,"🟡 SOBRESTOCK","🔴 STOCK MUERTO")))) -> 🔴 QUIEBRE | L9: =IF(F9<7,"⚠ SÍ","—") -> ⚠ SÍ | M9: =IF(E9>=PERCENTILE($E$5:$E$79,0.8),"A",IF(E9>=PERCENTILE($E$5:$E$79,0.5),"B","C")) -> A | N9: =IFERROR(Base_Datos!O10/Base_Datos!O83,0) -> 0.045597389 | O9: =IF(F9<7,"REPOSICIÓN URGENTE",IF(F9<14,"Revisar orden de compra",IF(AND(F9>180,J9>60),"LIQUIDAR / DEVOLVER",IF(F9>90,"Reducir próxima compra","Stock en niveles óptimos")))) -> REPOSICIÓN URGENTE | P9: =IF(F9<7,1,IF(AND(F9>180,J9>60),2,IF(F9<14,3,IF(F9>90,4,5)))) -> 1
A10: =Base_Datos!A11 -> SKU-006 | B10: =Base_Datos!B11 -> Harina 0000 1kg | C10: =Base_Datos!C11 -> Alimentos Secos | D10: =Base_Datos!G11 -> 308 | E10: =Base_Datos!P11 -> 128.83333 | F10: =IFERROR(Base_Datos!G11/(Base_Datos!P11/30),9999) -> 71.720569 | G10: =IFERROR(Base_Datos!O11/Base_Datos!G11,0) -> 2.5097403 | H10: =Base_Datos!S11 -> 508.2 | I10: =Base_Datos!H11 -> 31 | J10: =Base_Datos!R11 -> 20 | K10: =IF(IFERROR(Base_Datos!G11/(Base_Datos!P11/30),9999)<7,"🔴 QUIEBRE",IF(IFERROR(Base_Datos!G11/(Base_Datos!P11/30),9999)<14,"🟡 CRÍTICO",IF(IFERROR(Base_Datos!G11/(Base_Datos!P11/30),9999)<=90,"🟢 NORMAL",IF(IFERROR(Base_Datos!G11/(Base_Datos!P11/30),9999)<=180,"🟡 SOBRESTOCK","🔴 STOCK MUERTO")))) -> 🟢 NORMAL | L10: =IF(F10<7,"⚠ SÍ","—") -> — | M10: =IF(E10>=PERCENTILE($E$5:$E$79,0.8),"A",IF(E10>=PERCENTILE($E$5:$E$79,0.5),"B","C")) -> B | N10: =IFERROR(Base_Datos!O11/Base_Datos!O83,0) -> 0.015672202 | O10: =IF(F10<7,"REPOSICIÓN URGENTE",IF(F10<14,"Revisar orden de compra",IF(AND(F10>180,J10>60),"LIQUIDAR / DEVOLVER",IF(F10>90,"Reducir próxima compra","Stock en niveles óptimos")))) -> Stock en niveles óptimos | P10: =IF(F10<7,1,IF(AND(F10>180,J10>60),2,IF(F10<14,3,IF(F10>90,4,5)))) -> 5
A11: =Base_Datos!A12 -> SKU-007 | B11: =Base_Datos!B12 -> Azúcar Blanca 1kg | C11: =Base_Datos!C12 -> Alimentos Secos | D11: =Base_Datos!G12 -> 43 | E11: =Base_Datos!P12 -> 25.166667 | F11: =IFERROR(Base_Datos!G12/(Base_Datos!P12/30),9999) -> 51.258278 | G11: =IFERROR(Base_Datos!O12/Base_Datos!G12,0) -> 3.5116279 | H11: =Base_Datos!S12 -> 60.2 | I11: =Base_Datos!H12 -> 6 | J11: =Base_Datos!R12 -> 59 | K11: =IF(IFERROR(Base_Datos!G12/(Base_Datos!P12/30),9999)<7,"🔴 QUIEBRE",IF(IFERROR(Base_Datos!G12/(Base_Datos!P12/30),9999)<14,"🟡 CRÍTICO",IF(IFERROR(Base_Datos!G12/(Base_Datos!P12/30),9999)<=90,"🟢 NORMAL",IF(IFERROR(Base_Datos!G12/(Base_Datos!P12/30),9999)<=180,"🟡 SOBRESTOCK","🔴 STOCK MUERTO")))) -> 🟢 NORMAL | L11: =IF(F11<7,"⚠ SÍ","—") -> — | M11: =IF(E11>=PERCENTILE($E$5:$E$79,0.8),"A",IF(E11>=PERCENTILE($E$5:$E$79,0.5),"B","C")) -> C | N11: =IFERROR(Base_Datos!O12/Base_Datos!O83,0) -> 0.0030614521 | O11: =IF(F11<7,"REPOSICIÓN URGENTE",IF(F11<14,"Revisar orden de compra",IF(AND(F11>180,J11>60),"LIQUIDAR / DEVOLVER",IF(F11>90,"Reducir próxima compra","Stock en niveles óptimos")))) -> Stock en niveles óptimos | P11: =IF(F11<7,1,IF(AND(F11>180,J11>60),2,IF(F11<14,3,IF(F11>90,4,5)))) -> 5
A12: =Base_Datos!A13 -> SKU-008 | B12: =Base_Datos!B13 -> Azúcar Morena 1kg | C12: =Base_Datos!C13 -> Alimentos Secos | D12: =Base_Datos!G13 -> 333 | E12: =Base_Datos!P13 -> 49.833333 | F12: =IFERROR(Base_Datos!G13/(Base_Datos!P13/30),9999) -> 200.46823 | G12: =IFERROR(Base_Datos!O13/Base_Datos!G13,0) -> 0.8978979 | H12: =Base_Datos!S13 -> 532.8 | I12: =Base_Datos!H13 -> 9 | J12: =Base_Datos!R13 -> 21 | K12: =IF(IFERROR(Base_Datos!G13/(Base_Datos!P13/30),9999)<7,"🔴 QUIEBRE",IF(IFERROR(Base_Datos!G13/(Base_Datos!P13/30),9999)<14,"🟡 CRÍTICO",IF(IFERROR(Base_Datos!G13/(Base_Datos!P13/30),9999)<=90,"🟢 NORMAL",IF(IFERROR(Base_Datos!G13/(Base_Datos!P13/30),9999)<=180,"🟡 SOBRESTOCK","🔴 STOCK MUERTO")))) -> 🔴 STOCK MUERTO | L12: =IF(F12<7,"⚠ SÍ","—") -> — | M12: =IF(E12>=PERCENTILE($E$5:$E$79,0.8),"A",IF(E12>=PERCENTILE($E$5:$E$79,0.5),"B","C")) -> C | N12: =IFERROR(Base_Datos!O13/Base_Datos!O83,0) -> 0.0060620806 | O12: =IF(F12<7,"REPOSICIÓN URGENTE",IF(F12<14,"Revisar orden de compra",IF(AND(F12>180,J12>60),"LIQUIDAR / DEVOLVER",IF(F12>90,"Reducir próxima compra","Stock en niveles óptimos")))) -> Reducir próxima compra | P12: =IF(F12<7,1,IF(AND(F12>180,J12>60),2,IF(F12<14,3,IF(F12>90,4,5)))) -> 4
A13: =Base_Datos!A14 -> SKU-009 | B13: =Base_Datos!B14 -> Aceite de Girasol 900cc | C13: =Base_Datos!C14 -> Alimentos Secos | D13: =Base_Datos!G14 -> 209 | E13: =Base_Datos!P14 -> 168.16667 | F13: =IFERROR(Base_Datos!G14/(Base_Datos!P14/30),9999) -> 37.28444 | G13: =IFERROR(Base_Datos!O14/Base_Datos!G14,0) -> 4.8277512 | H13: =Base_Datos!S14 -> 606.1 | I13: =Base_Datos!H14 -> 39 | J13: =Base_Datos!R14 -> 29 | K13: =IF(IFERROR(Base_Datos!G14/(Base_Datos!P14/30),9999)<7,"🔴 QUIEBRE",IF(IFERROR(Base_Datos!G14/(Base_Datos!P14/30),9999)<14,"🟡 CRÍTICO",IF(IFERROR(Base_Datos!G14/(Base_Datos!P14/30),9999)<=90,"🟢 NORMAL",IF(IFERROR(Base_Datos!G14/(Base_Datos!P14/30),9999)<=180,"🟡 SOBRESTOCK","🔴 STOCK MUERTO")))) -> 🟢 NORMAL | L13: =IF(F13<7,"⚠ SÍ","—") -> — | M13: =IF(E13>=PERCENTILE($E$5:$E$79,0.8),"A",IF(E13>=PERCENTILE($E$5:$E$79,0.5),"B","C")) -> A | N13: =IFERROR(Base_Datos!O14/Base_Datos!O83,0) -> 0.020456988 | O13: =IF(F13<7,"REPOSICIÓN URGENTE",IF(F13<14,"Revisar orden de compra",IF(AND(F13>180,J13>60),"LIQUIDAR / DEVOLVER",IF(F13>90,"Reducir próxima compra","Stock en niveles óptimos")))) -> Stock en niveles óptimos | P13: =IF(F13<7,1,IF(AND(F13>180,J13>60),2,IF(F13<14,3,IF(F13>90,4,5)))) -> 5
A14: =Base_Datos!A15 -> SKU-010 | B14: =Base_Datos!B15 -> Aceite de Girasol 1.8L | C14: =Base_Datos!C15 -> Alimentos Secos | D14: =Base_Datos!G15 -> 162 | E14: =Base_Datos!P15 -> 153 | F14: =IFERROR(Base_Datos!G15/(Base_Datos!P15/30),9999) -> 31.764706 | G14: =IFERROR(Base_Datos!O15/Base_Datos!G15,0) -> 5.6666667 | H14: =Base_Datos!S15 -> 891 | I14: =Base_Datos!H15 -> 26 | J14: =Base_Datos!R15 -> 22 | K14: =IF(IFERROR(Base_Datos!G15/(Base_Datos!P15/30),9999)<7,"🔴 QUIEBRE",IF(IFERROR(Base_Datos!G15/(Base_Datos!P15/30),9999)<14,"🟡 CRÍTICO",IF(IFERROR(Base_Datos!G15/(Base_Datos!P15/30),9999)<=90,"🟢 NORMAL",IF(IFERROR(Base_Datos!G15/(Base_Datos!P15/30),9999)<=180,"🟡 SOBRESTOCK","🔴 STOCK MUERTO")))) -> 🟢 NORMAL | L14: =IF(F14<7,"⚠ SÍ","—") -> — | M14: =IF(E14>=PERCENTILE($E$5:$E$79,0.8),"A",IF(E14>=PERCENTILE($E$5:$E$79,0.5),"B","C")) -> B | N14: =IFERROR(Base_Datos!O15/Base_Datos!O83,0) -> 0.018612007 | O14: =IF(F14<7,"REPOSICIÓN URGENTE",IF(F14<14,"Revisar orden de compra",IF(AND(F14>180,J14>60),"LIQUIDAR / DEVOLVER",IF(F14>90,"Reducir próxima compra","Stock en niveles óptimos")))) -> Stock en niveles óptimos | P14: =IF(F14<7,1,IF(AND(F14>180,J14>60),2,IF(F14<14,3,IF(F14>90,4,5)))) -> 5
A15: =Base_Datos!A16 -> SKU-011 | B15: =Base_Datos!B16 -> Aceite de Maíz 900cc | C15: =Base_Datos!C16 -> Alimentos Secos | D15: =Base_Datos!G16 -> 109 | E15: =Base_Datos!P16 -> 1.6666667 | F15: =IFERROR(Base_Datos!G16/(Base_Datos!P16/30),9999) -> 1962 | G15: =IFERROR(Base_Datos!O16/Base_Datos!G16,0) -> 0.091743119 | H15: =Base_Datos!S16 -> 348.8 | I15: =Base_Datos!H16 -> 5 | J15: =Base_Datos!R16 -> 108 | K15: =IF(IFERROR(Base_Datos!G16/(Base_Datos!P16/30),9999)<7,"🔴 QUIEBRE",IF(IFERROR(Base_Datos!G16/(Base_Datos!P16/30),9999)<14,"🟡 CRÍTICO",IF(IFERROR(Base_Datos!G16/(Base_Datos!P16/30),9999)<=90,"🟢 NORMAL",IF(IFERROR(Base_Datos!G16/(Base_Datos!P16/30),9999)<=180,"🟡 SOBRESTOCK","🔴 STOCK MUERTO")))) -> 🔴 STOCK MUERTO | L15: =IF(F15<7,"⚠ SÍ","—") -> — | M15: =IF(E15>=PERCENTILE($E$5:$E$79,0.8),"A",IF(E15>=PERCENTILE($E$5:$E$79,0.5),"B","C")) -> C | N15: =IFERROR(Base_Datos!O16/Base_Datos!O83,0) -> 0.00020274517 | O15: =IF(F15<7,"REPOSICIÓN URGENTE",IF(F15<14,"Revisar orden de compra",IF(AND(F15>180,J15>60),"LIQUIDAR / DEVOLVER",IF(F15>90,"Reducir próxima compra","Stock en niveles óptimos")))) -> LIQUIDAR / DEVOLVER | P15: =IF(F15<7,1,IF(AND(F15>180,J15>60),2,IF(F15<14,3,IF(F15>90,4,5)))) -> 2
A16: =Base_Datos!A17 -> SKU-012 | B16: =Base_Datos!B17 -> Sal Fina 1kg | C16: =Base_Datos!C17 -> Alimentos Secos | D16: =Base_Datos!G17 -> 88 | E16: =Base_Datos!P17 -> 406.66667 | F16: =IFERROR(Base_Datos!G17/(Base_Datos!P17/30),9999) -> 6.4918033 | G16: =IFERROR(Base_Datos!O17/Base_Datos!G17,0) -> 27.727273 | H16: =Base_Datos!S17 -> 74.8 | I16: =Base_Datos!H17 -> 91 | J16: =Base_Datos!R17 -> 7 | K16: =IF(IFERROR(Base_Datos!G17/(Base_Datos!P17/30),9999)<7,"🔴 QUIEBRE",IF(IFERROR(Base_Datos!G17/(Base_Datos!P17/30),9999)<14,"🟡 CRÍTICO",IF(IFERROR(Base_Datos!G17/(Base_Datos!P17/30),9999)<=90,"🟢 NORMAL",IF(IFERROR(Base_Datos!G17/(Base_Datos!P17/30),9999)<=180,"🟡 SOBRESTOCK","🔴 STOCK MUERTO")))) -> 🔴 QUIEBRE | L16: =IF(F16<7,"⚠ SÍ","—") -> ⚠ SÍ | M16: =IF(E16>=PERCENTILE($E$5:$E$79,0.8),"A",IF(E16>=PERCENTILE($E$5:$E$79,0.5),"B","C")) -> A | N16: =IFERROR(Base_Datos!O17/Base_Datos!O83,0) -> 0.049469821 | O16: =IF(F16<7,"REPOSICIÓN URGENTE",IF(F16<14,"Revisar orden de compra",IF(AND(F16>180,J16>60),"LIQUIDAR / DEVOLVER",IF(F16>90,"Reducir próxima compra","Stock en niveles óptimos")))) -> REPOSICIÓN URGENTE | P16: =IF(F16<7,1,IF(AND(F16>180,J16>60),2,IF(F16<14,3,IF(F16>90,4,5)))) -> 1
A17: =Base_Datos!A18 -> SKU-013 | B17: =Base_Datos!B18 -> Sal Gruesa 1kg | C17: =Base_Datos!C18 -> Alimentos Secos | D17: =Base_Datos!G18 -> 142 | E17: =Base_Datos!P18 -> 87.333333 | F17: =IFERROR(Base_Datos!G18/(Base_Datos!P18/30),9999) -> 48.778626 | G17: =IFERROR(Base_Datos!O18/Base_Datos!G18,0) -> 3.6901408 | H17: =Base_Datos!S18 -> 113.6 | I17: =Base_Datos!H18 -> 14 | J17: =Base_Datos!R18 -> 12 | K17: =IF(IFERROR(Base_Datos!G18/(Base_Datos!P18/30),9999)<7,"🔴 QUIEBRE",IF(IFERROR(Base_Datos!G18/(Base_Datos!P18/30),9999)<14,"🟡 CRÍTICO",IF(IFERROR(Base_Datos!G18/(Base_Datos!P18/30),9999)<=90,"🟢 NORMAL",IF(IFERROR(Base_Datos!G18/(Base_Datos!P18/30),9999)<=180,"🟡 SOBRESTOCK","🔴 STOCK MUERTO")))) -> 🟢 NORMAL | L17: =IF(F17<7,"⚠ SÍ","—") -> — | M17: =IF(E17>=PERCENTILE($E$5:$E$79,0.8),"A",IF(E17>=PERCENTILE($E$5:$E$79,0.5),"B","C")) -> C | N17: =IFERROR(Base_Datos!O18/Base_Datos!O83,0) -> 0.010623847 | O17: =IF(F17<7,"REPOSICIÓN URGENTE",IF(F17<14,"Revisar orden de compra",IF(AND(F17>180,J17>60),"LIQUIDAR / DEVOLVER",IF(F17>90,"Reducir próxima compra","Stock en niveles óptimos")))) -> Stock en niveles óptimos | P17: =IF(F17<7,1,IF(AND(F17>180,J17>60),2,IF(F17<14,3,IF(F17>90,4,5)))) -> 5
A18: =Base_Datos!A19 -> SKU-014 | B18: =Base_Datos!B19 -> Yerba Mate 500g | C18: =Base_Datos!C19 -> Alimentos Secos | D18: =Base_Datos!G19 -> 288 | E18: =Base_Datos!P19 -> 117.16667 | F18: =IFERROR(Base_Datos!G19/(Base_Datos!P19/30),9999) -> 73.74111 | G18: =IFERROR(Base_Datos!O19/Base_Datos!G19,0) -> 2.4409722 | H18: =Base_Datos!S19 -> 1094.4 | I18: =Base_Datos!H19 -> 26 | J18: =Base_Datos!R19 -> 5 | K18: =IF(IFERROR(Base_Datos!G19/(Base_Datos!P19/30),9999)<7,"🔴 QUIEBRE",IF(IFERROR(Base_Datos!G19/(Base_Datos!P19/30),9999)<14,"🟡 CRÍTICO",IF(IFERROR(Base_Datos!G19/(Base_Datos!P19/30),9999)<=90,"🟢 NORMAL",IF(IFERROR(Base_Datos!G19/(Base_Datos!P19/30),9999)<=180,"🟡 SOBRESTOCK","🔴 STOCK MUERTO")))) -> 🟢 NORMAL | L18: =IF(F18<7,"⚠ SÍ","—") -> — | M18: =IF(E18>=PERCENTILE($E$5:$E$79,0.8),"A",IF(E18>=PERCENTILE($E$5:$E$79,0.5),"B","C")) -> B | N18: =IFERROR(Base_Datos!O19/Base_Datos!O83,0) -> 0.014252985 | O18: =IF(F18<7,"REPOSICIÓN URGENTE",IF(F18<14,"Revisar orden de compra",IF(AND(F18>180,J18>60),"LIQUIDAR / DEVOLVER",IF(F18>90,"Reducir próxima compra","Stock en niveles óptimos")))) -> Stock en niveles óptimos | P18: =IF(F18<7,1,IF(AND(F18>180,J18>60),2,IF(F18<14,3,IF(F18>90,4,5)))) -> 5
A19: =Base_Datos!A20 -> SKU-015 | B19: =Base_Datos!B20 -> Yerba Mate 1kg | C19: =Base_Datos!C20 -> Alimentos Secos | D19: =Base_Datos!G20 -> 540 | E19: =Base_Datos!P20 -> 79.166667 | F19: =IFERROR(Base_Datos!G20/(Base_Datos!P20/30),9999) -> 204.63158 | G19: =IFERROR(Base_Datos!O20/Base_Datos!G20,0) -> 0.87962963 | H19: =Base_Datos!S20 -> 3888 | I19: =Base_Datos!H20 -> 20 | J19: =Base_Datos!R20 -> 23 | K19: =IF(IFERROR(Base_Datos!G20/(Base_Datos!P20/30),9999)<7,"🔴 QUIEBRE",IF(IFERROR(Base_Datos!G20/(Base_Datos!P20/30),9999)<14,"🟡 CRÍTICO",IF(IFERROR(Base_Datos!G20/(Base_Datos!P20/30),9999)<=90,"🟢 NORMAL",IF(IFERROR(Base_Datos!G20/(Base_Datos!P20/30),9999)<=180,"🟡 SOBRESTOCK","🔴 STOCK MUERTO")))) -> 🔴 STOCK MUERTO | L19: =IF(F19<7,"⚠ SÍ","—") -> — | M19: =IF(E19>=PERCENTILE($E$5:$E$79,0.8),"A",IF(E19>=PERCENTILE($E$5:$E$79,0.5),"B","C")) -> C | N19: =IFERROR(Base_Datos!O20/Base_Datos!O83,0) -> 0.0096303956 | O19: =IF(F19<7,"REPOSICIÓN URGENTE",IF(F19<14,"Revisar orden de compra",IF(AND(F19>180,J19>60),"LIQUIDAR / DEVOLVER",IF(F19>90,"Reducir próxima compra","Stock en niveles óptimos")))) -> Reducir próxima compra | P19: =IF(F19<7,1,IF(AND(F19>180,J19>60),2,IF(F19<14,3,IF(F19>90,4,5)))) -> 4
A20: =Base_Datos!A21 -> SKU-016 | B20: =Base_Datos!B21 -> Café Molido 250g | C20: =Base_Datos!C21 -> Alimentos Secos | D20: =Base_Datos!G21 -> 13 | E20: =Base_Datos!P21 -> 11.166667 | F20: =IFERROR(Base_Datos!G21/(Base_Datos!P21/30),9999) -> 34.925373 | G20: =IFERROR(Base_Datos!O21/Base_Datos!G21,0) -> 5.1538462 | H20: =Base_Datos!S21 -> 58.5 | I20: =Base_Datos!H21 -> 5 | J20: =Base_Datos!R21 -> 35 | K20: =IF(IFERROR(Base_Datos!G21/(Base_Datos!P21/30),9999)<7,"🔴 QUIEBRE",IF(IFERROR(Base_Datos!G21/(Base_Datos!P21/30),9999)<14,"🟡 CRÍTICO",IF(IFERROR(Base_Datos!G21/(Base_Datos!P21/30),9999)<=90,"🟢 NORMAL",IF(IFERROR(Base_Datos!G21/(Base_Datos!P21/30),9999)<=180,"🟡 SOBRESTOCK","🔴 STOCK MUERTO")))) -> 🟢 NORMAL | L20: =IF(F20<7,"⚠ SÍ","—") -> — | M20: =IF(E20>=PERCENTILE($E$5:$E$79,0.8),"A",IF(E20>=PERCENTILE($E$5:$E$79,0.5),"B","C")) -> C | N20: =IFERROR(Base_Datos!O21/Base_Datos!O83,0) -> 0.0013583926 | O20: =IF(F20<7,"REPOSICIÓN URGENTE",IF(F20<14,"Revisar orden de compra",IF(AND(F20>180,J20>60),"LIQUIDAR / DEVOLVER",IF(F20>90,"Reducir próxima compra","Stock en niveles óptimos")))) -> Stock en niveles óptimos | P20: =IF(F20<7,1,IF(AND(F20>180,J20>60),2,IF(F20<14,3,IF(F20>90,4,5)))) -> 5
A21: =Base_Datos!A22 -> SKU-017 | B21: =Base_Datos!B22 -> Té en Saquitos x20 | C21: =Base_Datos!C22 -> Alimentos Secos | D21: =Base_Datos!G22 -> 117 | E21: =Base_Datos!P22 -> 86.166667 | F21: =IFERROR(Base_Datos!G22/(Base_Datos!P22/30),9999) -> 40.73501 | G21: =IFERROR(Base_Datos!O22/Base_Datos!G22,0) -> 4.4188034 | H21: =Base_Datos!S22 -> 245.7 | I21: =Base_Datos!H22 -> 19 | J21: =Base_Datos!R22 -> 9 | K21: =IF(IFERROR(Base_Datos!G22/(Base_Datos!P22/30),9999)<7,"🔴 QUIEBRE",IF(IFERROR(Base_Datos!G22/(Base_Datos!P22/30),9999)<14,"🟡 CRÍTICO",IF(IFERROR(Base_Datos!G22/(Base_Datos!P22/30),9999)<=90,"🟢 NORMAL",IF(IFERROR(Base_Datos!G22/(Base_Datos!P22/30),9999)<=180,"🟡 SOBRESTOCK","🔴 STOCK MUERTO")))) -> 🟢 NORMAL | L21: =IF(F21<7,"⚠ SÍ","—") -> — | M21: =IF(E21>=PERCENTILE($E$5:$E$79,0.8),"A",IF(E21>=PERCENTILE($E$5:$E$79,0.5),"B","C")) -> C | N21: =IFERROR(Base_Datos!O22/Base_Datos!O83,0) -> 0.010481925 | O21: =IF(F21<7,"REPOSICIÓN URGENTE",IF(F21<14,"Revisar orden de compra",IF(AND(F21>180,J21>60),"LIQUIDAR / DEVOLVER",IF(F21>90,"Reducir próxima compra","Stock en niveles óptimos")))) -> Stock en niveles óptimos | P21: =IF(F21<7,1,IF(AND(F21>180,J21>60),2,IF(F21<14,3,IF(F21>90,4,5)))) -> 5
A22: =Base_Datos!A23 -> SKU-018 | B22: =Base_Datos!B23 -> Galletitas Dulces 200g | C22: =Base_Datos!C23 -> Alimentos Secos | D22: =Base_Datos!G23 -> 367 | E22: =Base_Datos!P23 -> 169.16667 | F22: =IFERROR(Base_Datos!G23/(Base_Datos!P23/30),9999) -> 65.083744 | G22: =IFERROR(Base_Datos!O23/Base_Datos!G23,0) -> 2.7656676 | H22: =Base_Datos!S23 -> 697.3 | I22: =Base_Datos!H23 -> 30 | J22: =Base_Datos!R23 -> 4 | K22: =IF(IFERROR(Base_Datos!G23/(Base_Datos!P23/30),9999)<7,"🔴 QUIEBRE",IF(IFERROR(Base_Datos!G23/(Base_Datos!P23/30),9999)<14,"🟡 CRÍTICO",IF(IFERROR(Base_Datos!G23/(Base_Datos!P23/30),9999)<=90,"🟢 NORMAL",IF(IFERROR(Base_Datos!G23/(Base_Datos!P23/30),9999)<=180,"🟡 SOBRESTOCK","🔴 STOCK MUERTO")))) -> 🟢 NORMAL | L22: =IF(F22<7,"⚠ SÍ","—") -> — | M22: =IF(E22>=PERCENTILE($E$5:$E$79,0.8),"A",IF(E22>=PERCENTILE($E$5:$E$79,0.5),"B","C")) -> A | N22: =IFERROR(Base_Datos!O23/Base_Datos!O83,0) -> 0.020578635 | O22: =IF(F22<7,"REPOSICIÓN URGENTE",IF(F22<14,"Revisar orden de compra",IF(AND(F22>180,J22>60),"LIQUIDAR / DEVOLVER",IF(F22>90,"Reducir próxima compra","Stock en niveles óptimos")))) -> Stock en niveles óptimos | P22: =IF(F22<7,1,IF(AND(F22>180,J22>60),2,IF(F22<14,3,IF(F22>90,4,5)))) -> 5
A23: =Base_Datos!A24 -> SKU-019 | B23: =Base_Datos!B24 -> Galletitas Crackers 200g | C23: =Base_Datos!C24 -> Alimentos Secos | D23: =Base_Datos!G24 -> 710 | E23: =Base_Datos!P24 -> 152.83333 | F23: =IFERROR(Base_Datos!G24/(Base_Datos!P24/30),9999) -> 139.3675 | G23: =IFERROR(Base_Datos!O24/Base_Datos!G24,0) -> 1.2915493 | H23: =Base_Datos!S24 -> 1242.5 | I23: =Base_Datos!H24 -> 39 | J23: =Base_Datos!R24 -> 26 | K23: =IF(IFERROR(Base_Datos!G24/(Base_Datos!P24/30),9999)<7,"🔴 QUIEBRE",IF(IFERROR(Base_Datos!G24/(Base_Datos!P24/30),9999)<14,"🟡 CRÍTICO",IF(IFERROR(Base_Datos!G24/(Base_Datos!P24/30),9999)<=90,"🟢 NORMAL",IF(IFERROR(Base_Datos!G24/(Base_Datos!P24/30),9999)<=180,"🟡 SOBRESTOCK","🔴 STOCK MUERTO")))) -> 🟡 SOBRESTOCK | L23: =IF(F23<7,"⚠ SÍ","—") -> — | M23: =IF(E23>=PERCENTILE($E$5:$E$79,0.8),"A",IF(E23>=PERCENTILE($E$5:$E$79,0.5),"B","C")) -> B | N23: =IFERROR(Base_Datos!O24/Base_Datos!O83,0) -> 0.018591732 | O23: =IF(F23<7,"REPOSICIÓN URGENTE",IF(F23<14,"Revisar orden de compra",IF(AND(F23>180,J23>60),"LIQUIDAR / DEVOLVER",IF(F23>90,"Reducir próxima compra","Stock en niveles óptimos")))) -> Reducir próxima compra | P23: =IF(F23<7,1,IF(AND(F23>180,J23>60),2,IF(F23<14,3,IF(F23>90,4,5)))) -> 4
A24: =Base_Datos!A25 -> SKU-020 | B24: =Base_Datos!B25 -> Puré de Tomate 520g | C24: =Base_Datos!C25 -> Alimentos Secos | D24: =Base_Datos!G25 -> 193 | E24: =Base_Datos!P25 -> 0.33333333 | F24: =IFERROR(Base_Datos!G25/(Base_Datos!P25/30),9999) -> 17370 | G24: =IFERROR(Base_Datos!O25/Base_Datos!G25,0) -> 0.010362694 | H24: =Base_Datos!S25 -> 250.9 | I24: =Base_Datos!H25 -> 5 | J24: =Base_Datos!R25 -> 92 | K24: =IF(IFERROR(Base_Datos!G25/(Base_Datos!P25/30),9999)<7,"🔴 QUIEBRE",IF(IFERROR(Base_Datos!G25/(Base_Datos!P25/30),9999)<14,"🟡 CRÍTICO",IF(IFERROR(Base_Datos!G25/(Base_Datos!P25/30),9999)<=90,"🟢 NORMAL",IF(IFERROR(Base_Datos!G25/(Base_Datos!P25/30),9999)<=180,"🟡 SOBRESTOCK","🔴 STOCK MUERTO")))) -> 🔴 STOCK MUERTO | L24: =IF(F24<7,"⚠ SÍ","—") -> — | M24: =IF(E24>=PERCENTILE($E$5:$E$79,0.8),"A",IF(E24>=PERCENTILE($E$5:$E$79,0.5),"B","C")) -> C | N24: =IFERROR(Base_Datos!O25/Base_Datos!O83,0) -> 4.0549034e-05 | O24: =IF(F24<7,"REPOSICIÓN URGENTE",IF(F24<14,"Revisar orden de compra",IF(AND(F24>180,J24>60),"LIQUIDAR / DEVOLVER",IF(F24>90,"Reducir próxima compra","Stock en niveles óptimos")))) -> LIQUIDAR / DEVOLVER | P24: =IF(F24<7,1,IF(AND(F24>180,J24>60),2,IF(F24<14,3,IF(F24>90,4,5)))) -> 2
A25: =Base_Datos!A26 -> SKU-021 | B25: =Base_Datos!B26 -> Tomate Triturado 400g | C25: =Base_Datos!C26 -> Alimentos Secos | D25: =Base_Datos!G26 -> 209 | E25: =Base_Datos!P26 -> 98.166667 | F25: =IFERROR(Base_Datos!G26/(Base_Datos!P26/30),9999) -> 63.870968 | G25: =IFERROR(Base_Datos!O26/Base_Datos!G26,0) -> 2.8181818 | H25: =Base_Datos!S26 -> 229.9 | I25: =Base_Datos!H26 -> 18 | J25: =Base_Datos!R26 -> 23 | K25: =IF(IFERROR(Base_Datos!G26/(Base_Datos!P26/30),9999)<7,"🔴 QUIEBRE",IF(IFERROR(Base_Datos!G26/(Base_Datos!P26/30),9999)<14,"🟡 CRÍTICO",IF(IFERROR(Base_Datos!G26/(Base_Datos!P26/30),9999)<=90,"🟢 NORMAL",IF(IFERROR(Base_Datos!G26/(Base_Datos!P26/30),9999)<=180,"🟡 SOBRESTOCK","🔴 STOCK MUERTO")))) -> 🟢 NORMAL | L25: =IF(F25<7,"⚠ SÍ","—") -> — | M25: =IF(E25>=PERCENTILE($E$5:$E$79,0.8),"A",IF(E25>=PERCENTILE($E$5:$E$79,0.5),"B","C")) -> B | N25: =IFERROR(Base_Datos!O26/Base_Datos!O83,0) -> 0.01194169 | O25: =IF(F25<7,"REPOSICIÓN URGENTE",IF(F25<14,"Revisar orden de compra",IF(AND(F25>180,J25>60),"LIQUIDAR / DEVOLVER",IF(F25>90,"Reducir próxima compra","Stock en niveles óptimos")))) -> Stock en niveles óptimos | P25: =IF(F25<7,1,IF(AND(F25>180,J25>60),2,IF(F25<14,3,IF(F25>90,4,5)))) -> 5
A26: =Base_Datos!A27 -> SKU-022 | B26: =Base_Datos!B27 -> Mayonesa 500g | C26: =Base_Datos!C27 -> Alimentos Secos | D26: =Base_Datos!G27 -> 25 | E26: =Base_Datos!P27 -> 406.83333 | F26: =IFERROR(Base_Datos!G27/(Base_Datos!P27/30),9999) -> 1.8435068 | G26: =IFERROR(Base_Datos!O27/Base_Datos!G27,0) -> 97.64 | H26: =Base_Datos!S27 -> 85 | I26: =Base_Datos!H27 -> 105 | J26: =Base_Datos!R27 -> 2 | K26: =IF(IFERROR(Base_Datos!G27/(Base_Datos!P27/30),9999)<7,"🔴 QUIEBRE",IF(IFERROR(Base_Datos!G27/(Base_Datos!P27/30),9999)<14,"🟡 CRÍTICO",IF(IFERROR(Base_Datos!G27/(Base_Datos!P27/30),9999)<=90,"🟢 NORMAL",IF(IFERROR(Base_Datos!G27/(Base_Datos!P27/30),9999)<=180,"🟡 SOBRESTOCK","🔴 STOCK MUERTO")))) -> 🔴 QUIEBRE | L26: =IF(F26<7,"⚠ SÍ","—") -> ⚠ SÍ | M26: =IF(E26>=PERCENTILE($E$5:$E$79,0.8),"A",IF(E26>=PERCENTILE($E$5:$E$79,0.5),"B","C")) -> A | N26: =IFERROR(Base_Datos!O27/Base_Datos!O83,0) -> 0.049490096 | O26: =IF(F26<7,"REPOSICIÓN URGENTE",IF(F26<14,"Revisar orden de compra",IF(AND(F26>180,J26>60),"LIQUIDAR / DEVOLVER",IF(F26>90,"Reducir próxima compra","Stock en niveles óptimos")))) -> REPOSICIÓN URGENTE | P26: =IF(F26<7,1,IF(AND(F26>180,J26>60),2,IF(F26<14,3,IF(F26>90,4,5)))) -> 1
A27: =Base_Datos!A28 -> SKU-023 | B27: =Base_Datos!B28 -> Ketchup 400g | C27: =Base_Datos!C28 -> Alimentos Secos | D27: =Base_Datos!G28 -> 115 | E27: =Base_Datos!P28 -> 123.83333 | F27: =IFERROR(Base_Datos!G28/(Base_Datos!P28/30),9999) -> 27.860027 | G27: =IFERROR(Base_Datos!O28/Base_Datos!G28,0) -> 6.4608696 | H27: =Base_Datos!S28 -> 322 | I27: =Base_Datos!H28 -> 22 | J27: =Base_Datos!R28 -> 20 | K27: =IF(IFERROR(Base_Datos!G28/(Base_Datos!P28/30),9999)<7,"🔴 QUIEBRE",IF(IFERROR(Base_Datos!G28/(Base_Datos!P28/30),9999)<14,"🟡 CRÍTICO",IF(IFERROR(Base_Datos!G28/(Base_Datos!P28/30),9999)<=90,"🟢 NORMAL",IF(IFERROR(Base_Datos!G28/(Base_Datos!P28/30),9999)<=180,"🟡 SOBRESTOCK","🔴 STOCK MUERTO")))) -> 🟢 NORMAL | L27: =IF(F27<7,"⚠ SÍ","—") -> — | M27: =IF(E27>=PERCENTILE($E$5:$E$79,0.8),"A",IF(E27>=PERCENTILE($E$5:$E$79,0.5),"B","C")) -> B | N27: =IFERROR(Base_Datos!O28/Base_Datos!O83,0) -> 0.015063966 | O27: =IF(F27<7,"REPOSICIÓN URGENTE",IF(F27<14,"Revisar orden de compra",IF(AND(F27>180,J27>60),"LIQUIDAR / DEVOLVER",IF(F27>90,"Reducir próxima compra","Stock en niveles óptimos")))) -> Stock en niveles óptimos | P27: =IF(F27<7,1,IF(AND(F27>180,J27>60),2,IF(F27<14,3,IF(F27>90,4,5)))) -> 5
A28: =Base_Datos!A29 -> SKU-024 | B28: =Base_Datos!B29 -> Lentejas 500g | C28: =Base_Datos!C29 -> Alimentos Secos | D28: =Base_Datos!G29 -> 12 | E28: =Base_Datos!P29 -> 6.5 | F28: =IFERROR(Base_Datos!G29/(Base_Datos!P29/30),9999) -> 55.384615 | G28: =IFERROR(Base_Datos!O29/Base_Datos!G29,0) -> 3.25 | H28: =Base_Datos!S29 -> 19.2 | I28: =Base_Datos!H29 -> 5 | J28: =Base_Datos!R29 -> 53 | K28: =IF(IFERROR(Base_Datos!G29/(Base_Datos!P29/30),9999)<7,"🔴 QUIEBRE",IF(IFERROR(Base_Datos!G29/(Base_Datos!P29/30),9999)<14,"🟡 CRÍTICO",IF(IFERROR(Base_Datos!G29/(Base_Datos!P29/30),9999)<=90,"🟢 NORMAL",IF(IFERROR(Base_Datos!G29/(Base_Datos!P29/30),9999)<=180,"🟡 SOBRESTOCK","🔴 STOCK MUERTO")))) -> 🟢 NORMAL | L28: =IF(F28<7,"⚠ SÍ","—") -> — | M28: =IF(E28>=PERCENTILE($E$5:$E$79,0.8),"A",IF(E28>=PERCENTILE($E$5:$E$79,0.5),"B","C")) -> C | N28: =IFERROR(Base_Datos!O29/Base_Datos!O83,0) -> 0.00079070616 | O28: =IF(F28<7,"REPOSICIÓN URGENTE",IF(F28<14,"Revisar orden de compra",IF(AND(F28>180,J28>60),"LIQUIDAR / DEVOLVER",IF(F28>90,"Reducir próxima compra","Stock en niveles óptimos")))) -> Stock en niveles óptimos | P28: =IF(F28<7,1,IF(AND(F28>180,J28>60),2,IF(F28<14,3,IF(F28>90,4,5)))) -> 5
A29: =Base_Datos!A30 -> SKU-025 | B29: =Base_Datos!B30 -> Porotos Negros 500g | C29: =Base_Datos!C30 -> Alimentos Secos | D29: =Base_Datos!G30 -> 304 | E29: =Base_Datos!P30 -> 160.33333 | F29: =IFERROR(Base_Datos!G30/(Base_Datos!P30/30),9999) -> 56.881497 | G29: =IFERROR(Base_Datos!O30/Base_Datos!G30,0) -> 3.1644737 | H29: =Base_Datos!S30 -> 516.8 | I29: =Base_Datos!H30 -> 35 | J29: =Base_Datos!R30 -> 30 | K29: =IF(IFERROR(Base_Datos!G30/(Base_Datos!P30/30),9999)<7,"🔴 QUIEBRE",IF(IFERROR(Base_Datos!G30/(Base_Datos!P30/30),9999)<14,"🟡 CRÍTICO",IF(IFERROR(Base_Datos!G30/(Base_Datos!P30/30),9999)<=90,"🟢 NORMAL",IF(IFERROR(Base_Datos!G30/(Base_Datos!P30/30),9999)<=180,"🟡 SOBRESTOCK","🔴 STOCK MUERTO")))) -> 🟢 NORMAL | L29: =IF(F29<7,"⚠ SÍ","—") -> — | M29: =IF(E29>=PERCENTILE($E$5:$E$79,0.8),"A",IF(E29>=PERCENTILE($E$5:$E$79,0.5),"B","C")) -> B | N29: =IFERROR(Base_Datos!O30/Base_Datos!O83,0) -> 0.019504085 | O29: =IF(F29<7,"REPOSICIÓN URGENTE",IF(F29<14,"Revisar orden de compra",IF(AND(F29>180,J29>60),"LIQUIDAR / DEVOLVER",IF(F29>90,"Reducir próxima compra","Stock en niveles óptimos")))) -> Stock en niveles óptimos | P29: =IF(F29<7,1,IF(AND(F29>180,J29>60),2,IF(F29<14,3,IF(F29>90,4,5)))) -> 5
A30: =Base_Datos!A32 -> SKU-026 | B30: =Base_Datos!B32 -> Lavandina Concentrada 1L | C30: =Base_Datos!C32 -> Limpieza del Hogar | D30: =Base_Datos!G32 -> 267 | E30: =Base_Datos!P32 -> 55.333333 | F30: =IFERROR(Base_Datos!G32/(Base_Datos!P32/30),9999) -> 144.75904 | G30: =IFERROR(Base_Datos!O32/Base_Datos!G32,0) -> 1.2434457 | H30: =Base_Datos!S32 -> 320.4 | I30: =Base_Datos!H32 -> 11 | J30: =Base_Datos!R32 -> 3 | K30: =IF(IFERROR(Base_Datos!G32/(Base_Datos!P32/30),9999)<7,"🔴 QUIEBRE",IF(IFERROR(Base_Datos!G32/(Base_Datos!P32/30),9999)<14,"🟡 CRÍTICO",IF(IFERROR(Base_Datos!G32/(Base_Datos!P32/30),9999)<=90,"🟢 NORMAL",IF(IFERROR(Base_Datos!G32/(Base_Datos!P32/30),9999)<=180,"🟡 SOBRESTOCK","🔴 STOCK MUERTO")))) -> 🟡 SOBRESTOCK | L30: =IF(F30<7,"⚠ SÍ","—") -> — | M30: =IF(E30>=PERCENTILE($E$5:$E$79,0.8),"A",IF(E30>=PERCENTILE($E$5:$E$79,0.5),"B","C")) -> C | N30: =IFERROR(Base_Datos!O32/Base_Datos!O83,0) -> 0.0067311396 | O30: =IF(F30<7,"REPOSICIÓN URGENTE",IF(F30<14,"Revisar orden de compra",IF(AND(F30>180,J30>60),"LIQUIDAR / DEVOLVER",IF(F30>90,"Reducir próxima compra","Stock en niveles óptimos")))) -> Reducir próxima compra | P30: =IF(F30<7,1,IF(AND(F30>180,J30>60),2,IF(F30<14,3,IF(F30>90,4,5)))) -> 4
A31: =Base_Datos!A33 -> SKU-027 | B31: =Base_Datos!B33 -> Lavandina Clásica 2L | C31: =Base_Datos!C33 -> Limpieza del Hogar | D31: =Base_Datos!G33 -> 210 | E31: =Base_Datos!P33 -> 110.16667 | F31: =IFERROR(Base_Datos!G33/(Base_Datos!P33/30),9999) -> 57.186082 | G31: =IFERROR(Base_Datos!O33/Base_Datos!G33,0) -> 3.147619 | H31: =Base_Datos!S33 -> 378 | I31: =Base_Datos!H33 -> 16 | J31: =Base_Datos!R33 -> 27 | K31: =IF(IFERROR(Base_Datos!G33/(Base_Datos!P33/30),9999)<7,"🔴 QUIEBRE",IF(IFERROR(Base_Datos!G33/(Base_Datos!P33/30),9999)<14,"🟡 CRÍTICO",IF(IFERROR(Base_Datos!G33/(Base_Datos!P33/30),9999)<=90,"🟢 NORMAL",IF(IFERROR(Base_Datos!G33/(Base_Datos!P33/30),9999)<=180,"🟡 SOBRESTOCK","🔴 STOCK MUERTO")))) -> 🟢 NORMAL | L31: =IF(F31<7,"⚠ SÍ","—") -> — | M31: =IF(E31>=PERCENTILE($E$5:$E$79,0.8),"A",IF(E31>=PERCENTILE($E$5:$E$79,0.5),"B","C")) -> B | N31: =IFERROR(Base_Datos!O33/Base_Datos!O83,0) -> 0.013401456 | O31: =IF(F31<7,"REPOSICIÓN URGENTE",IF(F31<14,"Revisar orden de compra",IF(AND(F31>180,J31>60),"LIQUIDAR / DEVOLVER",IF(F31>90,"Reducir próxima compra","Stock en niveles óptimos")))) -> Stock en niveles óptimos | P31: =IF(F31<7,1,IF(AND(F31>180,J31>60),2,IF(F31<14,3,IF(F31>90,4,5)))) -> 5
A32: =Base_Datos!A34 -> SKU-028 | B32: =Base_Datos!B34 -> Detergente Lavavajillas 500ml | C32: =Base_Datos!C34 -> Limpieza del Hogar | D32: =Base_Datos!G34 -> 135 | E32: =Base_Datos!P34 -> 127 | F32: =IFERROR(Base_Datos!G34/(Base_Datos!P34/30),9999) -> 31.889764 | G32: =IFERROR(Base_Datos!O34/Base_Datos!G34,0) -> 5.6444444 | H32: =Base_Datos!S34 -> 324 | I32: =Base_Datos!H34 -> 24 | J32: =Base_Datos!R34 -> 7 | K32: =IF(IFERROR(Base_Datos!G34/(Base_Datos!P34/30),9999)<7,"🔴 QUIEBRE",IF(IFERROR(Base_Datos!G34/(Base_Datos!P34/30),9999)<14,"🟡 CRÍTICO",IF(IFERROR(Base_Datos!G34/(Base_Datos!P34/30),9999)<=90,"🟢 NORMAL",IF(IFERROR(Base_Datos!G34/(Base_Datos!P34/30),9999)<=180,"🟡 SOBRESTOCK","🔴 STOCK MUERTO")))) -> 🟢 NORMAL | L32: =IF(F32<7,"⚠ SÍ","—") -> — | M32: =IF(E32>=PERCENTILE($E$5:$E$79,0.8),"A",IF(E32>=PERCENTILE($E$5:$E$79,0.5),"B","C")) -> B | N32: =IFERROR(Base_Datos!O34/Base_Datos!O83,0) -> 0.015449182 | O32: =IF(F32<7,"REPOSICIÓN URGENTE",IF(F32<14,"Revisar orden de compra",IF(AND(F32>180,J32>60),"LIQUIDAR / DEVOLVER",IF(F32>90,"Reducir próxima compra","Stock en niveles óptimos")))) -> Stock en niveles óptimos | P32: =IF(F32<7,1,IF(AND(F32>180,J32>60),2,IF(F32<14,3,IF(F32>90,4,5)))) -> 5
A33: =Base_Datos!A35 -> SKU-029 | B33: =Base_Datos!B35 -> Detergente Lavavajillas 1L | C33: =Base_Datos!C35 -> Limpieza del Hogar | D33: =Base_Datos!G35 -> 14 | E33: =Base_Datos!P35 -> 15.333333 | F33: =IFERROR(Base_Datos!G35/(Base_Datos!P35/30),9999) -> 27.391304 | G33: =IFERROR(Base_Datos!O35/Base_Datos!G35,0) -> 6.5714286 | H33: =Base_Datos!S35 -> 58.8 | I33: =Base_Datos!H35 -> 5 | J33: =Base_Datos!R35 -> 43 | K33: =IF(IFERROR(Base_Datos!G35/(Base_Datos!P35/30),9999)<7,"🔴 QUIEBRE",IF(IFERROR(Base_Datos!G35/(Base_Datos!P35/30),9999)<14,"🟡 CRÍTICO",IF(IFERROR(Base_Datos!G35/(Base_Datos!P35/30),9999)<=90,"🟢 NORMAL",IF(IFERROR(Base_Datos!G35/(Base_Datos!P35/30),9999)<=180,"🟡 SOBRESTOCK","🔴 STOCK MUERTO")))) -> 🟢 NORMAL | L33: =IF(F33<7,"⚠ SÍ","—") -> — | M33: =IF(E33>=PERCENTILE($E$5:$E$79,0.8),"A",IF(E33>=PERCENTILE($E$5:$E$79,0.5),"B","C")) -> C | N33: =IFERROR(Base_Datos!O35/Base_Datos!O83,0) -> 0.0018652556 | O33: =IF(F33<7,"REPOSICIÓN URGENTE",IF(F33<14,"Revisar orden de compra",IF(AND(F33>180,J33>60),"LIQUIDAR / DEVOLVER",IF(F33>90,"Reducir próxima compra","Stock en niveles óptimos")))) -> Stock en niveles óptimos | P33: =IF(F33<7,1,IF(AND(F33>180,J33>60),2,IF(F33<14,3,IF(F33>90,4,5)))) -> 5
A34: =Base_Datos!A36 -> SKU-030 | B34: =Base_Datos!B36 -> Jabón en Polvo 1kg | C34: =Base_Datos!C36 -> Limpieza del Hogar | D34: =Base_Datos!G36 -> 78 | E34: =Base_Datos!P36 -> 51.666667 | F34: =IFERROR(Base_Datos!G36/(Base_Datos!P36/30),9999) -> 45.290323 | G34: =IFERROR(Base_Datos!O36/Base_Datos!G36,0) -> 3.974359 | H34: =Base_Datos!S36 -> 374.4 | I34: =Base_Datos!H36 -> 7 | J34: =Base_Datos!R36 -> 3 | K34: =IF(IFERROR(Base_Datos!G36/(Base_Datos!P36/30),9999)<7,"🔴 QUIEBRE",IF(IFERROR(Base_Datos!G36/(Base_Datos!P36/30),9999)<14,"🟡 CRÍTICO",IF(IFERROR(Base_Datos!G36/(Base_Datos!P36/30),9999)<=90,"🟢 NORMAL",IF(IFERROR(Base_Datos!G36/(Base_Datos!P36/30),9999)<=180,"🟡 SOBRESTOCK","🔴 STOCK MUERTO")))) -> 🟢 NORMAL | L34: =IF(F34<7,"⚠ SÍ","—") -> — | M34: =IF(E34>=PERCENTILE($E$5:$E$79,0.8),"A",IF(E34>=PERCENTILE($E$5:$E$79,0.5),"B","C")) -> C | N34: =IFERROR(Base_Datos!O36/Base_Datos!O83,0) -> 0.0062851003 | O34: =IF(F34<7,"REPOSICIÓN URGENTE",IF(F34<14,"Revisar orden de compra",IF(AND(F34>180,J34>60),"LIQUIDAR / DEVOLVER",IF(F34>90,"Reducir próxima compra","Stock en niveles óptimos")))) -> Stock en niveles óptimos | P34: =IF(F34<7,1,IF(AND(F34>180,J34>60),2,IF(F34<14,3,IF(F34>90,4,5)))) -> 5
A35: =Base_Datos!A37 -> SKU-031 | B35: =Base_Datos!B37 -> Jabón en Polvo 3kg | C35: =Base_Datos!C37 -> Limpieza del Hogar | D35: =Base_Datos!G37 -> 512 | E35: =Base_Datos!P37 -> 76 | F35: =IFERROR(Base_Datos!G37/(Base_Datos!P37/30),9999) -> 202.10526 | G35: =IFERROR(Base_Datos!O37/Base_Datos!G37,0) -> 0.890625 | H35: =Base_Datos!S37 -> 6912 | I35: =Base_Datos!H37 -> 20 | J35: =Base_Datos!R37 -> 28 | K35: =IF(IFERROR(Base_Datos!G37/(Base_Datos!P37/30),9999)<7,"🔴 QUIEBRE",IF(IFERROR(Base_Datos!G37/(Base_Datos!P37/30),9999)<14,"🟡 CRÍTICO",IF(IFERROR(Base_Datos!G37/(Base_Datos!P37/30),9999)<=90,"🟢 NORMAL",IF(IFERROR(Base_Datos!G37/(Base_Datos!P37/30),9999)<=180,"🟡 SOBRESTOCK","🔴 STOCK MUERTO")))) -> 🔴 STOCK MUERTO | L35: =IF(F35<7,"⚠ SÍ","—") -> — | M35: =IF(E35>=PERCENTILE($E$5:$E$79,0.8),"A",IF(E35>=PERCENTILE($E$5:$E$79,0.5),"B","C")) -> C | N35: =IFERROR(Base_Datos!O37/Base_Datos!O83,0) -> 0.0092451797 | O35: =IF(F35<7,"REPOSICIÓN URGENTE",IF(F35<14,"Revisar orden de compra",IF(AND(F35>180,J35>60),"LIQUIDAR / DEVOLVER",IF(F35>90,"Reducir próxima compra","Stock en niveles óptimos")))) -> Reducir próxima compra | P35: =IF(F35<7,1,IF(AND(F35>180,J35>60),2,IF(F35<14,3,IF(F35>90,4,5)))) -> 4
A36: =Base_Datos!A38 -> SKU-032 | B36: =Base_Datos!B38 -> Suavizante Ropa 800ml | C36: =Base_Datos!C38 -> Limpieza del Hogar | D36: =Base_Datos!G38 -> 76 | E36: =Base_Datos!P38 -> 51.333333 | F36: =IFERROR(Base_Datos!G38/(Base_Datos!P38/30),9999) -> 44.415584 | G36: =IFERROR(Base_Datos!O38/Base_Datos!G38,0) -> 4.0526316 | H36: =Base_Datos!S38 -> 273.6 | I36: =Base_Datos!H38 -> 12 | J36: =Base_Datos!R38 -> 5 | K36: =IF(IFERROR(Base_Datos!G38/(Base_Datos!P38/30),9999)<7,"🔴 QUIEBRE",IF(IFERROR(Base_Datos!G38/(Base_Datos!P38/30),9999)<14,"🟡 CRÍTICO",IF(IFERROR(Base_Datos!G38/(Base_Datos!P38/30),9999)<=90,"🟢 NORMAL",IF(IFERROR(Base_Datos!G38/(Base_Datos!P38/30),9999)<=180,"🟡 SOBRESTOCK","🔴 STOCK MUERTO")))) -> 🟢 NORMAL | L36: =IF(F36<7,"⚠ SÍ","—") -> — | M36: =IF(E36>=PERCENTILE($E$5:$E$79,0.8),"A",IF(E36>=PERCENTILE($E$5:$E$79,0.5),"B","C")) -> C | N36: =IFERROR(Base_Datos!O38/Base_Datos!O83,0) -> 0.0062445512 | O36: =IF(F36<7,"REPOSICIÓN URGENTE",IF(F36<14,"Revisar orden de compra",IF(AND(F36>180,J36>60),"LIQUIDAR / DEVOLVER",IF(F36>90,"Reducir próxima compra","Stock en niveles óptimos")))) -> Stock en niveles óptimos | P36: =IF(F36<7,1,IF(AND(F36>180,J36>60),2,IF(F36<14,3,IF(F36>90,4,5)))) -> 5
A37: =Base_Datos!A39 -> SKU-033 | B37: =Base_Datos!B39 -> Suavizante Ropa 1.5L | C37: =Base_Datos!C39 -> Limpieza del Hogar | D37: =Base_Datos!G39 -> 185 | E37: =Base_Datos!P39 -> 1.1666667 | F37: =IFERROR(Base_Datos!G39/(Base_Datos!P39/30),9999) -> 4757.1429 | G37: =IFERROR(Base_Datos!O39/Base_Datos!G39,0) -> 0.037837838 | H37: =Base_Datos!S39 -> 1147 | I37: =Base_Datos!H39 -> 5 | J37: =Base_Datos!R39 -> 76 | K37: =IF(IFERROR(Base_Datos!G39/(Base_Datos!P39/30),9999)<7,"🔴 QUIEBRE",IF(IFERROR(Base_Datos!G39/(Base_Datos!P39/30),9999)<14,"🟡 CRÍTICO",IF(IFERROR(Base_Datos!G39/(Base_Datos!P39/30),9999)<=90,"🟢 NORMAL",IF(IFERROR(Base_Datos!G39/(Base_Datos!P39/30),9999)<=180,"🟡 SOBRESTOCK","🔴 STOCK MUERTO")))) -> 🔴 STOCK MUERTO | L37: =IF(F37<7,"⚠ SÍ","—") -> — | M37: =IF(E37>=PERCENTILE($E$5:$E$79,0.8),"A",IF(E37>=PERCENTILE($E$5:$E$79,0.5),"B","C")) -> C | N37: =IFERROR(Base_Datos!O39/Base_Datos!O83,0) -> 0.00014192162 | O37: =IF(F37<7,"REPOSICIÓN URGENTE",IF(F37<14,"Revisar orden de compra",IF(AND(F37>180,J37>60),"LIQUIDAR / DEVOLVER",IF(F37>90,"Reducir próxima compra","Stock en niveles óptimos")))) -> LIQUIDAR / DEVOLVER | P37: =IF(F37<7,1,IF(AND(F37>180,J37>60),2,IF(F37<14,3,IF(F37>90,4,5)))) -> 2
A38: =Base_Datos!A40 -> SKU-034 | B38: =Base_Datos!B40 -> Limpiador Multiuso 500ml | C38: =Base_Datos!C40 -> Limpieza del Hogar | D38: =Base_Datos!G40 -> 101 | E38: =Base_Datos!P40 -> 89.833333 | F38: =IFERROR(Base_Datos!G40/(Base_Datos!P40/30),9999) -> 33.729128 | G38: =IFERROR(Base_Datos!O40/Base_Datos!G40,0) -> 5.3366337 | H38: =Base_Datos!S40 -> 292.9 | I38: =Base_Datos!H40 -> 17 | J38: =Base_Datos!R40 -> 28 | K38: =IF(IFERROR(Base_Datos!G40/(Base_Datos!P40/30),9999)<7,"🔴 QUIEBRE",IF(IFERROR(Base_Datos!G40/(Base_Datos!P40/30),9999)<14,"🟡 CRÍTICO",IF(IFERROR(Base_Datos!G40/(Base_Datos!P40/30),9999)<=90,"🟢 NORMAL",IF(IFERROR(Base_Datos!G40/(Base_Datos!P40/30),9999)<=180,"🟡 SOBRESTOCK","🔴 STOCK MUERTO")))) -> 🟢 NORMAL | L38: =IF(F38<7,"⚠ SÍ","—") -> — | M38: =IF(E38>=PERCENTILE($E$5:$E$79,0.8),"A",IF(E38>=PERCENTILE($E$5:$E$79,0.5),"B","C")) -> C | N38: =IFERROR(Base_Datos!O40/Base_Datos!O83,0) -> 0.010927965 | O38: =IF(F38<7,"REPOSICIÓN URGENTE",IF(F38<14,"Revisar orden de compra",IF(AND(F38>180,J38>60),"LIQUIDAR / DEVOLVER",IF(F38>90,"Reducir próxima compra","Stock en niveles óptimos")))) -> Stock en niveles óptimos | P38: =IF(F38<7,1,IF(AND(F38>180,J38>60),2,IF(F38<14,3,IF(F38>90,4,5)))) -> 5
A39: =Base_Datos!A41 -> SKU-035 | B39: =Base_Datos!B41 -> Limpiador Piso 1L | C39: =Base_Datos!C41 -> Limpieza del Hogar | D39: =Base_Datos!G41 -> 43 | E39: =Base_Datos!P41 -> 183 | F39: =IFERROR(Base_Datos!G41/(Base_Datos!P41/30),9999) -> 7.0491803 | G39: =IFERROR(Base_Datos!O41/Base_Datos!G41,0) -> 25.534884 | H39: =Base_Datos!S41 -> 133.3 | I39: =Base_Datos!H41 -> 30 | J39: =Base_Datos!R41 -> 9 | K39: =IF(IFERROR(Base_Datos!G41/(Base_Datos!P41/30),9999)<7,"🔴 QUIEBRE",IF(IFERROR(Base_Datos!G41/(Base_Datos!P41/30),9999)<14,"🟡 CRÍTICO",IF(IFERROR(Base_Datos!G41/(Base_Datos!P41/30),9999)<=90,"🟢 NORMAL",IF(IFERROR(Base_Datos!G41/(Base_Datos!P41/30),9999)<=180,"🟡 SOBRESTOCK","🔴 STOCK MUERTO")))) -> 🟡 CRÍTICO | L39: =IF(F39<7,"⚠ SÍ","—") -> — | M39: =IF(E39>=PERCENTILE($E$5:$E$79,0.8),"A",IF(E39>=PERCENTILE($E$5:$E$79,0.5),"B","C")) -> A | N39: =IFERROR(Base_Datos!O41/Base_Datos!O83,0) -> 0.02226142 | O39: =IF(F39<7,"REPOSICIÓN URGENTE",IF(F39<14,"Revisar orden de compra",IF(AND(F39>180,J39>60),"LIQUIDAR / DEVOLVER",IF(F39>90,"Reducir próxima compra","Stock en niveles óptimos")))) -> Revisar orden de compra | P39: =IF(F39<7,1,IF(AND(F39>180,J39>60),2,IF(F39<14,3,IF(F39>90,4,5)))) -> 3
A40: =Base_Datos!A42 -> SKU-036 | B40: =Base_Datos!B42 -> Desengrasante 500ml | C40: =Base_Datos!C42 -> Limpieza del Hogar | D40: =Base_Datos!G42 -> 137 | E40: =Base_Datos!P42 -> 89 | F40: =IFERROR(Base_Datos!G42/(Base_Datos!P42/30),9999) -> 46.179775 | G40: =IFERROR(Base_Datos!O42/Base_Datos!G42,0) -> 3.8978102 | H40: =Base_Datos!S42 -> 479.5 | I40: =Base_Datos!H42 -> 26 | J40: =Base_Datos!R42 -> 4 | K40: =IF(IFERROR(Base_Datos!G42/(Base_Datos!P42/30),9999)<7,"🔴 QUIEBRE",IF(IFERROR(Base_Datos!G42/(Base_Datos!P42/30),9999)<14,"🟡 CRÍTICO",IF(IFERROR(Base_Datos!G42/(Base_Datos!P42/30),9999)<=90,"🟢 NORMAL",IF(IFERROR(Base_Datos!G42/(Base_Datos!P42/30),9999)<=180,"🟡 SOBRESTOCK","🔴 STOCK MUERTO")))) -> 🟢 NORMAL | L40: =IF(F40<7,"⚠ SÍ","—") -> — | M40: =IF(E40>=PERCENTILE($E$5:$E$79,0.8),"A",IF(E40>=PERCENTILE($E$5:$E$79,0.5),"B","C")) -> C | N40: =IFERROR(Base_Datos!O42/Base_Datos!O83,0) -> 0.010826592 | O40: =IF(F40<7,"REPOSICIÓN URGENTE",IF(F40<14,"Revisar orden de compra",IF(AND(F40>180,J40>60),"LIQUIDAR / DEVOLVER",IF(F40>90,"Reducir próxima compra","Stock en niveles óptimos")))) -> Stock en niveles óptimos | P40: =IF(F40<7,1,IF(AND(F40>180,J40>60),2,IF(F40<14,3,IF(F40>90,4,5)))) -> 5
A41: =Base_Datos!A43 -> SKU-037 | B41: =Base_Datos!B43 -> Limpiavidrios 500ml | C41: =Base_Datos!C43 -> Limpieza del Hogar | D41: =Base_Datos!G43 -> 274 | E41: =Base_Datos!P43 -> 139.33333 | F41: =IFERROR(Base_Datos!G43/(Base_Datos!P43/30),9999) -> 58.995215 | G41: =IFERROR(Base_Datos!O43/Base_Datos!G43,0) -> 3.0510949 | H41: =Base_Datos!S43 -> 739.8 | I41: =Base_Datos!H43 -> 40 | J41: =Base_Datos!R43 -> 24 | K41: =IF(IFERROR(Base_Datos!G43/(Base_Datos!P43/30),9999)<7,"🔴 QUIEBRE",IF(IFERROR(Base_Datos!G43/(Base_Datos!P43/30),9999)<14,"🟡 CRÍTICO",IF(IFERROR(Base_Datos!G43/(Base_Datos!P43/30),9999)<=90,"🟢 NORMAL",IF(IFERROR(Base_Datos!G43/(Base_Datos!P43/30),9999)<=180,"🟡 SOBRESTOCK","🔴 STOCK MUERTO")))) -> 🟢 NORMAL | L41: =IF(F41<7,"⚠ SÍ","—") -> — | M41: =IF(E41>=PERCENTILE($E$5:$E$79,0.8),"A",IF(E41>=PERCENTILE($E$5:$E$79,0.5),"B","C")) -> B | N41: =IFERROR(Base_Datos!O43/Base_Datos!O83,0) -> 0.016949496 | O41: =IF(F41<7,"REPOSICIÓN URGENTE",IF(F41<14,"Revisar orden de compra",IF(AND(F41>180,J41>60),"LIQUIDAR / DEVOLVER",IF(F41>90,"Reducir próxima compra","Stock en niveles óptimos")))) -> Stock en niveles óptimos | P41: =IF(F41<7,1,IF(AND(F41>180,J41>60),2,IF(F41<14,3,IF(F41>90,4,5)))) -> 5
A42: =Base_Datos!A44 -> SKU-038 | B42: =Base_Datos!B44 -> Esponjas Doble Faz x3 | C42: =Base_Datos!C44 -> Limpieza del Hogar | D42: =Base_Datos!G44 -> 556 | E42: =Base_Datos!P44 -> 88.333333 | F42: =IFERROR(Base_Datos!G44/(Base_Datos!P44/30),9999) -> 188.83019 | G42: =IFERROR(Base_Datos!O44/Base_Datos!G44,0) -> 0.95323741 | H42: =Base_Datos!S44 -> 1223.2 | I42: =Base_Datos!H44 -> 17 | J42: =Base_Datos!R44 -> 10 | K42: =IF(IFERROR(Base_Datos!G44/(Base_Datos!P44/30),9999)<7,"🔴 QUIEBRE",IF(IFERROR(Base_Datos!G44/(Base_Datos!P44/30),9999)<14,"🟡 CRÍTICO",IF(IFERROR(Base_Datos!G44/(Base_Datos!P44/30),9999)<=90,"🟢 NORMAL",IF(IFERROR(Base_Datos!G44/(Base_Datos!P44/30),9999)<=180,"🟡 SOBRESTOCK","🔴 STOCK MUERTO")))) -> 🔴 STOCK MUERTO | L42: =IF(F42<7,"⚠ SÍ","—") -> — | M42: =IF(E42>=PERCENTILE($E$5:$E$79,0.8),"A",IF(E42>=PERCENTILE($E$5:$E$79,0.5),"B","C")) -> C | N42: =IFERROR(Base_Datos!O44/Base_Datos!O83,0) -> 0.010745494 | O42: =IF(F42<7,"REPOSICIÓN URGENTE",IF(F42<14,"Revisar orden de compra",IF(AND(F42>180,J42>60),"LIQUIDAR / DEVOLVER",IF(F42>90,"Reducir próxima compra","Stock en niveles óptimos")))) -> Reducir próxima compra | P42: =IF(F42<7,1,IF(AND(F42>180,J42>60),2,IF(F42<14,3,IF(F42>90,4,5)))) -> 4
A43: =Base_Datos!A45 -> SKU-039 | B43: =Base_Datos!B45 -> Trapo de Piso x1 | C43: =Base_Datos!C45 -> Limpieza del Hogar | D43: =Base_Datos!G45 -> 36 | E43: =Base_Datos!P45 -> 17.666667 | F43: =IFERROR(Base_Datos!G45/(Base_Datos!P45/30),9999) -> 61.132075 | G43: =IFERROR(Base_Datos!O45/Base_Datos!G45,0) -> 2.9444444 | H43: =Base_Datos!S45 -> 136.8 | I43: =Base_Datos!H45 -> 5 | J43: =Base_Datos!R45 -> 53 | K43: =IF(IFERROR(Base_Datos!G45/(Base_Datos!P45/30),9999)<7,"🔴 QUIEBRE",IF(IFERROR(Base_Datos!G45/(Base_Datos!P45/30),9999)<14,"🟡 CRÍTICO",IF(IFERROR(Base_Datos!G45/(Base_Datos!P45/30),9999)<=90,"🟢 NORMAL",IF(IFERROR(Base_Datos!G45/(Base_Datos!P45/30),9999)<=180,"🟡 SOBRESTOCK","🔴 STOCK MUERTO")))) -> 🟢 NORMAL | L43: =IF(F43<7,"⚠ SÍ","—") -> — | M43: =IF(E43>=PERCENTILE($E$5:$E$79,0.8),"A",IF(E43>=PERCENTILE($E$5:$E$79,0.5),"B","C")) -> C | N43: =IFERROR(Base_Datos!O45/Base_Datos!O83,0) -> 0.0021490988 | O43: =IF(F43<7,"REPOSICIÓN URGENTE",IF(F43<14,"Revisar orden de compra",IF(AND(F43>180,J43>60),"LIQUIDAR / DEVOLVER",IF(F43>90,"Reducir próxima compra","Stock en niveles óptimos")))) -> Stock en niveles óptimos | P43: =IF(F43<7,1,IF(AND(F43>180,J43>60),2,IF(F43<14,3,IF(F43>90,4,5)))) -> 5
A44: =Base_Datos!A46 -> SKU-040 | B44: =Base_Datos!B46 -> Escoba con Mango | C44: =Base_Datos!C46 -> Limpieza del Hogar | D44: =Base_Datos!G46 -> 163 | E44: =Base_Datos!P46 -> 121 | F44: =IFERROR(Base_Datos!G46/(Base_Datos!P46/30),9999) -> 40.413223 | G44: =IFERROR(Base_Datos!O46/Base_Datos!G46,0) -> 4.4539877 | H44: =Base_Datos!S46 -> 1385.5 | I44: =Base_Datos!H46 -> 26 | J44: =Base_Datos!R46 -> 22 | K44: =IF(IFERROR(Base_Datos!G46/(Base_Datos!P46/30),9999)<7,"🔴 QUIEBRE",IF(IFERROR(Base_Datos!G46/(Base_Datos!P46/30),9999)<14,"🟡 CRÍTICO",IF(IFERROR(Base_Datos!G46/(Base_Datos!P46/30),9999)<=90,"🟢 NORMAL",IF(IFERROR(Base_Datos!G46/(Base_Datos!P46/30),9999)<=180,"🟡 SOBRESTOCK","🔴 STOCK MUERTO")))) -> 🟢 NORMAL | L44: =IF(F44<7,"⚠ SÍ","—") -> — | M44: =IF(E44>=PERCENTILE($E$5:$E$79,0.8),"A",IF(E44>=PERCENTILE($E$5:$E$79,0.5),"B","C")) -> B | N44: =IFERROR(Base_Datos!O46/Base_Datos!O83,0) -> 0.014719299 | O44: =IF(F44<7,"REPOSICIÓN URGENTE",IF(F44<14,"Revisar orden de compra",IF(AND(F44>180,J44>60),"LIQUIDAR / DEVOLVER",IF(F44>90,"Reducir próxima compra","Stock en niveles óptimos")))) -> Stock en niveles óptimos | P44: =IF(F44<7,1,IF(AND(F44>180,J44>60),2,IF(F44<14,3,IF(F44>90,4,5)))) -> 5
A45: =Base_Datos!A47 -> SKU-041 | B45: =Base_Datos!B47 -> Cesto de Residuos 20L | C45: =Base_Datos!C47 -> Limpieza del Hogar | D45: =Base_Datos!G47 -> 200 | E45: =Base_Datos!P47 -> 104 | F45: =IFERROR(Base_Datos!G47/(Base_Datos!P47/30),9999) -> 57.692308 | G45: =IFERROR(Base_Datos!O47/Base_Datos!G47,0) -> 3.12 | H45: =Base_Datos!S47 -> 2400 | I45: =Base_Datos!H47 -> 25 | J45: =Base_Datos!R47 -> 3 | K45: =IF(IFERROR(Base_Datos!G47/(Base_Datos!P47/30),9999)<7,"🔴 QUIEBRE",IF(IFERROR(Base_Datos!G47/(Base_Datos!P47/30),9999)<14,"🟡 CRÍTICO",IF(IFERROR(Base_Datos!G47/(Base_Datos!P47/30),9999)<=90,"🟢 NORMAL",IF(IFERROR(Base_Datos!G47/(Base_Datos!P47/30),9999)<=180,"🟡 SOBRESTOCK","🔴 STOCK MUERTO")))) -> 🟢 NORMAL | L45: =IF(F45<7,"⚠ SÍ","—") -> — | M45: =IF(E45>=PERCENTILE($E$5:$E$79,0.8),"A",IF(E45>=PERCENTILE($E$5:$E$79,0.5),"B","C")) -> B | N45: =IFERROR(Base_Datos!O47/Base_Datos!O83,0) -> 0.012651299 | O45: =IF(F45<7,"REPOSICIÓN URGENTE",IF(F45<14,"Revisar orden de compra",IF(AND(F45>180,J45>60),"LIQUIDAR / DEVOLVER",IF(F45>90,"Reducir próxima compra","Stock en niveles óptimos")))) -> Stock en niveles óptimos | P45: =IF(F45<7,1,IF(AND(F45>180,J45>60),2,IF(F45<14,3,IF(F45>90,4,5)))) -> 5
A46: =Base_Datos!A48 -> SKU-042 | B46: =Base_Datos!B48 -> Bolsas de Basura x10 90L | C46: =Base_Datos!C48 -> Limpieza del Hogar | D46: =Base_Datos!G48 -> 606 | E46: =Base_Datos!P48 -> 91.5 | F46: =IFERROR(Base_Datos!G48/(Base_Datos!P48/30),9999) -> 198.68852 | G46: =IFERROR(Base_Datos!O48/Base_Datos!G48,0) -> 0.90594059 | H46: =Base_Datos!S48 -> 1696.8 | I46: =Base_Datos!H48 -> 14 | J46: =Base_Datos!R48 -> 14 | K46: =IF(IFERROR(Base_Datos!G48/(Base_Datos!P48/30),9999)<7,"🔴 QUIEBRE",IF(IFERROR(Base_Datos!G48/(Base_Datos!P48/30),9999)<14,"🟡 CRÍTICO",IF(IFERROR(Base_Datos!G48/(Base_Datos!P48/30),9999)<=90,"🟢 NORMAL",IF(IFERROR(Base_Datos!G48/(Base_Datos!P48/30),9999)<=180,"🟡 SOBRESTOCK","🔴 STOCK MUERTO")))) -> 🔴 STOCK MUERTO | L46: =IF(F46<7,"⚠ SÍ","—") -> — | M46: =IF(E46>=PERCENTILE($E$5:$E$79,0.8),"A",IF(E46>=PERCENTILE($E$5:$E$79,0.5),"B","C")) -> C | N46: =IFERROR(Base_Datos!O48/Base_Datos!O83,0) -> 0.01113071 | O46: =IF(F46<7,"REPOSICIÓN URGENTE",IF(F46<14,"Revisar orden de compra",IF(AND(F46>180,J46>60),"LIQUIDAR / DEVOLVER",IF(F46>90,"Reducir próxima compra","Stock en niveles óptimos")))) -> Reducir próxima compra | P46: =IF(F46<7,1,IF(AND(F46>180,J46>60),2,IF(F46<14,3,IF(F46>90,4,5)))) -> 4
A47: =Base_Datos!A49 -> SKU-043 | B47: =Base_Datos!B49 -> Bolsas de Basura x30 35L | C47: =Base_Datos!C49 -> Limpieza del Hogar | D47: =Base_Datos!G49 -> 209 | E47: =Base_Datos!P49 -> 92.5 | F47: =IFERROR(Base_Datos!G49/(Base_Datos!P49/30),9999) -> 67.783784 | G47: =IFERROR(Base_Datos!O49/Base_Datos!G49,0) -> 2.6555024 | H47: =Base_Datos!S49 -> 668.8 | I47: =Base_Datos!H49 -> 26 | J47: =Base_Datos!R49 -> 25 | K47: =IF(IFERROR(Base_Datos!G49/(Base_Datos!P49/30),9999)<7,"🔴 QUIEBRE",IF(IFERROR(Base_Datos!G49/(Base_Datos!P49/30),9999)<14,"🟡 CRÍTICO",IF(IFERROR(Base_Datos!G49/(Base_Datos!P49/30),9999)<=90,"🟢 NORMAL",IF(IFERROR(Base_Datos!G49/(Base_Datos!P49/30),9999)<=180,"🟡 SOBRESTOCK","🔴 STOCK MUERTO")))) -> 🟢 NORMAL | L47: =IF(F47<7,"⚠ SÍ","—") -> — | M47: =IF(E47>=PERCENTILE($E$5:$E$79,0.8),"A",IF(E47>=PERCENTILE($E$5:$E$79,0.5),"B","C")) -> C | N47: =IFERROR(Base_Datos!O49/Base_Datos!O83,0) -> 0.011252357 | O47: =IF(F47<7,"REPOSICIÓN URGENTE",IF(F47<14,"Revisar orden de compra",IF(AND(F47>180,J47>60),"LIQUIDAR / DEVOLVER",IF(F47>90,"Reducir próxima compra","Stock en niveles óptimos")))) -> Stock en niveles óptimos | P47: =IF(F47<7,1,IF(AND(F47>180,J47>60),2,IF(F47<14,3,IF(F47>90,4,5)))) -> 5
A48: =Base_Datos!A50 -> SKU-044 | B48: =Base_Datos!B50 -> Papel Higiénico x4 | C48: =Base_Datos!C50 -> Limpieza del Hogar | D48: =Base_Datos!G50 -> 20 | E48: =Base_Datos!P50 -> 279.5 | F48: =IFERROR(Base_Datos!G50/(Base_Datos!P50/30),9999) -> 2.1466905 | G48: =IFERROR(Base_Datos!O50/Base_Datos!G50,0) -> 83.85 | H48: =Base_Datos!S50 -> 72 | I48: =Base_Datos!H50 -> 47 | J48: =Base_Datos!R50 -> 15 | K48: =IF(IFERROR(Base_Datos!G50/(Base_Datos!P50/30),9999)<7,"🔴 QUIEBRE",IF(IFERROR(Base_Datos!G50/(Base_Datos!P50/30),9999)<14,"🟡 CRÍTICO",IF(IFERROR(Base_Datos!G50/(Base_Datos!P50/30),9999)<=90,"🟢 NORMAL",IF(IFERROR(Base_Datos!G50/(Base_Datos!P50/30),9999)<=180,"🟡 SOBRESTOCK","🔴 STOCK MUERTO")))) -> 🔴 QUIEBRE | L48: =IF(F48<7,"⚠ SÍ","—") -> ⚠ SÍ | M48: =IF(E48>=PERCENTILE($E$5:$E$79,0.8),"A",IF(E48>=PERCENTILE($E$5:$E$79,0.5),"B","C")) -> A | N48: =IFERROR(Base_Datos!O50/Base_Datos!O83,0) -> 0.034000365 | O48: =IF(F48<7,"REPOSICIÓN URGENTE",IF(F48<14,"Revisar orden de compra",IF(AND(F48>180,J48>60),"LIQUIDAR / DEVOLVER",IF(F48>90,"Reducir próxima compra","Stock en niveles óptimos")))) -> REPOSICIÓN URGENTE | P48: =IF(F48<7,1,IF(AND(F48>180,J48>60),2,IF(F48<14,3,IF(F48>90,4,5)))) -> 1
A49: =Base_Datos!A51 -> SKU-045 | B49: =Base_Datos!B51 -> Papel Higiénico x12 | C49: =Base_Datos!C51 -> Limpieza del Hogar | D49: =Base_Datos!G51 -> 343 | E49: =Base_Datos!P51 -> 207.16667 | F49: =IFERROR(Base_Datos!G51/(Base_Datos!P51/30),9999) -> 49.670153 | G49: =IFERROR(Base_Datos!O51/Base_Datos!G51,0) -> 3.6239067 | H49: =Base_Datos!S51 -> 3361.4 | I49: =Base_Datos!H51 -> 56 | J49: =Base_Datos!R51 -> 18 | K49: =IF(IFERROR(Base_Datos!G51/(Base_Datos!P51/30),9999)<7,"🔴 QUIEBRE",IF(IFERROR(Base_Datos!G51/(Base_Datos!P51/30),9999)<14,"🟡 CRÍTICO",IF(IFERROR(Base_Datos!G51/(Base_Datos!P51/30),9999)<=90,"🟢 NORMAL",IF(IFERROR(Base_Datos!G51/(Base_Datos!P51/30),9999)<=180,"🟡 SOBRESTOCK","🔴 STOCK MUERTO")))) -> 🟢 NORMAL | L49: =IF(F49<7,"⚠ SÍ","—") -> — | M49: =IF(E49>=PERCENTILE($E$5:$E$79,0.8),"A",IF(E49>=PERCENTILE($E$5:$E$79,0.5),"B","C")) -> A | N49: =IFERROR(Base_Datos!O51/Base_Datos!O83,0) -> 0.025201225 | O49: =IF(F49<7,"REPOSICIÓN URGENTE",IF(F49<14,"Revisar orden de compra",IF(AND(F49>180,J49>60),"LIQUIDAR / DEVOLVER",IF(F49>90,"Reducir próxima compra","Stock en niveles óptimos")))) -> Stock en niveles óptimos | P49: =IF(F49<7,1,IF(AND(F49>180,J49>60),2,IF(F49<14,3,IF(F49>90,4,5)))) -> 5
A50: =Base_Datos!A52 -> SKU-046 | B50: =Base_Datos!B52 -> Servilletas x100 | C50: =Base_Datos!C52 -> Limpieza del Hogar | D50: =Base_Datos!G52 -> 338 | E50: =Base_Datos!P52 -> 161 | F50: =IFERROR(Base_Datos!G52/(Base_Datos!P52/30),9999) -> 62.981366 | G50: =IFERROR(Base_Datos!O52/Base_Datos!G52,0) -> 2.8579882 | H50: =Base_Datos!S52 -> 642.2 | I50: =Base_Datos!H52 -> 36 | J50: =Base_Datos!R52 -> 21 | K50: =IF(IFERROR(Base_Datos!G52/(Base_Datos!P52/30),9999)<7,"🔴 QUIEBRE",IF(IFERROR(Base_Datos!G52/(Base_Datos!P52/30),9999)<14,"🟡 CRÍTICO",IF(IFERROR(Base_Datos!G52/(Base_Datos!P52/30),9999)<=90,"🟢 NORMAL",IF(IFERROR(Base_Datos!G52/(Base_Datos!P52/30),9999)<=180,"🟡 SOBRESTOCK","🔴 STOCK MUERTO")))) -> 🟢 NORMAL | L50: =IF(F50<7,"⚠ SÍ","—") -> — | M50: =IF(E50>=PERCENTILE($E$5:$E$79,0.8),"A",IF(E50>=PERCENTILE($E$5:$E$79,0.5),"B","C")) -> B | N50: =IFERROR(Base_Datos!O52/Base_Datos!O83,0) -> 0.019585183 | O50: =IF(F50<7,"REPOSICIÓN URGENTE",IF(F50<14,"Revisar orden de compra",IF(AND(F50>180,J50>60),"LIQUIDAR / DEVOLVER",IF(F50>90,"Reducir próxima compra","Stock en niveles óptimos")))) -> Stock en niveles óptimos | P50: =IF(F50<7,1,IF(AND(F50>180,J50>60),2,IF(F50<14,3,IF(F50>90,4,5)))) -> 5
A51: =Base_Datos!A53 -> SKU-047 | B51: =Base_Datos!B53 -> Toallas de Papel x2 | C51: =Base_Datos!C53 -> Limpieza del Hogar | D51: =Base_Datos!G53 -> 10 | E51: =Base_Datos!P53 -> 10.333333 | F51: =IFERROR(Base_Datos!G53/(Base_Datos!P53/30),9999) -> 29.032258 | G51: =IFERROR(Base_Datos!O53/Base_Datos!G53,0) -> 6.2 | H51: =Base_Datos!S53 -> 34 | I51: =Base_Datos!H53 -> 5 | J51: =Base_Datos!R53 -> 57 | K51: =IF(IFERROR(Base_Datos!G53/(Base_Datos!P53/30),9999)<7,"🔴 QUIEBRE",IF(IFERROR(Base_Datos!G53/(Base_Datos!P53/30),9999)<14,"🟡 CRÍTICO",IF(IFERROR(Base_Datos!G53/(Base_Datos!P53/30),9999)<=90,"🟢 NORMAL",IF(IFERROR(Base_Datos!G53/(Base_Datos!P53/30),9999)<=180,"🟡 SOBRESTOCK","🔴 STOCK MUERTO")))) -> 🟢 NORMAL | L51: =IF(F51<7,"⚠ SÍ","—") -> — | M51: =IF(E51>=PERCENTILE($E$5:$E$79,0.8),"A",IF(E51>=PERCENTILE($E$5:$E$79,0.5),"B","C")) -> C | N51: =IFERROR(Base_Datos!O53/Base_Datos!O83,0) -> 0.0012570201 | O51: =IF(F51<7,"REPOSICIÓN URGENTE",IF(F51<14,"Revisar orden de compra",IF(AND(F51>180,J51>60),"LIQUIDAR / DEVOLVER",IF(F51>90,"Reducir próxima compra","Stock en niveles óptimos")))) -> Stock en niveles óptimos | P51: =IF(F51<7,1,IF(AND(F51>180,J51>60),2,IF(F51<14,3,IF(F51>90,4,5)))) -> 5
A52: =Base_Datos!A54 -> SKU-048 | B52: =Base_Datos!B54 -> Repasador x2 | C52: =Base_Datos!C54 -> Limpieza del Hogar | D52: =Base_Datos!G54 -> 229 | E52: =Base_Datos!P54 -> 1.6666667 | F52: =IFERROR(Base_Datos!G54/(Base_Datos!P54/30),9999) -> 4122 | G52: =IFERROR(Base_Datos!O54/Base_Datos!G54,0) -> 0.043668122 | H52: =Base_Datos!S54 -> 961.8 | I52: =Base_Datos!H54 -> 5 | J52: =Base_Datos!R54 -> 116 | K52: =IF(IFERROR(Base_Datos!G54/(Base_Datos!P54/30),9999)<7,"🔴 QUIEBRE",IF(IFERROR(Base_Datos!G54/(Base_Datos!P54/30),9999)<14,"🟡 CRÍTICO",IF(IFERROR(Base_Datos!G54/(Base_Datos!P54/30),9999)<=90,"🟢 NORMAL",IF(IFERROR(Base_Datos!G54/(Base_Datos!P54/30),9999)<=180,"🟡 SOBRESTOCK","🔴 STOCK MUERTO")))) -> 🔴 STOCK MUERTO | L52: =IF(F52<7,"⚠ SÍ","—") -> — | M52: =IF(E52>=PERCENTILE($E$5:$E$79,0.8),"A",IF(E52>=PERCENTILE($E$5:$E$79,0.5),"B","C")) -> C | N52: =IFERROR(Base_Datos!O54/Base_Datos!O83,0) -> 0.00020274517 | O52: =IF(F52<7,"REPOSICIÓN URGENTE",IF(F52<14,"Revisar orden de compra",IF(AND(F52>180,J52>60),"LIQUIDAR / DEVOLVER",IF(F52>90,"Reducir próxima compra","Stock en niveles óptimos")))) -> LIQUIDAR / DEVOLVER | P52: =IF(F52<7,1,IF(AND(F52>180,J52>60),2,IF(F52<14,3,IF(F52>90,4,5)))) -> 2
A53: =Base_Datos!A55 -> SKU-049 | B53: =Base_Datos!B55 -> Guantes de Látex Talle M | C53: =Base_Datos!C55 -> Limpieza del Hogar | D53: =Base_Datos!G55 -> 259 | E53: =Base_Datos!P55 -> 159.83333 | F53: =IFERROR(Base_Datos!G55/(Base_Datos!P55/30),9999) -> 48.613139 | G53: =IFERROR(Base_Datos!O55/Base_Datos!G55,0) -> 3.7027027 | H53: =Base_Datos!S55 -> 673.4 | I53: =Base_Datos!H55 -> 33 | J53: =Base_Datos!R55 -> 22 | K53: =IF(IFERROR(Base_Datos!G55/(Base_Datos!P55/30),9999)<7,"🔴 QUIEBRE",IF(IFERROR(Base_Datos!G55/(Base_Datos!P55/30),9999)<14,"🟡 CRÍTICO",IF(IFERROR(Base_Datos!G55/(Base_Datos!P55/30),9999)<=90,"🟢 NORMAL",IF(IFERROR(Base_Datos!G55/(Base_Datos!P55/30),9999)<=180,"🟡 SOBRESTOCK","🔴 STOCK MUERTO")))) -> 🟢 NORMAL | L53: =IF(F53<7,"⚠ SÍ","—") -> — | M53: =IF(E53>=PERCENTILE($E$5:$E$79,0.8),"A",IF(E53>=PERCENTILE($E$5:$E$79,0.5),"B","C")) -> B | N53: =IFERROR(Base_Datos!O55/Base_Datos!O83,0) -> 0.019443262 | O53: =IF(F53<7,"REPOSICIÓN URGENTE",IF(F53<14,"Revisar orden de compra",IF(AND(F53>180,J53>60),"LIQUIDAR / DEVOLVER",IF(F53>90,"Reducir próxima compra","Stock en niveles óptimos")))) -> Stock en niveles óptimos | P53: =IF(F53<7,1,IF(AND(F53>180,J53>60),2,IF(F53<14,3,IF(F53>90,4,5)))) -> 5
A54: =Base_Datos!A56 -> SKU-050 | B54: =Base_Datos!B56 -> Guantes de Látex Talle G | C54: =Base_Datos!C56 -> Limpieza del Hogar | D54: =Base_Datos!G56 -> 309 | E54: =Base_Datos!P56 -> 171.16667 | F54: =IFERROR(Base_Datos!G56/(Base_Datos!P56/30),9999) -> 54.157741 | G54: =IFERROR(Base_Datos!O56/Base_Datos!G56,0) -> 3.3236246 | H54: =Base_Datos!S56 -> 803.4 | I54: =Base_Datos!H56 -> 42 | J54: =Base_Datos!R56 -> 3 | K54: =IF(IFERROR(Base_Datos!G56/(Base_Datos!P56/30),9999)<7,"🔴 QUIEBRE",IF(IFERROR(Base_Datos!G56/(Base_Datos!P56/30),9999)<14,"🟡 CRÍTICO",IF(IFERROR(Base_Datos!G56/(Base_Datos!P56/30),9999)<=90,"🟢 NORMAL",IF(IFERROR(Base_Datos!G56/(Base_Datos!P56/30),9999)<=180,"🟡 SOBRESTOCK","🔴 STOCK MUERTO")))) -> 🟢 NORMAL | L54: =IF(F54<7,"⚠ SÍ","—") -> — | M54: =IF(E54>=PERCENTILE($E$5:$E$79,0.8),"A",IF(E54>=PERCENTILE($E$5:$E$79,0.5),"B","C")) -> A | N54: =IFERROR(Base_Datos!O56/Base_Datos!O83,0) -> 0.020821929 | O54: =IF(F54<7,"REPOSICIÓN URGENTE",IF(F54<14,"Revisar orden de compra",IF(AND(F54>180,J54>60),"LIQUIDAR / DEVOLVER",IF(F54>90,"Reducir próxima compra","Stock en niveles óptimos")))) -> Stock en niveles óptimos | P54: =IF(F54<7,1,IF(AND(F54>180,J54>60),2,IF(F54<14,3,IF(F54>90,4,5)))) -> 5
A55: =Base_Datos!A58 -> SKU-051 | B55: =Base_Datos!B58 -> Jabón de Tocador x3 | C55: =Base_Datos!C58 -> Higiene Personal | D55: =Base_Datos!G58 -> 848 | E55: =Base_Datos!P58 -> 132.5 | F55: =IFERROR(Base_Datos!G58/(Base_Datos!P58/30),9999) -> 192 | G55: =IFERROR(Base_Datos!O58/Base_Datos!G58,0) -> 0.9375 | H55: =Base_Datos!S58 -> 2713.6 | I55: =Base_Datos!H58 -> 27 | J55: =Base_Datos!R58 -> 25 | K55: =IF(IFERROR(Base_Datos!G58/(Base_Datos!P58/30),9999)<7,"🔴 QUIEBRE",IF(IFERROR(Base_Datos!G58/(Base_Datos!P58/30),9999)<14,"🟡 CRÍTICO",IF(IFERROR(Base_Datos!G58/(Base_Datos!P58/30),9999)<=90,"🟢 NORMAL",IF(IFERROR(Base_Datos!G58/(Base_Datos!P58/30),9999)<=180,"🟡 SOBRESTOCK","🔴 STOCK MUERTO")))) -> 🔴 STOCK MUERTO | L55: =IF(F55<7,"⚠ SÍ","—") -> — | M55: =IF(E55>=PERCENTILE($E$5:$E$79,0.8),"A",IF(E55>=PERCENTILE($E$5:$E$79,0.5),"B","C")) -> B | N55: =IFERROR(Base_Datos!O58/Base_Datos!O83,0) -> 0.016118241 | O55: =IF(F55<7,"REPOSICIÓN URGENTE",IF(F55<14,"Revisar orden de compra",IF(AND(F55>180,J55>60),"LIQUIDAR / DEVOLVER",IF(F55>90,"Reducir próxima compra","Stock en niveles óptimos")))) -> Reducir próxima compra | P55: =IF(F55<7,1,IF(AND(F55>180,J55>60),2,IF(F55<14,3,IF(F55>90,4,5)))) -> 4
A56: =Base_Datos!A59 -> SKU-052 | B56: =Base_Datos!B59 -> Jabón Líquido 300ml | C56: =Base_Datos!C59 -> Higiene Personal | D56: =Base_Datos!G59 -> 31 | E56: =Base_Datos!P59 -> 16.5 | F56: =IFERROR(Base_Datos!G59/(Base_Datos!P59/30),9999) -> 56.363636 | G56: =IFERROR(Base_Datos!O59/Base_Datos!G59,0) -> 3.1935484 | H56: =Base_Datos!S59 -> 139.5 | I56: =Base_Datos!H59 -> 5 | J56: =Base_Datos!R59 -> 55 | K56: =IF(IFERROR(Base_Datos!G59/(Base_Datos!P59/30),9999)<7,"🔴 QUIEBRE",IF(IFERROR(Base_Datos!G59/(Base_Datos!P59/30),9999)<14,"🟡 CRÍTICO",IF(IFERROR(Base_Datos!G59/(Base_Datos!P59/30),9999)<=90,"🟢 NORMAL",IF(IFERROR(Base_Datos!G59/(Base_Datos!P59/30),9999)<=180,"🟡 SOBRESTOCK","🔴 STOCK MUERTO")))) -> 🟢 NORMAL | L56: =IF(F56<7,"⚠ SÍ","—") -> — | M56: =IF(E56>=PERCENTILE($E$5:$E$79,0.8),"A",IF(E56>=PERCENTILE($E$5:$E$79,0.5),"B","C")) -> C | N56: =IFERROR(Base_Datos!O59/Base_Datos!O83,0) -> 0.0020071772 | O56: =IF(F56<7,"REPOSICIÓN URGENTE",IF(F56<14,"Revisar orden de compra",IF(AND(F56>180,J56>60),"LIQUIDAR / DEVOLVER",IF(F56>90,"Reducir próxima compra","Stock en niveles óptimos")))) -> Stock en niveles óptimos | P56: =IF(F56<7,1,IF(AND(F56>180,J56>60),2,IF(F56<14,3,IF(F56>90,4,5)))) -> 5
A57: =Base_Datos!A60 -> SKU-053 | B57: =Base_Datos!B60 -> Shampoo 400ml | C57: =Base_Datos!C60 -> Higiene Personal | D57: =Base_Datos!G60 -> 91 | E57: =Base_Datos!P60 -> 47 | F57: =IFERROR(Base_Datos!G60/(Base_Datos!P60/30),9999) -> 58.085106 | G57: =IFERROR(Base_Datos!O60/Base_Datos!G60,0) -> 3.0989011 | H57: =Base_Datos!S60 -> 527.8 | I57: =Base_Datos!H60 -> 11 | J57: =Base_Datos!R60 -> 7 | K57: =IF(IFERROR(Base_Datos!G60/(Base_Datos!P60/30),9999)<7,"🔴 QUIEBRE",IF(IFERROR(Base_Datos!G60/(Base_Datos!P60/30),9999)<14,"🟡 CRÍTICO",IF(IFERROR(Base_Datos!G60/(Base_Datos!P60/30),9999)<=90,"🟢 NORMAL",IF(IFERROR(Base_Datos!G60/(Base_Datos!P60/30),9999)<=180,"🟡 SOBRESTOCK","🔴 STOCK MUERTO")))) -> 🟢 NORMAL | L57: =IF(F57<7,"⚠ SÍ","—") -> — | M57: =IF(E57>=PERCENTILE($E$5:$E$79,0.8),"A",IF(E57>=PERCENTILE($E$5:$E$79,0.5),"B","C")) -> C | N57: =IFERROR(Base_Datos!O60/Base_Datos!O83,0) -> 0.0057174138 | O57: =IF(F57<7,"REPOSICIÓN URGENTE",IF(F57<14,"Revisar orden de compra",IF(AND(F57>180,J57>60),"LIQUIDAR / DEVOLVER",IF(F57>90,"Reducir próxima compra","Stock en niveles óptimos")))) -> Stock en niveles óptimos | P57: =IF(F57<7,1,IF(AND(F57>180,J57>60),2,IF(F57<14,3,IF(F57>90,4,5)))) -> 5
A58: =Base_Datos!A61 -> SKU-054 | B58: =Base_Datos!B61 -> Acondicionador 400ml | C58: =Base_Datos!C61 -> Higiene Personal | D58: =Base_Datos!G61 -> 359 | E58: =Base_Datos!P61 -> 164 | F58: =IFERROR(Base_Datos!G61/(Base_Datos!P61/30),9999) -> 65.670732 | G58: =IFERROR(Base_Datos!O61/Base_Datos!G61,0) -> 2.7409471 | H58: =Base_Datos!S61 -> 2082.2 | I58: =Base_Datos!H61 -> 48 | J58: =Base_Datos!R61 -> 4 | K58: =IF(IFERROR(Base_Datos!G61/(Base_Datos!P61/30),9999)<7,"🔴 QUIEBRE",IF(IFERROR(Base_Datos!G61/(Base_Datos!P61/30),9999)<14,"🟡 CRÍTICO",IF(IFERROR(Base_Datos!G61/(Base_Datos!P61/30),9999)<=90,"🟢 NORMAL",IF(IFERROR(Base_Datos!G61/(Base_Datos!P61/30),9999)<=180,"🟡 SOBRESTOCK","🔴 STOCK MUERTO")))) -> 🟢 NORMAL | L58: =IF(F58<7,"⚠ SÍ","—") -> — | M58: =IF(E58>=PERCENTILE($E$5:$E$79,0.8),"A",IF(E58>=PERCENTILE($E$5:$E$79,0.5),"B","C")) -> A | N58: =IFERROR(Base_Datos!O61/Base_Datos!O83,0) -> 0.019950125 | O58: =IF(F58<7,"REPOSICIÓN URGENTE",IF(F58<14,"Revisar orden de compra",IF(AND(F58>180,J58>60),"LIQUIDAR / DEVOLVER",IF(F58>90,"Reducir próxima compra","Stock en niveles óptimos")))) -> Stock en niveles óptimos | P58: =IF(F58<7,1,IF(AND(F58>180,J58>60),2,IF(F58<14,3,IF(F58>90,4,5)))) -> 5
A59: =Base_Datos!A62 -> SKU-055 | B59: =Base_Datos!B62 -> Pasta Dental 90g | C59: =Base_Datos!C62 -> Higiene Personal | D59: =Base_Datos!G62 -> 20 | E59: =Base_Datos!P62 -> 307.16667 | F59: =IFERROR(Base_Datos!G62/(Base_Datos!P62/30),9999) -> 1.953337 | G59: =IFERROR(Base_Datos!O62/Base_Datos!G62,0) -> 92.15 | H59: =Base_Datos!S62 -> 48 | I59: =Base_Datos!H62 -> 77 | J59: =Base_Datos!R62 -> 21 | K59: =IF(IFERROR(Base_Datos!G62/(Base_Datos!P62/30),9999)<7,"🔴 QUIEBRE",IF(IFERROR(Base_Datos!G62/(Base_Datos!P62/30),9999)<14,"🟡 CRÍTICO",IF(IFERROR(Base_Datos!G62/(Base_Datos!P62/30),9999)<=90,"🟢 NORMAL",IF(IFERROR(Base_Datos!G62/(Base_Datos!P62/30),9999)<=180,"🟡 SOBRESTOCK","🔴 STOCK MUERTO")))) -> 🔴 QUIEBRE | L59: =IF(F59<7,"⚠ SÍ","—") -> ⚠ SÍ | M59: =IF(E59>=PERCENTILE($E$5:$E$79,0.8),"A",IF(E59>=PERCENTILE($E$5:$E$79,0.5),"B","C")) -> A | N59: =IFERROR(Base_Datos!O62/Base_Datos!O83,0) -> 0.037365935 | O59: =IF(F59<7,"REPOSICIÓN URGENTE",IF(F59<14,"Revisar orden de compra",IF(AND(F59>180,J59>60),"LIQUIDAR / DEVOLVER",IF(F59>90,"Reducir próxima compra","Stock en niveles óptimos")))) -> REPOSICIÓN URGENTE | P59: =IF(F59<7,1,IF(AND(F59>180,J59>60),2,IF(F59<14,3,IF(F59>90,4,5)))) -> 1
A60: =Base_Datos!A63 -> SKU-056 | B60: =Base_Datos!B63 -> Pasta Dental 150g | C60: =Base_Datos!C63 -> Higiene Personal | D60: =Base_Datos!G63 -> 230 | E60: =Base_Datos!P63 -> 108.16667 | F60: =IFERROR(Base_Datos!G63/(Base_Datos!P63/30),9999) -> 63.790447 | G60: =IFERROR(Base_Datos!O63/Base_Datos!G63,0) -> 2.8217391 | H60: =Base_Datos!S63 -> 874 | I60: =Base_Datos!H63 -> 21 | J60: =Base_Datos!R63 -> 14 | K60: =IF(IFERROR(Base_Datos!G63/(Base_Datos!P63/30),9999)<7,"🔴 QUIEBRE",IF(IFERROR(Base_Datos!G63/(Base_Datos!P63/30),9999)<14,"🟡 CRÍTICO",IF(IFERROR(Base_Datos!G63/(Base_Datos!P63/30),9999)<=90,"🟢 NORMAL",IF(IFERROR(Base_Datos!G63/(Base_Datos!P63/30),9999)<=180,"🟡 SOBRESTOCK","🔴 STOCK MUERTO")))) -> 🟢 NORMAL | L60: =IF(F60<7,"⚠ SÍ","—") -> — | M60: =IF(E60>=PERCENTILE($E$5:$E$79,0.8),"A",IF(E60>=PERCENTILE($E$5:$E$79,0.5),"B","C")) -> B | N60: =IFERROR(Base_Datos!O63/Base_Datos!O83,0) -> 0.013158162 | O60: =IF(F60<7,"REPOSICIÓN URGENTE",IF(F60<14,"Revisar orden de compra",IF(AND(F60>180,J60>60),"LIQUIDAR / DEVOLVER",IF(F60>90,"Reducir próxima compra","Stock en niveles óptimos")))) -> Stock en niveles óptimos | P60: =IF(F60<7,1,IF(AND(F60>180,J60>60),2,IF(F60<14,3,IF(F60>90,4,5)))) -> 5
A61: =Base_Datos!A64 -> SKU-057 | B61: =Base_Datos!B64 -> Cepillo de Dientes x2 | C61: =Base_Datos!C64 -> Higiene Personal | D61: =Base_Datos!G64 -> 678 | E61: =Base_Datos!P64 -> 125.5 | F61: =IFERROR(Base_Datos!G64/(Base_Datos!P64/30),9999) -> 162.07171 | G61: =IFERROR(Base_Datos!O64/Base_Datos!G64,0) -> 1.1106195 | H61: =Base_Datos!S64 -> 2440.8 | I61: =Base_Datos!H64 -> 35 | J61: =Base_Datos!R64 -> 15 | K61: =IF(IFERROR(Base_Datos!G64/(Base_Datos!P64/30),9999)<7,"🔴 QUIEBRE",IF(IFERROR(Base_Datos!G64/(Base_Datos!P64/30),9999)<14,"🟡 CRÍTICO",IF(IFERROR(Base_Datos!G64/(Base_Datos!P64/30),9999)<=90,"🟢 NORMAL",IF(IFERROR(Base_Datos!G64/(Base_Datos!P64/30),9999)<=180,"🟡 SOBRESTOCK","🔴 STOCK MUERTO")))) -> 🟡 SOBRESTOCK | L61: =IF(F61<7,"⚠ SÍ","—") -> — | M61: =IF(E61>=PERCENTILE($E$5:$E$79,0.8),"A",IF(E61>=PERCENTILE($E$5:$E$79,0.5),"B","C")) -> B | N61: =IFERROR(Base_Datos!O64/Base_Datos!O83,0) -> 0.015266711 | O61: =IF(F61<7,"REPOSICIÓN URGENTE",IF(F61<14,"Revisar orden de compra",IF(AND(F61>180,J61>60),"LIQUIDAR / DEVOLVER",IF(F61>90,"Reducir próxima compra","Stock en niveles óptimos")))) -> Reducir próxima compra | P61: =IF(F61<7,1,IF(AND(F61>180,J61>60),2,IF(F61<14,3,IF(F61>90,4,5)))) -> 4
A62: =Base_Datos!A65 -> SKU-058 | B62: =Base_Datos!B65 -> Desodorante Roll-On 65ml | C62: =Base_Datos!C65 -> Higiene Personal | D62: =Base_Datos!G65 -> 139 | E62: =Base_Datos!P65 -> 86 | F62: =IFERROR(Base_Datos!G65/(Base_Datos!P65/30),9999) -> 48.488372 | G62: =IFERROR(Base_Datos!O65/Base_Datos!G65,0) -> 3.7122302 | H62: =Base_Datos!S65 -> 542.1 | I62: =Base_Datos!H65 -> 18 | J62: =Base_Datos!R65 -> 24 | K62: =IF(IFERROR(Base_Datos!G65/(Base_Datos!P65/30),9999)<7,"🔴 QUIEBRE",IF(IFERROR(Base_Datos!G65/(Base_Datos!P65/30),9999)<14,"🟡 CRÍTICO",IF(IFERROR(Base_Datos!G65/(Base_Datos!P65/30),9999)<=90,"🟢 NORMAL",IF(IFERROR(Base_Datos!G65/(Base_Datos!P65/30),9999)<=180,"🟡 SOBRESTOCK","🔴 STOCK MUERTO")))) -> 🟢 NORMAL | L62: =IF(F62<7,"⚠ SÍ","—") -> — | M62: =IF(E62>=PERCENTILE($E$5:$E$79,0.8),"A",IF(E62>=PERCENTILE($E$5:$E$79,0.5),"B","C")) -> C | N62: =IFERROR(Base_Datos!O65/Base_Datos!O83,0) -> 0.010461651 | O62: =IF(F62<7,"REPOSICIÓN URGENTE",IF(F62<14,"Revisar orden de compra",IF(AND(F62>180,J62>60),"LIQUIDAR / DEVOLVER",IF(F62>90,"Reducir próxima compra","Stock en niveles óptimos")))) -> Stock en niveles óptimos | P62: =IF(F62<7,1,IF(AND(F62>180,J62>60),2,IF(F62<14,3,IF(F62>90,4,5)))) -> 5
A63: =Base_Datos!A66 -> SKU-059 | B63: =Base_Datos!B66 -> Desodorante Aerosol 150ml | C63: =Base_Datos!C66 -> Higiene Personal | D63: =Base_Datos!G66 -> 194 | E63: =Base_Datos!P66 -> 110 | F63: =IFERROR(Base_Datos!G66/(Base_Datos!P66/30),9999) -> 52.909091 | G63: =IFERROR(Base_Datos!O66/Base_Datos!G66,0) -> 3.4020619 | H63: =Base_Datos!S66 -> 1008.8 | I63: =Base_Datos!H66 -> 27 | J63: =Base_Datos!R66 -> 11 | K63: =IF(IFERROR(Base_Datos!G66/(Base_Datos!P66/30),9999)<7,"🔴 QUIEBRE",IF(IFERROR(Base_Datos!G66/(Base_Datos!P66/30),9999)<14,"🟡 CRÍTICO",IF(IFERROR(Base_Datos!G66/(Base_Datos!P66/30),9999)<=90,"🟢 NORMAL",IF(IFERROR(Base_Datos!G66/(Base_Datos!P66/30),9999)<=180,"🟡 SOBRESTOCK","🔴 STOCK MUERTO")))) -> 🟢 NORMAL | L63: =IF(F63<7,"⚠ SÍ","—") -> — | M63: =IF(E63>=PERCENTILE($E$5:$E$79,0.8),"A",IF(E63>=PERCENTILE($E$5:$E$79,0.5),"B","C")) -> B | N63: =IFERROR(Base_Datos!O66/Base_Datos!O83,0) -> 0.013381181 | O63: =IF(F63<7,"REPOSICIÓN URGENTE",IF(F63<14,"Revisar orden de compra",IF(AND(F63>180,J63>60),"LIQUIDAR / DEVOLVER",IF(F63>90,"Reducir próxima compra","Stock en niveles óptimos")))) -> Stock en niveles óptimos | P63: =IF(F63<7,1,IF(AND(F63>180,J63>60),2,IF(F63<14,3,IF(F63>90,4,5)))) -> 5
A64: =Base_Datos!A67 -> SKU-060 | B64: =Base_Datos!B67 -> Crema Corporal 200ml | C64: =Base_Datos!C67 -> Higiene Personal | D64: =Base_Datos!G67 -> 7 | E64: =Base_Datos!P67 -> 4.3333333 | F64: =IFERROR(Base_Datos!G67/(Base_Datos!P67/30),9999) -> 48.461538 | G64: =IFERROR(Base_Datos!O67/Base_Datos!G67,0) -> 3.7142857 | H64: =Base_Datos!S67 -> 44.8 | I64: =Base_Datos!H67 -> 5 | J64: =Base_Datos!R67 -> 52 | K64: =IF(IFERROR(Base_Datos!G67/(Base_Datos!P67/30),9999)<7,"🔴 QUIEBRE",IF(IFERROR(Base_Datos!G67/(Base_Datos!P67/30),9999)<14,"🟡 CRÍTICO",IF(IFERROR(Base_Datos!G67/(Base_Datos!P67/30),9999)<=90,"🟢 NORMAL",IF(IFERROR(Base_Datos!G67/(Base_Datos!P67/30),9999)<=180,"🟡 SOBRESTOCK","🔴 STOCK MUERTO")))) -> 🟢 NORMAL | L64: =IF(F64<7,"⚠ SÍ","—") -> — | M64: =IF(E64>=PERCENTILE($E$5:$E$79,0.8),"A",IF(E64>=PERCENTILE($E$5:$E$79,0.5),"B","C")) -> C | N64: =IFERROR(Base_Datos!O67/Base_Datos!O83,0) -> 0.00052713744 | O64: =IF(F64<7,"REPOSICIÓN URGENTE",IF(F64<14,"Revisar orden de compra",IF(AND(F64>180,J64>60),"LIQUIDAR / DEVOLVER",IF(F64>90,"Reducir próxima compra","Stock en niveles óptimos")))) -> Stock en niveles óptimos | P64: =IF(F64<7,1,IF(AND(F64>180,J64>60),2,IF(F64<14,3,IF(F64>90,4,5)))) -> 5
A65: =Base_Datos!A68 -> SKU-061 | B65: =Base_Datos!B68 -> Crema de Manos 100ml | C65: =Base_Datos!C68 -> Higiene Personal | D65: =Base_Datos!G68 -> 205 | E65: =Base_Datos!P68 -> 1.5 | F65: =IFERROR(Base_Datos!G68/(Base_Datos!P68/30),9999) -> 4100 | G65: =IFERROR(Base_Datos!O68/Base_Datos!G68,0) -> 0.043902439 | H65: =Base_Datos!S68 -> 779 | I65: =Base_Datos!H68 -> 5 | J65: =Base_Datos!R68 -> 81 | K65: =IF(IFERROR(Base_Datos!G68/(Base_Datos!P68/30),9999)<7,"🔴 QUIEBRE",IF(IFERROR(Base_Datos!G68/(Base_Datos!P68/30),9999)<14,"🟡 CRÍTICO",IF(IFERROR(Base_Datos!G68/(Base_Datos!P68/30),9999)<=90,"🟢 NORMAL",IF(IFERROR(Base_Datos!G68/(Base_Datos!P68/30),9999)<=180,"🟡 SOBRESTOCK","🔴 STOCK MUERTO")))) -> 🔴 STOCK MUERTO | L65: =IF(F65<7,"⚠ SÍ","—") -> — | M65: =IF(E65>=PERCENTILE($E$5:$E$79,0.8),"A",IF(E65>=PERCENTILE($E$5:$E$79,0.5),"B","C")) -> C | N65: =IFERROR(Base_Datos!O68/Base_Datos!O83,0) -> 0.00018247065 | O65: =IF(F65<7,"REPOSICIÓN URGENTE",IF(F65<14,"Revisar orden de compra",IF(AND(F65>180,J65>60),"LIQUIDAR / DEVOLVER",IF(F65>90,"Reducir próxima compra","Stock en niveles óptimos")))) -> LIQUIDAR / DEVOLVER | P65: =IF(F65<7,1,IF(AND(F65>180,J65>60),2,IF(F65<14,3,IF(F65>90,4,5)))) -> 2
A66: =Base_Datos!A69 -> SKU-062 | B66: =Base_Datos!B69 -> Protector Solar FPS50 150ml | C66: =Base_Datos!C69 -> Higiene Personal | D66: =Base_Datos!G69 -> 175 | E66: =Base_Datos!P69 -> 139.33333 | F66: =IFERROR(Base_Datos!G69/(Base_Datos!P69/30),9999) -> 37.679426 | G66: =IFERROR(Base_Datos!O69/Base_Datos!G69,0) -> 4.7771429 | H66: =Base_Datos!S69 -> 1557.5 | I66: =Base_Datos!H69 -> 26 | J66: =Base_Datos!R69 -> 4 | K66: =IF(IFERROR(Base_Datos!G69/(Base_Datos!P69/30),9999)<7,"🔴 QUIEBRE",IF(IFERROR(Base_Datos!G69/(Base_Datos!P69/30),9999)<14,"🟡 CRÍTICO",IF(IFERROR(Base_Datos!G69/(Base_Datos!P69/30),9999)<=90,"🟢 NORMAL",IF(IFERROR(Base_Datos!G69/(Base_Datos!P69/30),9999)<=180,"🟡 SOBRESTOCK","🔴 STOCK MUERTO")))) -> 🟢 NORMAL | L66: =IF(F66<7,"⚠ SÍ","—") -> — | M66: =IF(E66>=PERCENTILE($E$5:$E$79,0.8),"A",IF(E66>=PERCENTILE($E$5:$E$79,0.5),"B","C")) -> B | N66: =IFERROR(Base_Datos!O69/Base_Datos!O83,0) -> 0.016949496 | O66: =IF(F66<7,"REPOSICIÓN URGENTE",IF(F66<14,"Revisar orden de compra",IF(AND(F66>180,J66>60),"LIQUIDAR / DEVOLVER",IF(F66>90,"Reducir próxima compra","Stock en niveles óptimos")))) -> Stock en niveles óptimos | P66: =IF(F66<7,1,IF(AND(F66>180,J66>60),2,IF(F66<14,3,IF(F66>90,4,5)))) -> 5
A67: =Base_Datos!A70 -> SKU-063 | B67: =Base_Datos!B70 -> Papel Higiénico Húmedo x40 | C67: =Base_Datos!C70 -> Higiene Personal | D67: =Base_Datos!G70 -> 498 | E67: =Base_Datos!P70 -> 96 | F67: =IFERROR(Base_Datos!G70/(Base_Datos!P70/30),9999) -> 155.625 | G67: =IFERROR(Base_Datos!O70/Base_Datos!G70,0) -> 1.1566265 | H67: =Base_Datos!S70 -> 2091.6 | I67: =Base_Datos!H70 -> 22 | J67: =Base_Datos!R70 -> 25 | K67: =IF(IFERROR(Base_Datos!G70/(Base_Datos!P70/30),9999)<7,"🔴 QUIEBRE",IF(IFERROR(Base_Datos!G70/(Base_Datos!P70/30),9999)<14,"🟡 CRÍTICO",IF(IFERROR(Base_Datos!G70/(Base_Datos!P70/30),9999)<=90,"🟢 NORMAL",IF(IFERROR(Base_Datos!G70/(Base_Datos!P70/30),9999)<=180,"🟡 SOBRESTOCK","🔴 STOCK MUERTO")))) -> 🟡 SOBRESTOCK | L67: =IF(F67<7,"⚠ SÍ","—") -> — | M67: =IF(E67>=PERCENTILE($E$5:$E$79,0.8),"A",IF(E67>=PERCENTILE($E$5:$E$79,0.5),"B","C")) -> C | N67: =IFERROR(Base_Datos!O70/Base_Datos!O83,0) -> 0.011678122 | O67: =IF(F67<7,"REPOSICIÓN URGENTE",IF(F67<14,"Revisar orden de compra",IF(AND(F67>180,J67>60),"LIQUIDAR / DEVOLVER",IF(F67>90,"Reducir próxima compra","Stock en niveles óptimos")))) -> Reducir próxima compra | P67: =IF(F67<7,1,IF(AND(F67>180,J67>60),2,IF(F67<14,3,IF(F67>90,4,5)))) -> 4
A68: =Base_Datos!A71 -> SKU-064 | B68: =Base_Datos!B71 -> Algodón 100g | C68: =Base_Datos!C71 -> Higiene Personal | D68: =Base_Datos!G71 -> 368 | E68: =Base_Datos!P71 -> 183.83333 | F68: =IFERROR(Base_Datos!G71/(Base_Datos!P71/30),9999) -> 60.054397 | G68: =IFERROR(Base_Datos!O71/Base_Datos!G71,0) -> 2.9972826 | H68: =Base_Datos!S71 -> 772.8 | I68: =Base_Datos!H71 -> 31 | J68: =Base_Datos!R71 -> 2 | K68: =IF(IFERROR(Base_Datos!G71/(Base_Datos!P71/30),9999)<7,"🔴 QUIEBRE",IF(IFERROR(Base_Datos!G71/(Base_Datos!P71/30),9999)<14,"🟡 CRÍTICO",IF(IFERROR(Base_Datos!G71/(Base_Datos!P71/30),9999)<=90,"🟢 NORMAL",IF(IFERROR(Base_Datos!G71/(Base_Datos!P71/30),9999)<=180,"🟡 SOBRESTOCK","🔴 STOCK MUERTO")))) -> 🟢 NORMAL | L68: =IF(F68<7,"⚠ SÍ","—") -> — | M68: =IF(E68>=PERCENTILE($E$5:$E$79,0.8),"A",IF(E68>=PERCENTILE($E$5:$E$79,0.5),"B","C")) -> A | N68: =IFERROR(Base_Datos!O71/Base_Datos!O83,0) -> 0.022362792 | O68: =IF(F68<7,"REPOSICIÓN URGENTE",IF(F68<14,"Revisar orden de compra",IF(AND(F68>180,J68>60),"LIQUIDAR / DEVOLVER",IF(F68>90,"Reducir próxima compra","Stock en niveles óptimos")))) -> Stock en niveles óptimos | P68: =IF(F68<7,1,IF(AND(F68>180,J68>60),2,IF(F68<14,3,IF(F68>90,4,5)))) -> 5
A69: =Base_Datos!A72 -> SKU-065 | B69: =Base_Datos!B72 -> Hisopos x100 | C69: =Base_Datos!C72 -> Higiene Personal | D69: =Base_Datos!G72 -> 10 | E69: =Base_Datos!P72 -> 6 | F69: =IFERROR(Base_Datos!G72/(Base_Datos!P72/30),9999) -> 50 | G69: =IFERROR(Base_Datos!O72/Base_Datos!G72,0) -> 3.6 | H69: =Base_Datos!S72 -> 18 | I69: =Base_Datos!H72 -> 5 | J69: =Base_Datos!R72 -> 49 | K69: =IF(IFERROR(Base_Datos!G72/(Base_Datos!P72/30),9999)<7,"🔴 QUIEBRE",IF(IFERROR(Base_Datos!G72/(Base_Datos!P72/30),9999)<14,"🟡 CRÍTICO",IF(IFERROR(Base_Datos!G72/(Base_Datos!P72/30),9999)<=90,"🟢 NORMAL",IF(IFERROR(Base_Datos!G72/(Base_Datos!P72/30),9999)<=180,"🟡 SOBRESTOCK","🔴 STOCK MUERTO")))) -> 🟢 NORMAL | L69: =IF(F69<7,"⚠ SÍ","—") -> — | M69: =IF(E69>=PERCENTILE($E$5:$E$79,0.8),"A",IF(E69>=PERCENTILE($E$5:$E$79,0.5),"B","C")) -> C | N69: =IFERROR(Base_Datos!O72/Base_Datos!O83,0) -> 0.00072988261 | O69: =IF(F69<7,"REPOSICIÓN URGENTE",IF(F69<14,"Revisar orden de compra",IF(AND(F69>180,J69>60),"LIQUIDAR / DEVOLVER",IF(F69>90,"Reducir próxima compra","Stock en niveles óptimos")))) -> Stock en niveles óptimos | P69: =IF(F69<7,1,IF(AND(F69>180,J69>60),2,IF(F69<14,3,IF(F69>90,4,5)))) -> 5
A70: =Base_Datos!A73 -> SKU-066 | B70: =Base_Datos!B73 -> Pañuelos Descartables x10 | C70: =Base_Datos!C73 -> Higiene Personal | D70: =Base_Datos!G73 -> 118 | E70: =Base_Datos!P73 -> 128.16667 | F70: =IFERROR(Base_Datos!G73/(Base_Datos!P73/30),9999) -> 27.620286 | G70: =IFERROR(Base_Datos!O73/Base_Datos!G73,0) -> 6.5169492 | H70: =Base_Datos!S73 -> 177 | I70: =Base_Datos!H73 -> 31 | J70: =Base_Datos!R73 -> 2 | K70: =IF(IFERROR(Base_Datos!G73/(Base_Datos!P73/30),9999)<7,"🔴 QUIEBRE",IF(IFERROR(Base_Datos!G73/(Base_Datos!P73/30),9999)<14,"🟡 CRÍTICO",IF(IFERROR(Base_Datos!G73/(Base_Datos!P73/30),9999)<=90,"🟢 NORMAL",IF(IFERROR(Base_Datos!G73/(Base_Datos!P73/30),9999)<=180,"🟡 SOBRESTOCK","🔴 STOCK MUERTO")))) -> 🟢 NORMAL | L70: =IF(F70<7,"⚠ SÍ","—") -> — | M70: =IF(E70>=PERCENTILE($E$5:$E$79,0.8),"A",IF(E70>=PERCENTILE($E$5:$E$79,0.5),"B","C")) -> B | N70: =IFERROR(Base_Datos!O73/Base_Datos!O83,0) -> 0.015591104 | O70: =IF(F70<7,"REPOSICIÓN URGENTE",IF(F70<14,"Revisar orden de compra",IF(AND(F70>180,J70>60),"LIQUIDAR / DEVOLVER",IF(F70>90,"Reducir próxima compra","Stock en niveles óptimos")))) -> Stock en niveles óptimos | P70: =IF(F70<7,1,IF(AND(F70>180,J70>60),2,IF(F70<14,3,IF(F70>90,4,5)))) -> 5
A71: =Base_Datos!A74 -> SKU-067 | B71: =Base_Datos!B74 -> Afeitadora Descartable x5 | C71: =Base_Datos!C74 -> Higiene Personal | D71: =Base_Datos!G74 -> 32 | E71: =Base_Datos!P74 -> 190.5 | F71: =IFERROR(Base_Datos!G74/(Base_Datos!P74/30),9999) -> 5.0393701 | G71: =IFERROR(Base_Datos!O74/Base_Datos!G74,0) -> 35.71875 | H71: =Base_Datos!S74 -> 153.6 | I71: =Base_Datos!H74 -> 51 | J71: =Base_Datos!R74 -> 8 | K71: =IF(IFERROR(Base_Datos!G74/(Base_Datos!P74/30),9999)<7,"🔴 QUIEBRE",IF(IFERROR(Base_Datos!G74/(Base_Datos!P74/30),9999)<14,"🟡 CRÍTICO",IF(IFERROR(Base_Datos!G74/(Base_Datos!P74/30),9999)<=90,"🟢 NORMAL",IF(IFERROR(Base_Datos!G74/(Base_Datos!P74/30),9999)<=180,"🟡 SOBRESTOCK","🔴 STOCK MUERTO")))) -> 🔴 QUIEBRE | L71: =IF(F71<7,"⚠ SÍ","—") -> ⚠ SÍ | M71: =IF(E71>=PERCENTILE($E$5:$E$79,0.8),"A",IF(E71>=PERCENTILE($E$5:$E$79,0.5),"B","C")) -> A | N71: =IFERROR(Base_Datos!O74/Base_Datos!O83,0) -> 0.023173773 | O71: =IF(F71<7,"REPOSICIÓN URGENTE",IF(F71<14,"Revisar orden de compra",IF(AND(F71>180,J71>60),"LIQUIDAR / DEVOLVER",IF(F71>90,"Reducir próxima compra","Stock en niveles óptimos")))) -> REPOSICIÓN URGENTE | P71: =IF(F71<7,1,IF(AND(F71>180,J71>60),2,IF(F71<14,3,IF(F71>90,4,5)))) -> 1
A72: =Base_Datos!A75 -> SKU-068 | B72: =Base_Datos!B75 -> Espuma de Afeitar 200ml | C72: =Base_Datos!C75 -> Higiene Personal | D72: =Base_Datos!G75 -> 161 | E72: =Base_Datos!P75 -> 179.5 | F72: =IFERROR(Base_Datos!G75/(Base_Datos!P75/30),9999) -> 26.908078 | G72: =IFERROR(Base_Datos!O75/Base_Datos!G75,0) -> 6.689441 | H72: =Base_Datos!S75 -> 676.2 | I72: =Base_Datos!H75 -> 52 | J72: =Base_Datos!R75 -> 4 | K72: =IF(IFERROR(Base_Datos!G75/(Base_Datos!P75/30),9999)<7,"🔴 QUIEBRE",IF(IFERROR(Base_Datos!G75/(Base_Datos!P75/30),9999)<14,"🟡 CRÍTICO",IF(IFERROR(Base_Datos!G75/(Base_Datos!P75/30),9999)<=90,"🟢 NORMAL",IF(IFERROR(Base_Datos!G75/(Base_Datos!P75/30),9999)<=180,"🟡 SOBRESTOCK","🔴 STOCK MUERTO")))) -> 🟢 NORMAL | L72: =IF(F72<7,"⚠ SÍ","—") -> — | M72: =IF(E72>=PERCENTILE($E$5:$E$79,0.8),"A",IF(E72>=PERCENTILE($E$5:$E$79,0.5),"B","C")) -> A | N72: =IFERROR(Base_Datos!O75/Base_Datos!O83,0) -> 0.021835655 | O72: =IF(F72<7,"REPOSICIÓN URGENTE",IF(F72<14,"Revisar orden de compra",IF(AND(F72>180,J72>60),"LIQUIDAR / DEVOLVER",IF(F72>90,"Reducir próxima compra","Stock en niveles óptimos")))) -> Stock en niveles óptimos | P72: =IF(F72<7,1,IF(AND(F72>180,J72>60),2,IF(F72<14,3,IF(F72>90,4,5)))) -> 5
A73: =Base_Datos!A76 -> SKU-069 | B73: =Base_Datos!B76 -> Peine y Cepillo Set | C73: =Base_Datos!C76 -> Higiene Personal | D73: =Base_Datos!G76 -> 127 | E73: =Base_Datos!P76 -> 85.5 | F73: =IFERROR(Base_Datos!G76/(Base_Datos!P76/30),9999) -> 44.561404 | G73: =IFERROR(Base_Datos!O76/Base_Datos!G76,0) -> 4.0393701 | H73: =Base_Datos!S76 -> 698.5 | I73: =Base_Datos!H76 -> 21 | J73: =Base_Datos!R76 -> 16 | K73: =IF(IFERROR(Base_Datos!G76/(Base_Datos!P76/30),9999)<7,"🔴 QUIEBRE",IF(IFERROR(Base_Datos!G76/(Base_Datos!P76/30),9999)<14,"🟡 CRÍTICO",IF(IFERROR(Base_Datos!G76/(Base_Datos!P76/30),9999)<=90,"🟢 NORMAL",IF(IFERROR(Base_Datos!G76/(Base_Datos!P76/30),9999)<=180,"🟡 SOBRESTOCK","🔴 STOCK MUERTO")))) -> 🟢 NORMAL | L73: =IF(F73<7,"⚠ SÍ","—") -> — | M73: =IF(E73>=PERCENTILE($E$5:$E$79,0.8),"A",IF(E73>=PERCENTILE($E$5:$E$79,0.5),"B","C")) -> C | N73: =IFERROR(Base_Datos!O76/Base_Datos!O83,0) -> 0.010400827 | O73: =IF(F73<7,"REPOSICIÓN URGENTE",IF(F73<14,"Revisar orden de compra",IF(AND(F73>180,J73>60),"LIQUIDAR / DEVOLVER",IF(F73>90,"Reducir próxima compra","Stock en niveles óptimos")))) -> Stock en niveles óptimos | P73: =IF(F73<7,1,IF(AND(F73>180,J73>60),2,IF(F73<14,3,IF(F73>90,4,5)))) -> 5
A74: =Base_Datos!A77 -> SKU-070 | B74: =Base_Datos!B77 -> Toallas Femeninas x8 | C74: =Base_Datos!C77 -> Higiene Personal | D74: =Base_Datos!G77 -> 534 | E74: =Base_Datos!P77 -> 103.5 | F74: =IFERROR(Base_Datos!G77/(Base_Datos!P77/30),9999) -> 154.78261 | G74: =IFERROR(Base_Datos!O77/Base_Datos!G77,0) -> 1.1629213 | H74: =Base_Datos!S77 -> 1922.4 | I74: =Base_Datos!H77 -> 27 | J74: =Base_Datos!R77 -> 19 | K74: =IF(IFERROR(Base_Datos!G77/(Base_Datos!P77/30),9999)<7,"🔴 QUIEBRE",IF(IFERROR(Base_Datos!G77/(Base_Datos!P77/30),9999)<14,"🟡 CRÍTICO",IF(IFERROR(Base_Datos!G77/(Base_Datos!P77/30),9999)<=90,"🟢 NORMAL",IF(IFERROR(Base_Datos!G77/(Base_Datos!P77/30),9999)<=180,"🟡 SOBRESTOCK","🔴 STOCK MUERTO")))) -> 🟡 SOBRESTOCK | L74: =IF(F74<7,"⚠ SÍ","—") -> — | M74: =IF(E74>=PERCENTILE($E$5:$E$79,0.8),"A",IF(E74>=PERCENTILE($E$5:$E$79,0.5),"B","C")) -> B | N74: =IFERROR(Base_Datos!O77/Base_Datos!O83,0) -> 0.012590475 | O74: =IF(F74<7,"REPOSICIÓN URGENTE",IF(F74<14,"Revisar orden de compra",IF(AND(F74>180,J74>60),"LIQUIDAR / DEVOLVER",IF(F74>90,"Reducir próxima compra","Stock en niveles óptimos")))) -> Reducir próxima compra | P74: =IF(F74<7,1,IF(AND(F74>180,J74>60),2,IF(F74<14,3,IF(F74>90,4,5)))) -> 4
A75: =Base_Datos!A78 -> SKU-071 | B75: =Base_Datos!B78 -> Tampones x16 | C75: =Base_Datos!C78 -> Higiene Personal | D75: =Base_Datos!G78 -> 103 | E75: =Base_Datos!P78 -> 95.333333 | F75: =IFERROR(Base_Datos!G78/(Base_Datos!P78/30),9999) -> 32.412587 | G75: =IFERROR(Base_Datos!O78/Base_Datos!G78,0) -> 5.5533981 | H75: =Base_Datos!S78 -> 504.7 | I75: =Base_Datos!H78 -> 18 | J75: =Base_Datos!R78 -> 24 | K75: =IF(IFERROR(Base_Datos!G78/(Base_Datos!P78/30),9999)<7,"🔴 QUIEBRE",IF(IFERROR(Base_Datos!G78/(Base_Datos!P78/30),9999)<14,"🟡 CRÍTICO",IF(IFERROR(Base_Datos!G78/(Base_Datos!P78/30),9999)<=90,"🟢 NORMAL",IF(IFERROR(Base_Datos!G78/(Base_Datos!P78/30),9999)<=180,"🟡 SOBRESTOCK","🔴 STOCK MUERTO")))) -> 🟢 NORMAL | L75: =IF(F75<7,"⚠ SÍ","—") -> — | M75: =IF(E75>=PERCENTILE($E$5:$E$79,0.8),"A",IF(E75>=PERCENTILE($E$5:$E$79,0.5),"B","C")) -> C | N75: =IFERROR(Base_Datos!O78/Base_Datos!O83,0) -> 0.011597024 | O75: =IF(F75<7,"REPOSICIÓN URGENTE",IF(F75<14,"Revisar orden de compra",IF(AND(F75>180,J75>60),"LIQUIDAR / DEVOLVER",IF(F75>90,"Reducir próxima compra","Stock en niveles óptimos")))) -> Stock en niveles óptimos | P75: =IF(F75<7,1,IF(AND(F75>180,J75>60),2,IF(F75<14,3,IF(F75>90,4,5)))) -> 5
A76: =Base_Datos!A79 -> SKU-072 | B76: =Base_Datos!B79 -> Talco Corporal 100g | C76: =Base_Datos!C79 -> Higiene Personal | D76: =Base_Datos!G79 -> 38 | E76: =Base_Datos!P79 -> 22.666667 | F76: =IFERROR(Base_Datos!G79/(Base_Datos!P79/30),9999) -> 50.294118 | G76: =IFERROR(Base_Datos!O79/Base_Datos!G79,0) -> 3.5789474 | H76: =Base_Datos!S79 -> 117.8 | I76: =Base_Datos!H79 -> 5 | J76: =Base_Datos!R79 -> 54 | K76: =IF(IFERROR(Base_Datos!G79/(Base_Datos!P79/30),9999)<7,"🔴 QUIEBRE",IF(IFERROR(Base_Datos!G79/(Base_Datos!P79/30),9999)<14,"🟡 CRÍTICO",IF(IFERROR(Base_Datos!G79/(Base_Datos!P79/30),9999)<=90,"🟢 NORMAL",IF(IFERROR(Base_Datos!G79/(Base_Datos!P79/30),9999)<=180,"🟡 SOBRESTOCK","🔴 STOCK MUERTO")))) -> 🟢 NORMAL | L76: =IF(F76<7,"⚠ SÍ","—") -> — | M76: =IF(E76>=PERCENTILE($E$5:$E$79,0.8),"A",IF(E76>=PERCENTILE($E$5:$E$79,0.5),"B","C")) -> C | N76: =IFERROR(Base_Datos!O79/Base_Datos!O83,0) -> 0.0027573343 | O76: =IF(F76<7,"REPOSICIÓN URGENTE",IF(F76<14,"Revisar orden de compra",IF(AND(F76>180,J76>60),"LIQUIDAR / DEVOLVER",IF(F76>90,"Reducir próxima compra","Stock en niveles óptimos")))) -> Stock en niveles óptimos | P76: =IF(F76<7,1,IF(AND(F76>180,J76>60),2,IF(F76<14,3,IF(F76>90,4,5)))) -> 5
A77: =Base_Datos!A80 -> SKU-073 | B77: =Base_Datos!B80 -> Loción After Shave 100ml | C77: =Base_Datos!C80 -> Higiene Personal | D77: =Base_Datos!G80 -> 36 | E77: =Base_Datos!P80 -> 166 | F77: =IFERROR(Base_Datos!G80/(Base_Datos!P80/30),9999) -> 6.5060241 | G77: =IFERROR(Base_Datos!O80/Base_Datos!G80,0) -> 27.666667 | H77: =Base_Datos!S80 -> 244.8 | I77: =Base_Datos!H80 -> 39 | J77: =Base_Datos!R80 -> 1 | K77: =IF(IFERROR(Base_Datos!G80/(Base_Datos!P80/30),9999)<7,"🔴 QUIEBRE",IF(IFERROR(Base_Datos!G80/(Base_Datos!P80/30),9999)<14,"🟡 CRÍTICO",IF(IFERROR(Base_Datos!G80/(Base_Datos!P80/30),9999)<=90,"🟢 NORMAL",IF(IFERROR(Base_Datos!G80/(Base_Datos!P80/30),9999)<=180,"🟡 SOBRESTOCK","🔴 STOCK MUERTO")))) -> 🔴 QUIEBRE | L77: =IF(F77<7,"⚠ SÍ","—") -> ⚠ SÍ | M77: =IF(E77>=PERCENTILE($E$5:$E$79,0.8),"A",IF(E77>=PERCENTILE($E$5:$E$79,0.5),"B","C")) -> A | N77: =IFERROR(Base_Datos!O80/Base_Datos!O83,0) -> 0.020193419 | O77: =IF(F77<7,"REPOSICIÓN URGENTE",IF(F77<14,"Revisar orden de compra",IF(AND(F77>180,J77>60),"LIQUIDAR / DEVOLVER",IF(F77>90,"Reducir próxima compra","Stock en niveles óptimos")))) -> REPOSICIÓN URGENTE | P77: =IF(F77<7,1,IF(AND(F77>180,J77>60),2,IF(F77<14,3,IF(F77>90,4,5)))) -> 1
A78: =Base_Datos!A81 -> SKU-074 | B78: =Base_Datos!B81 -> Maquinilla de Afeitar Recargable | C78: =Base_Datos!C81 -> Higiene Personal | D78: =Base_Datos!G81 -> 269 | E78: =Base_Datos!P81 -> 107.83333 | F78: =IFERROR(Base_Datos!G81/(Base_Datos!P81/30),9999) -> 74.837713 | G78: =IFERROR(Base_Datos!O81/Base_Datos!G81,0) -> 2.4052045 | H78: =Base_Datos!S81 -> 3362.5 | I78: =Base_Datos!H81 -> 23 | J78: =Base_Datos!R81 -> 27 | K78: =IF(IFERROR(Base_Datos!G81/(Base_Datos!P81/30),9999)<7,"🔴 QUIEBRE",IF(IFERROR(Base_Datos!G81/(Base_Datos!P81/30),9999)<14,"🟡 CRÍTICO",IF(IFERROR(Base_Datos!G81/(Base_Datos!P81/30),9999)<=90,"🟢 NORMAL",IF(IFERROR(Base_Datos!G81/(Base_Datos!P81/30),9999)<=180,"🟡 SOBRESTOCK","🔴 STOCK MUERTO")))) -> 🟢 NORMAL | L78: =IF(F78<7,"⚠ SÍ","—") -> — | M78: =IF(E78>=PERCENTILE($E$5:$E$79,0.8),"A",IF(E78>=PERCENTILE($E$5:$E$79,0.5),"B","C")) -> B | N78: =IFERROR(Base_Datos!O81/Base_Datos!O83,0) -> 0.013117612 | O78: =IF(F78<7,"REPOSICIÓN URGENTE",IF(F78<14,"Revisar orden de compra",IF(AND(F78>180,J78>60),"LIQUIDAR / DEVOLVER",IF(F78>90,"Reducir próxima compra","Stock en niveles óptimos")))) -> Stock en niveles óptimos | P78: =IF(F78<7,1,IF(AND(F78>180,J78>60),2,IF(F78<14,3,IF(F78>90,4,5)))) -> 5
A79: =Base_Datos!A82 -> SKU-075 | B79: =Base_Datos!B82 -> Repuestos Maquinilla x4 | C79: =Base_Datos!C82 -> Higiene Personal | D79: =Base_Datos!G82 -> 206 | E79: =Base_Datos!P82 -> 1.6666667 | F79: =IFERROR(Base_Datos!G82/(Base_Datos!P82/30),9999) -> 3708 | G79: =IFERROR(Base_Datos!O82/Base_Datos!G82,0) -> 0.048543689 | H79: =Base_Datos!S82 -> 2018.8 | I79: =Base_Datos!H82 -> 5 | J79: =Base_Datos!R82 -> 69 | K79: =IF(IFERROR(Base_Datos!G82/(Base_Datos!P82/30),9999)<7,"🔴 QUIEBRE",IF(IFERROR(Base_Datos!G82/(Base_Datos!P82/30),9999)<14,"🟡 CRÍTICO",IF(IFERROR(Base_Datos!G82/(Base_Datos!P82/30),9999)<=90,"🟢 NORMAL",IF(IFERROR(Base_Datos!G82/(Base_Datos!P82/30),9999)<=180,"🟡 SOBRESTOCK","🔴 STOCK MUERTO")))) -> 🔴 STOCK MUERTO | L79: =IF(F79<7,"⚠ SÍ","—") -> — | M79: =IF(E79>=PERCENTILE($E$5:$E$79,0.8),"A",IF(E79>=PERCENTILE($E$5:$E$79,0.5),"B","C")) -> C | N79: =IFERROR(Base_Datos!O82/Base_Datos!O83,0) -> 0.00020274517 | O79: =IF(F79<7,"REPOSICIÓN URGENTE",IF(F79<14,"Revisar orden de compra",IF(AND(F79>180,J79>60),"LIQUIDAR / DEVOLVER",IF(F79>90,"Reducir próxima compra","Stock en niveles óptimos")))) -> LIQUIDAR / DEVOLVER | P79: =IF(F79<7,1,IF(AND(F79>180,J79>60),2,IF(F79<14,3,IF(F79>90,4,5)))) -> 2
A82: RESUMEN EJECUTIVO DEL ANÁLISIS
A83: Indicador | B83: Valor
A84: SKUs con quiebre (<7d) | B84: =COUNTIF(K5:K79,"🔴 QUIEBRE") -> 7 | C84: SKUs
A85: SKUs stock muerto | B85: =COUNTIF(K5:K79,"🔴 STOCK MUERTO") -> 12 | C85: SKUs
A86: SKUs sobrestock | B86: =COUNTIF(K5:K79,"🟡 SOBRESTOCK") -> 6 | C86: SKUs
A87: SKUs en nivel normal | B87: =COUNTIF(K5:K79,"🟢 NORMAL") -> 49 | C87: SKUs
A88: Capital total inmovilizado | B88: =SUM(H5:H79) -> 64825.2 | C88: USD
A89: Capital en stock muerto | B89: =SUMIF(K5:K79,"🔴 STOCK MUERTO",H5:H79) -> 22472.7 | C89: USD
A90: Días cobertura promedio | B90: =AVERAGE(F5:F79) -> 540.36272 | C90: días
A91: Rotación promedio | B91: =AVERAGE(G5:G79) -> 9.253742 | C91: x/mes

Sheet Alertas
A1: PANEL DE ALERTAS OPERATIVAS
A2: Extracción automática de SKUs críticos · Actualización inmediata al cambiar Base_Datos · Usar para reuniones de operaciones
A4: 🔴 QUIEBRE INMINENTE — Cobertura menor a 7 días
A5: SKU ID | B5: Descripción | C5: Categoría | D5: Stock Actual | E5: Venta Prom. Mensual | F5: Días Cobertura | G5: Stock Mínimo | H5: ABC | I5: Capital Inmov. | J5: Acción
A6: =IFERROR(IF(Análisis!$K$5="🔴 QUIEBRE",Análisis!A5,""),"—") | B6: =IFERROR(IF(Análisis!$K$5="🔴 QUIEBRE",Análisis!B5,""),"—") | C6: =IFERROR(IF(Análisis!$K$5="🔴 QUIEBRE",Análisis!C5,""),"—") | D6: =IFERROR(IF(Análisis!$K$5="🔴 QUIEBRE",Análisis!D5,""),"—") | E6: =IFERROR(IF(Análisis!$K$5="🔴 QUIEBRE",Análisis!E5,""),"—") | F6: =IFERROR(IF(Análisis!$K$5="🔴 QUIEBRE",Análisis!F5,""),"—") | G6: =IFERROR(IF(Análisis!$K$5="🔴 QUIEBRE",Análisis!I5,""),"—") | H6: =IFERROR(IF(Análisis!$K$5="🔴 QUIEBRE",Análisis!M5,""),"—") | I6: =IFERROR(IF(Análisis!$K$5="🔴 QUIEBRE",Análisis!H5,""),"—") | J6: =IFERROR(IF(Análisis!$K$5="🔴 QUIEBRE",Análisis!O5,""),"—")
A7: =IFERROR(IF(Análisis!$K$6="🔴 QUIEBRE",Análisis!A6,""),"—") | B7: =IFERROR(IF(Análisis!$K$6="🔴 QUIEBRE",Análisis!B6,""),"—") | C7: =IFERROR(IF(Análisis!$K$6="🔴 QUIEBRE",Análisis!C6,""),"—") | D7: =IFERROR(IF(Análisis!$K$6="🔴 QUIEBRE",Análisis!D6,""),"—") | E7: =IFERROR(IF(Análisis!$K$6="🔴 QUIEBRE",Análisis!E6,""),"—") | F7: =IFERROR(IF(Análisis!$K$6="🔴 QUIEBRE",Análisis!F6,""),"—") | G7: =IFERROR(IF(Análisis!$K$6="🔴 QUIEBRE",Análisis!I6,""),"—") | H7: =IFERROR(IF(Análisis!$K$6="🔴 QUIEBRE",Análisis!M6,""),"—") | I7: =IFERROR(IF(Análisis!$K$6="🔴 QUIEBRE",Análisis!H6,""),"—") | J7: =IFERROR(IF(Análisis!$K$6="🔴 QUIEBRE",Análisis!O6,""),"—")
A8: =IFERROR(IF(Análisis!$K$7="🔴 QUIEBRE",Análisis!A7,""),"—") | B8: =IFERROR(IF(Análisis!$K$7="🔴 QUIEBRE",Análisis!B7,""),"—") | C8: =IFERROR(IF(Análisis!$K$7="🔴 QUIEBRE",Análisis!C7,""),"—") | D8: =IFERROR(IF(Análisis!$K$7="🔴 QUIEBRE",Análisis!D7,""),"—") | E8: =IFERROR(IF(Análisis!$K$7="🔴 QUIEBRE",Análisis!E7,""),"—") | F8: =IFERROR(IF(Análisis!$K$7="🔴 QUIEBRE",Análisis!F7,""),"—") | G8: =IFERROR(IF(Análisis!$K$7="🔴 QUIEBRE",Análisis!I7,""),"—") | H8: =IFERROR(IF(Análisis!$K$7="🔴 QUIEBRE",Análisis!M7,""),"—") | I8: =IFERROR(IF(Análisis!$K$7="🔴 QUIEBRE",Análisis!H7,""),"—") | J8: =IFERROR(IF(Análisis!$K$7="🔴 QUIEBRE",Análisis!O7,""),"—")
A9: =IFERROR(IF(Análisis!$K$8="🔴 QUIEBRE",Análisis!A8,""),"—") | B9: =IFERROR(IF(Análisis!$K$8="🔴 QUIEBRE",Análisis!B8,""),"—") | C9: =IFERROR(IF(Análisis!$K$8="🔴 QUIEBRE",Análisis!C8,""),"—") | D9: =IFERROR(IF(Análisis!$K$8="🔴 QUIEBRE",Análisis!D8,""),"—") | E9: =IFERROR(IF(Análisis!$K$8="🔴 QUIEBRE",Análisis!E8,""),"—") | F9: =IFERROR(IF(Análisis!$K$8="🔴 QUIEBRE",Análisis!F8,""),"—") | G9: =IFERROR(IF(Análisis!$K$8="🔴 QUIEBRE",Análisis!I8,""),"—") | H9: =IFERROR(IF(Análisis!$K$8="🔴 QUIEBRE",Análisis!M8,""),"—") | I9: =IFERROR(IF(Análisis!$K$8="🔴 QUIEBRE",Análisis!H8,""),"—") | J9: =IFERROR(IF(Análisis!$K$8="🔴 QUIEBRE",Análisis!O8,""),"—")
A10: =IFERROR(IF(Análisis!$K$9="🔴 QUIEBRE",Análisis!A9,""),"—") -> SKU-005 | B10: =IFERROR(IF(Análisis!$K$9="🔴 QUIEBRE",Análisis!B9,""),"—") -> Harina 000 1kg | C10: =IFERROR(IF(Análisis!$K$9="🔴 QUIEBRE",Análisis!C9,""),"—") -> Alimentos Secos | D10: =IFERROR(IF(Análisis!$K$9="🔴 QUIEBRE",Análisis!D9,""),"—") -> 24 | E10: =IFERROR(IF(Análisis!$K$9="🔴 QUIEBRE",Análisis!E9,""),"—") -> 374.83333 | F10: =IFERROR(IF(Análisis!$K$9="🔴 QUIEBRE",Análisis!F9,""),"—") -> 1.9208537 | G10: =IFERROR(IF(Análisis!$K$9="🔴 QUIEBRE",Análisis!I9,""),"—") -> 69 | H10: =IFERROR(IF(Análisis!$K$9="🔴 QUIEBRE",Análisis!M9,""),"—") -> A | I10: =IFERROR(IF(Análisis!$K$9="🔴 QUIEBRE",Análisis!H9,""),"—") -> 36 | J10: =IFERROR(IF(Análisis!$K$9="🔴 QUIEBRE",Análisis!O9,""),"—") -> REPOSICIÓN URGENTE
A11: =IFERROR(IF(Análisis!$K$10="🔴 QUIEBRE",Análisis!A10,""),"—") | B11: =IFERROR(IF(Análisis!$K$10="🔴 QUIEBRE",Análisis!B10,""),"—") | C11: =IFERROR(IF(Análisis!$K$10="🔴 QUIEBRE",Análisis!C10,""),"—") | D11: =IFERROR(IF(Análisis!$K$10="🔴 QUIEBRE",Análisis!D10,""),"—") | E11: =IFERROR(IF(Análisis!$K$10="🔴 QUIEBRE",Análisis!E10,""),"—") | F11: =IFERROR(IF(Análisis!$K$10="🔴 QUIEBRE",Análisis!F10,""),"—") | G11: =IFERROR(IF(Análisis!$K$10="🔴 QUIEBRE",Análisis!I10,""),"—") | H11: =IFERROR(IF(Análisis!$K$10="🔴 QUIEBRE",Análisis!M10,""),"—") | I11: =IFERROR(IF(Análisis!$K$10="🔴 QUIEBRE",Análisis!H10,""),"—") | J11: =IFERROR(IF(Análisis!$K$10="🔴 QUIEBRE",Análisis!O10,""),"—")
A12: =IFERROR(IF(Análisis!$K$11="🔴 QUIEBRE",Análisis!A11,""),"—") | B12: =IFERROR(IF(Análisis!$K$11="🔴 QUIEBRE",Análisis!B11,""),"—") | C12: =IFERROR(IF(Análisis!$K$11="🔴 QUIEBRE",Análisis!C11,""),"—") | D12: =IFERROR(IF(Análisis!$K$11="🔴 QUIEBRE",Análisis!D11,""),"—") | E12: =IFERROR(IF(Análisis!$K$11="🔴 QUIEBRE",Análisis!E11,""),"—") | F12: =IFERROR(IF(Análisis!$K$11="🔴 QUIEBRE",Análisis!F11,""),"—") | G12: =IFERROR(IF(Análisis!$K$11="🔴 QUIEBRE",Análisis!I11,""),"—") | H12: =IFERROR(IF(Análisis!$K$11="🔴 QUIEBRE",Análisis!M11,""),"—") | I12: =IFERROR(IF(Análisis!$K$11="🔴 QUIEBRE",Análisis!H11,""),"—") | J12: =IFERROR(IF(Análisis!$K$11="🔴 QUIEBRE",Análisis!O11,""),"—")
A13: =IFERROR(IF(Análisis!$K$12="🔴 QUIEBRE",Análisis!A12,""),"—") | B13: =IFERROR(IF(Análisis!$K$12="🔴 QUIEBRE",Análisis!B12,""),"—") | C13: =IFERROR(IF(Análisis!$K$12="🔴 QUIEBRE",Análisis!C12,""),"—") | D13: =IFERROR(IF(Análisis!$K$12="🔴 QUIEBRE",Análisis!D12,""),"—") | E13: =IFERROR(IF(Análisis!$K$12="🔴 QUIEBRE",Análisis!E12,""),"—") | F13: =IFERROR(IF(Análisis!$K$12="🔴 QUIEBRE",Análisis!F12,""),"—") | G13: =IFERROR(IF(Análisis!$K$12="🔴 QUIEBRE",Análisis!I12,""),"—") | H13: =IFERROR(IF(Análisis!$K$12="🔴 QUIEBRE",Análisis!M12,""),"—") | I13: =IFERROR(IF(Análisis!$K$12="🔴 QUIEBRE",Análisis!H12,""),"—") | J13: =IFERROR(IF(Análisis!$K$12="🔴 QUIEBRE",Análisis!O12,""),"—")
A14: =IFERROR(IF(Análisis!$K$13="🔴 QUIEBRE",Análisis!A13,""),"—") | B14: =IFERROR(IF(Análisis!$K$13="🔴 QUIEBRE",Análisis!B13,""),"—") | C14: =IFERROR(IF(Análisis!$K$13="🔴 QUIEBRE",Análisis!C13,""),"—") | D14: =IFERROR(IF(Análisis!$K$13="🔴 QUIEBRE",Análisis!D13,""),"—") | E14: =IFERROR(IF(Análisis!$K$13="🔴 QUIEBRE",Análisis!E13,""),"—") | F14: =IFERROR(IF(Análisis!$K$13="🔴 QUIEBRE",Análisis!F13,""),"—") | G14: =IFERROR(IF(Análisis!$K$13="🔴 QUIEBRE",Análisis!I13,""),"—") | H14: =IFERROR(IF(Análisis!$K$13="🔴 QUIEBRE",Análisis!M13,""),"—") | I14: =IFERROR(IF(Análisis!$K$13="🔴 QUIEBRE",Análisis!H13,""),"—") | J14: =IFERROR(IF(Análisis!$K$13="🔴 QUIEBRE",Análisis!O13,""),"—")
A15: =IFERROR(IF(Análisis!$K$14="🔴 QUIEBRE",Análisis!A14,""),"—") | B15: =IFERROR(IF(Análisis!$K$14="🔴 QUIEBRE",Análisis!B14,""),"—") | C15: =IFERROR(IF(Análisis!$K$14="🔴 QUIEBRE",Análisis!C14,""),"—") | D15: =IFERROR(IF(Análisis!$K$14="🔴 QUIEBRE",Análisis!D14,""),"—") | E15: =IFERROR(IF(Análisis!$K$14="🔴 QUIEBRE",Análisis!E14,""),"—") | F15: =IFERROR(IF(Análisis!$K$14="🔴 QUIEBRE",Análisis!F14,""),"—") | G15: =IFERROR(IF(Análisis!$K$14="🔴 QUIEBRE",Análisis!I14,""),"—") | H15: =IFERROR(IF(Análisis!$K$14="🔴 QUIEBRE",Análisis!M14,""),"—") | I15: =IFERROR(IF(Análisis!$K$14="🔴 QUIEBRE",Análisis!H14,""),"—") | J15: =IFERROR(IF(Análisis!$K$14="🔴 QUIEBRE",Análisis!O14,""),"—")
A16: =IFERROR(IF(Análisis!$K$15="🔴 QUIEBRE",Análisis!A15,""),"—") | B16: =IFERROR(IF(Análisis!$K$15="🔴 QUIEBRE",Análisis!B15,""),"—") | C16: =IFERROR(IF(Análisis!$K$15="🔴 QUIEBRE",Análisis!C15,""),"—") | D16: =IFERROR(IF(Análisis!$K$15="🔴 QUIEBRE",Análisis!D15,""),"—") | E16: =IFERROR(IF(Análisis!$K$15="🔴 QUIEBRE",Análisis!E15,""),"—") | F16: =IFERROR(IF(Análisis!$K$15="🔴 QUIEBRE",Análisis!F15,""),"—") | G16: =IFERROR(IF(Análisis!$K$15="🔴 QUIEBRE",Análisis!I15,""),"—") | H16: =IFERROR(IF(Análisis!$K$15="🔴 QUIEBRE",Análisis!M15,""),"—") | I16: =IFERROR(IF(Análisis!$K$15="🔴 QUIEBRE",Análisis!H15,""),"—") | J16: =IFERROR(IF(Análisis!$K$15="🔴 QUIEBRE",Análisis!O15,""),"—")
A17: =IFERROR(IF(Análisis!$K$16="🔴 QUIEBRE",Análisis!A16,""),"—") -> SKU-012 | B17: =IFERROR(IF(Análisis!$K$16="🔴 QUIEBRE",Análisis!B16,""),"—") -> Sal Fina 1kg | C17: =IFERROR(IF(Análisis!$K$16="🔴 QUIEBRE",Análisis!C16,""),"—") -> Alimentos Secos | D17: =IFERROR(IF(Análisis!$K$16="🔴 QUIEBRE",Análisis!D16,""),"—") -> 88 | E17: =IFERROR(IF(Análisis!$K$16="🔴 QUIEBRE",Análisis!E16,""),"—") -> 406.66667 | F17: =IFERROR(IF(Análisis!$K$16="🔴 QUIEBRE",Análisis!F16,""),"—") -> 6.4918033 | G17: =IFERROR(IF(Análisis!$K$16="🔴 QUIEBRE",Análisis!I16,""),"—") -> 91 | H17: =IFERROR(IF(Análisis!$K$16="🔴 QUIEBRE",Análisis!M16,""),"—") -> A | I17: =IFERROR(IF(Análisis!$K$16="🔴 QUIEBRE",Análisis!H16,""),"—") -> 74.8 | J17: =IFERROR(IF(Análisis!$K$16="🔴 QUIEBRE",Análisis!O16,""),"—") -> REPOSICIÓN URGENTE
A18: =IFERROR(IF(Análisis!$K$17="🔴 QUIEBRE",Análisis!A17,""),"—") | B18: =IFERROR(IF(Análisis!$K$17="🔴 QUIEBRE",Análisis!B17,""),"—") | C18: =IFERROR(IF(Análisis!$K$17="🔴 QUIEBRE",Análisis!C17,""),"—") | D18: =IFERROR(IF(Análisis!$K$17="🔴 QUIEBRE",Análisis!D17,""),"—") | E18: =IFERROR(IF(Análisis!$K$17="🔴 QUIEBRE",Análisis!E17,""),"—") | F18: =IFERROR(IF(Análisis!$K$17="🔴 QUIEBRE",Análisis!F17,""),"—") | G18: =IFERROR(IF(Análisis!$K$17="🔴 QUIEBRE",Análisis!I17,""),"—") | H18: =IFERROR(IF(Análisis!$K$17="🔴 QUIEBRE",Análisis!M17,""),"—") | I18: =IFERROR(IF(Análisis!$K$17="🔴 QUIEBRE",Análisis!H17,""),"—") | J18: =IFERROR(IF(Análisis!$K$17="🔴 QUIEBRE",Análisis!O17,""),"—")
A19: =IFERROR(IF(Análisis!$K$18="🔴 QUIEBRE",Análisis!A18,""),"—") | B19: =IFERROR(IF(Análisis!$K$18="🔴 QUIEBRE",Análisis!B18,""),"—") | C19: =IFERROR(IF(Análisis!$K$18="🔴 QUIEBRE",Análisis!C18,""),"—") | D19: =IFERROR(IF(Análisis!$K$18="🔴 QUIEBRE",Análisis!D18,""),"—") | E19: =IFERROR(IF(Análisis!$K$18="🔴 QUIEBRE",Análisis!E18,""),"—") | F19: =IFERROR(IF(Análisis!$K$18="🔴 QUIEBRE",Análisis!F18,""),"—") | G19: =IFERROR(IF(Análisis!$K$18="🔴 QUIEBRE",Análisis!I18,""),"—") | H19: =IFERROR(IF(Análisis!$K$18="🔴 QUIEBRE",Análisis!M18,""),"—") | I19: =IFERROR(IF(Análisis!$K$18="🔴 QUIEBRE",Análisis!H18,""),"—") | J19: =IFERROR(IF(Análisis!$K$18="🔴 QUIEBRE",Análisis!O18,""),"—")
A20: =IFERROR(IF(Análisis!$K$19="🔴 QUIEBRE",Análisis!A19,""),"—") | B20: =IFERROR(IF(Análisis!$K$19="🔴 QUIEBRE",Análisis!B19,""),"—") | C20: =IFERROR(IF(Análisis!$K$19="🔴 QUIEBRE",Análisis!C19,""),"—") | D20: =IFERROR(IF(Análisis!$K$19="🔴 QUIEBRE",Análisis!D19,""),"—") | E20: =IFERROR(IF(Análisis!$K$19="🔴 QUIEBRE",Análisis!E19,""),"—") | F20: =IFERROR(IF(Análisis!$K$19="🔴 QUIEBRE",Análisis!F19,""),"—") | G20: =IFERROR(IF(Análisis!$K$19="🔴 QUIEBRE",Análisis!I19,""),"—") | H20: =IFERROR(IF(Análisis!$K$19="🔴 QUIEBRE",Análisis!M19,""),"—") | I20: =IFERROR(IF(Análisis!$K$19="🔴 QUIEBRE",Análisis!H19,""),"—") | J20: =IFERROR(IF(Análisis!$K$19="🔴 QUIEBRE",Análisis!O19,""),"—")
A21: =IFERROR(IF(Análisis!$K$20="🔴 QUIEBRE",Análisis!A20,""),"—") | B21: =IFERROR(IF(Análisis!$K$20="🔴 QUIEBRE",Análisis!B20,""),"—") | C21: =IFERROR(IF(Análisis!$K$20="🔴 QUIEBRE",Análisis!C20,""),"—") | D21: =IFERROR(IF(Análisis!$K$20="🔴 QUIEBRE",Análisis!D20,""),"—") | E21: =IFERROR(IF(Análisis!$K$20="🔴 QUIEBRE",Análisis!E20,""),"—") | F21: =IFERROR(IF(Análisis!$K$20="🔴 QUIEBRE",Análisis!F20,""),"—") | G21: =IFERROR(IF(Análisis!$K$20="🔴 QUIEBRE",Análisis!I20,""),"—") | H21: =IFERROR(IF(Análisis!$K$20="🔴 QUIEBRE",Análisis!M20,""),"—") | I21: =IFERROR(IF(Análisis!$K$20="🔴 QUIEBRE",Análisis!H20,""),"—") | J21: =IFERROR(IF(Análisis!$K$20="🔴 QUIEBRE",Análisis!O20,""),"—")
A22: =IFERROR(IF(Análisis!$K$21="🔴 QUIEBRE",Análisis!A21,""),"—") | B22: =IFERROR(IF(Análisis!$K$21="🔴 QUIEBRE",Análisis!B21,""),"—") | C22: =IFERROR(IF(Análisis!$K$21="🔴 QUIEBRE",Análisis!C21,""),"—") | D22: =IFERROR(IF(Análisis!$K$21="🔴 QUIEBRE",Análisis!D21,""),"—") | E22: =IFERROR(IF(Análisis!$K$21="🔴 QUIEBRE",Análisis!E21,""),"—") | F22: =IFERROR(IF(Análisis!$K$21="🔴 QUIEBRE",Análisis!F21,""),"—") | G22: =IFERROR(IF(Análisis!$K$21="🔴 QUIEBRE",Análisis!I21,""),"—") | H22: =IFERROR(IF(Análisis!$K$21="🔴 QUIEBRE",Análisis!M21,""),"—") | I22: =IFERROR(IF(Análisis!$K$21="🔴 QUIEBRE",Análisis!H21,""),"—") | J22: =IFERROR(IF(Análisis!$K$21="🔴 QUIEBRE",Análisis!O21,""),"—")
A23: =IFERROR(IF(Análisis!$K$22="🔴 QUIEBRE",Análisis!A22,""),"—") | B23: =IFERROR(IF(Análisis!$K$22="🔴 QUIEBRE",Análisis!B22,""),"—") | C23: =IFERROR(IF(Análisis!$K$22="🔴 QUIEBRE",Análisis!C22,""),"—") | D23: =IFERROR(IF(Análisis!$K$22="🔴 QUIEBRE",Análisis!D22,""),"—") | E23: =IFERROR(IF(Análisis!$K$22="🔴 QUIEBRE",Análisis!E22,""),"—") | F23: =IFERROR(IF(Análisis!$K$22="🔴 QUIEBRE",Análisis!F22,""),"—") | G23: =IFERROR(IF(Análisis!$K$22="🔴 QUIEBRE",Análisis!I22,""),"—") | H23: =IFERROR(IF(Análisis!$K$22="🔴 QUIEBRE",Análisis!M22,""),"—") | I23: =IFERROR(IF(Análisis!$K$22="🔴 QUIEBRE",Análisis!H22,""),"—") | J23: =IFERROR(IF(Análisis!$K$22="🔴 QUIEBRE",Análisis!O22,""),"—")
A24: =IFERROR(IF(Análisis!$K$23="🔴 QUIEBRE",Análisis!A23,""),"—") | B24: =IFERROR(IF(Análisis!$K$23="🔴 QUIEBRE",Análisis!B23,""),"—") | C24: =IFERROR(IF(Análisis!$K$23="🔴 QUIEBRE",Análisis!C23,""),"—") | D24: =IFERROR(IF(Análisis!$K$23="🔴 QUIEBRE",Análisis!D23,""),"—") | E24: =IFERROR(IF(Análisis!$K$23="🔴 QUIEBRE",Análisis!E23,""),"—") | F24: =IFERROR(IF(Análisis!$K$23="🔴 QUIEBRE",Análisis!F23,""),"—") | G24: =IFERROR(IF(Análisis!$K$23="🔴 QUIEBRE",Análisis!I23,""),"—") | H24: =IFERROR(IF(Análisis!$K$23="🔴 QUIEBRE",Análisis!M23,""),"—") | I24: =IFERROR(IF(Análisis!$K$23="🔴 QUIEBRE",Análisis!H23,""),"—") | J24: =IFERROR(IF(Análisis!$K$23="🔴 QUIEBRE",Análisis!O23,""),"—")
A25: =IFERROR(IF(Análisis!$K$24="🔴 QUIEBRE",Análisis!A24,""),"—") | B25: =IFERROR(IF(Análisis!$K$24="🔴 QUIEBRE",Análisis!B24,""),"—") | C25: =IFERROR(IF(Análisis!$K$24="🔴 QUIEBRE",Análisis!C24,""),"—") | D25: =IFERROR(IF(Análisis!$K$24="🔴 QUIEBRE",Análisis!D24,""),"—") | E25: =IFERROR(IF(Análisis!$K$24="🔴 QUIEBRE",Análisis!E24,""),"—") | F25: =IFERROR(IF(Análisis!$K$24="🔴 QUIEBRE",Análisis!F24,""),"—") | G25: =IFERROR(IF(Análisis!$K$24="🔴 QUIEBRE",Análisis!I24,""),"—") | H25: =IFERROR(IF(Análisis!$K$24="🔴 QUIEBRE",Análisis!M24,""),"—") | I25: =IFERROR(IF(Análisis!$K$24="🔴 QUIEBRE",Análisis!H24,""),"—") | J25: =IFERROR(IF(Análisis!$K$24="🔴 QUIEBRE",Análisis!O24,""),"—")
A26: =IFERROR(IF(Análisis!$K$25="🔴 QUIEBRE",Análisis!A25,""),"—") | B26: =IFERROR(IF(Análisis!$K$25="🔴 QUIEBRE",Análisis!B25,""),"—") | C26: =IFERROR(IF(Análisis!$K$25="🔴 QUIEBRE",Análisis!C25,""),"—") | D26: =IFERROR(IF(Análisis!$K$25="🔴 QUIEBRE",Análisis!D25,""),"—") | E26: =IFERROR(IF(Análisis!$K$25="🔴 QUIEBRE",Análisis!E25,""),"—") | F26: =IFERROR(IF(Análisis!$K$25="🔴 QUIEBRE",Análisis!F25,""),"—") | G26: =IFERROR(IF(Análisis!$K$25="🔴 QUIEBRE",Análisis!I25,""),"—") | H26: =IFERROR(IF(Análisis!$K$25="🔴 QUIEBRE",Análisis!M25,""),"—") | I26: =IFERROR(IF(Análisis!$K$25="🔴 QUIEBRE",Análisis!H25,""),"—") | J26: =IFERROR(IF(Análisis!$K$25="🔴 QUIEBRE",Análisis!O25,""),"—")
A27: =IFERROR(IF(Análisis!$K$26="🔴 QUIEBRE",Análisis!A26,""),"—") -> SKU-022 | B27: =IFERROR(IF(Análisis!$K$26="🔴 QUIEBRE",Análisis!B26,""),"—") -> Mayonesa 500g | C27: =IFERROR(IF(Análisis!$K$26="🔴 QUIEBRE",Análisis!C26,""),"—") -> Alimentos Secos | D27: =IFERROR(IF(Análisis!$K$26="🔴 QUIEBRE",Análisis!D26,""),"—") -> 25 | E27: =IFERROR(IF(Análisis!$K$26="🔴 QUIEBRE",Análisis!E26,""),"—") -> 406.83333 | F27: =IFERROR(IF(Análisis!$K$26="🔴 QUIEBRE",Análisis!F26,""),"—") -> 1.8435068 | G27: =IFERROR(IF(Análisis!$K$26="🔴 QUIEBRE",Análisis!I26,""),"—") -> 105 | H27: =IFERROR(IF(Análisis!$K$26="🔴 QUIEBRE",Análisis!M26,""),"—") -> A | I27: =IFERROR(IF(Análisis!$K$26="🔴 QUIEBRE",Análisis!H26,""),"—") -> 85 | J27: =IFERROR(IF(Análisis!$K$26="🔴 QUIEBRE",Análisis!O26,""),"—") -> REPOSICIÓN URGENTE
A28: =IFERROR(IF(Análisis!$K$27="🔴 QUIEBRE",Análisis!A27,""),"—") | B28: =IFERROR(IF(Análisis!$K$27="🔴 QUIEBRE",Análisis!B27,""),"—") | C28: =IFERROR(IF(Análisis!$K$27="🔴 QUIEBRE",Análisis!C27,""),"—") | D28: =IFERROR(IF(Análisis!$K$27="🔴 QUIEBRE",Análisis!D27,""),"—") | E28: =IFERROR(IF(Análisis!$K$27="🔴 QUIEBRE",Análisis!E27,""),"—") | F28: =IFERROR(IF(Análisis!$K$27="🔴 QUIEBRE",Análisis!F27,""),"—") | G28: =IFERROR(IF(Análisis!$K$27="🔴 QUIEBRE",Análisis!I27,""),"—") | H28: =IFERROR(IF(Análisis!$K$27="🔴 QUIEBRE",Análisis!M27,""),"—") | I28: =IFERROR(IF(Análisis!$K$27="🔴 QUIEBRE",Análisis!H27,""),"—") | J28: =IFERROR(IF(Análisis!$K$27="🔴 QUIEBRE",Análisis!O27,""),"—")
A29: =IFERROR(IF(Análisis!$K$28="🔴 QUIEBRE",Análisis!A28,""),"—") | B29: =IFERROR(IF(Análisis!$K$28="🔴 QUIEBRE",Análisis!B28,""),"—") | C29: =IFERROR(IF(Análisis!$K$28="🔴 QUIEBRE",Análisis!C28,""),"—") | D29: =IFERROR(IF(Análisis!$K$28="🔴 QUIEBRE",Análisis!D28,""),"—") | E29: =IFERROR(IF(Análisis!$K$28="🔴 QUIEBRE",Análisis!E28,""),"—") | F29: =IFERROR(IF(Análisis!$K$28="🔴 QUIEBRE",Análisis!F28,""),"—") | G29: =IFERROR(IF(Análisis!$K$28="🔴 QUIEBRE",Análisis!I28,""),"—") | H29: =IFERROR(IF(Análisis!$K$28="🔴 QUIEBRE",Análisis!M28,""),"—") | I29: =IFERROR(IF(Análisis!$K$28="🔴 QUIEBRE",Análisis!H28,""),"—") | J29: =IFERROR(IF(Análisis!$K$28="🔴 QUIEBRE",Análisis!O28,""),"—")
A30: =IFERROR(IF(Análisis!$K$29="🔴 QUIEBRE",Análisis!A29,""),"—") | B30: =IFERROR(IF(Análisis!$K$29="🔴 QUIEBRE",Análisis!B29,""),"—") | C30: =IFERROR(IF(Análisis!$K$29="🔴 QUIEBRE",Análisis!C29,""),"—") | D30: =IFERROR(IF(Análisis!$K$29="🔴 QUIEBRE",Análisis!D29,""),"—") | E30: =IFERROR(IF(Análisis!$K$29="🔴 QUIEBRE",Análisis!E29,""),"—") | F30: =IFERROR(IF(Análisis!$K$29="🔴 QUIEBRE",Análisis!F29,""),"—") | G30: =IFERROR(IF(Análisis!$K$29="🔴 QUIEBRE",Análisis!I29,""),"—") | H30: =IFERROR(IF(Análisis!$K$29="🔴 QUIEBRE",Análisis!M29,""),"—") | I30: =IFERROR(IF(Análisis!$K$29="🔴 QUIEBRE",Análisis!H29,""),"—") | J30: =IFERROR(IF(Análisis!$K$29="🔴 QUIEBRE",Análisis!O29,""),"—")
A31: =IFERROR(IF(Análisis!$K$30="🔴 QUIEBRE",Análisis!A30,""),"—") | B31: =IFERROR(IF(Análisis!$K$30="🔴 QUIEBRE",Análisis!B30,""),"—") | C31: =IFERROR(IF(Análisis!$K$30="🔴 QUIEBRE",Análisis!C30,""),"—") | D31: =IFERROR(IF(Análisis!$K$30="🔴 QUIEBRE",Análisis!D30,""),"—") | E31: =IFERROR(IF(Análisis!$K$30="🔴 QUIEBRE",Análisis!E30,""),"—") | F31: =IFERROR(IF(Análisis!$K$30="🔴 QUIEBRE",Análisis!F30,""),"—") | G31: =IFERROR(IF(Análisis!$K$30="🔴 QUIEBRE",Análisis!I30,""),"—") | H31: =IFERROR(IF(Análisis!$K$30="🔴 QUIEBRE",Análisis!M30,""),"—") | I31: =IFERROR(IF(Análisis!$K$30="🔴 QUIEBRE",Análisis!H30,""),"—") | J31: =IFERROR(IF(Análisis!$K$30="🔴 QUIEBRE",Análisis!O30,""),"—")
A32: =IFERROR(IF(Análisis!$K$31="🔴 QUIEBRE",Análisis!A31,""),"—") | B32: =IFERROR(IF(Análisis!$K$31="🔴 QUIEBRE",Análisis!B31,""),"—") | C32: =IFERROR(IF(Análisis!$K$31="🔴 QUIEBRE",Análisis!C31,""),"—") | D32: =IFERROR(IF(Análisis!$K$31="🔴 QUIEBRE",Análisis!D31,""),"—") | E32: =IFERROR(IF(Análisis!$K$31="🔴 QUIEBRE",Análisis!E31,""),"—") | F32: =IFERROR(IF(Análisis!$K$31="🔴 QUIEBRE",Análisis!F31,""),"—") | G32: =IFERROR(IF(Análisis!$K$31="🔴 QUIEBRE",Análisis!I31,""),"—") | H32: =IFERROR(IF(Análisis!$K$31="🔴 QUIEBRE",Análisis!M31,""),"—") | I32: =IFERROR(IF(Análisis!$K$31="🔴 QUIEBRE",Análisis!H31,""),"—") | J32: =IFERROR(IF(Análisis!$K$31="🔴 QUIEBRE",Análisis!O31,""),"—")
A33: =IFERROR(IF(Análisis!$K$32="🔴 QUIEBRE",Análisis!A32,""),"—") | B33: =IFERROR(IF(Análisis!$K$32="🔴 QUIEBRE",Análisis!B32,""),"—") | C33: =IFERROR(IF(Análisis!$K$32="🔴 QUIEBRE",Análisis!C32,""),"—") | D33: =IFERROR(IF(Análisis!$K$32="🔴 QUIEBRE",Análisis!D32,""),"—") | E33: =IFERROR(IF(Análisis!$K$32="🔴 QUIEBRE",Análisis!E32,""),"—") | F33: =IFERROR(IF(Análisis!$K$32="🔴 QUIEBRE",Análisis!F32,""),"—") | G33: =IFERROR(IF(Análisis!$K$32="🔴 QUIEBRE",Análisis!I32,""),"—") | H33: =IFERROR(IF(Análisis!$K$32="🔴 QUIEBRE",Análisis!M32,""),"—") | I33: =IFERROR(IF(Análisis!$K$32="🔴 QUIEBRE",Análisis!H32,""),"—") | J33: =IFERROR(IF(Análisis!$K$32="🔴 QUIEBRE",Análisis!O32,""),"—")
A34: =IFERROR(IF(Análisis!$K$33="🔴 QUIEBRE",Análisis!A33,""),"—") | B34: =IFERROR(IF(Análisis!$K$33="🔴 QUIEBRE",Análisis!B33,""),"—") | C34: =IFERROR(IF(Análisis!$K$33="🔴 QUIEBRE",Análisis!C33,""),"—") | D34: =IFERROR(IF(Análisis!$K$33="🔴 QUIEBRE",Análisis!D33,""),"—") | E34: =IFERROR(IF(Análisis!$K$33="🔴 QUIEBRE",Análisis!E33,""),"—") | F34: =IFERROR(IF(Análisis!$K$33="🔴 QUIEBRE",Análisis!F33,""),"—") | G34: =IFERROR(IF(Análisis!$K$33="🔴 QUIEBRE",Análisis!I33,""),"—") | H34: =IFERROR(IF(Análisis!$K$33="🔴 QUIEBRE",Análisis!M33,""),"—") | I34: =IFERROR(IF(Análisis!$K$33="🔴 QUIEBRE",Análisis!H33,""),"—") | J34: =IFERROR(IF(Análisis!$K$33="🔴 QUIEBRE",Análisis!O33,""),"—")
A35: =IFERROR(IF(Análisis!$K$34="🔴 QUIEBRE",Análisis!A34,""),"—") | B35: =IFERROR(IF(Análisis!$K$34="🔴 QUIEBRE",Análisis!B34,""),"—") | C35: =IFERROR(IF(Análisis!$K$34="🔴 QUIEBRE",Análisis!C34,""),"—") | D35: =IFERROR(IF(Análisis!$K$34="🔴 QUIEBRE",Análisis!D34,""),"—") | E35: =IFERROR(IF(Análisis!$K$34="🔴 QUIEBRE",Análisis!E34,""),"—") | F35: =IFERROR(IF(Análisis!$K$34="🔴 QUIEBRE",Análisis!F34,""),"—") | G35: =IFERROR(IF(Análisis!$K$34="🔴 QUIEBRE",Análisis!I34,""),"—") | H35: =IFERROR(IF(Análisis!$K$34="🔴 QUIEBRE",Análisis!M34,""),"—") | I35: =IFERROR(IF(Análisis!$K$34="🔴 QUIEBRE",Análisis!H34,""),"—") | J35: =IFERROR(IF(Análisis!$K$34="🔴 QUIEBRE",Análisis!O34,""),"—")
A36: =IFERROR(IF(Análisis!$K$35="🔴 QUIEBRE",Análisis!A35,""),"—") | B36: =IFERROR(IF(Análisis!$K$35="🔴 QUIEBRE",Análisis!B35,""),"—") | C36: =IFERROR(IF(Análisis!$K$35="🔴 QUIEBRE",Análisis!C35,""),"—") | D36: =IFERROR(IF(Análisis!$K$35="🔴 QUIEBRE",Análisis!D35,""),"—") | E36: =IFERROR(IF(Análisis!$K$35="🔴 QUIEBRE",Análisis!E35,""),"—") | F36: =IFERROR(IF(Análisis!$K$35="🔴 QUIEBRE",Análisis!F35,""),"—") | G36: =IFERROR(IF(Análisis!$K$35="🔴 QUIEBRE",Análisis!I35,""),"—") | H36: =IFERROR(IF(Análisis!$K$35="🔴 QUIEBRE",Análisis!M35,""),"—") | I36: =IFERROR(IF(Análisis!$K$35="🔴 QUIEBRE",Análisis!H35,""),"—") | J36: =IFERROR(IF(Análisis!$K$35="🔴 QUIEBRE",Análisis!O35,""),"—")
A37: =IFERROR(IF(Análisis!$K$36="🔴 QUIEBRE",Análisis!A36,""),"—") | B37: =IFERROR(IF(Análisis!$K$36="🔴 QUIEBRE",Análisis!B36,""),"—") | C37: =IFERROR(IF(Análisis!$K$36="🔴 QUIEBRE",Análisis!C36,""),"—") | D37: =IFERROR(IF(Análisis!$K$36="🔴 QUIEBRE",Análisis!D36,""),"—") | E37: =IFERROR(IF(Análisis!$K$36="🔴 QUIEBRE",Análisis!E36,""),"—") | F37: =IFERROR(IF(Análisis!$K$36="🔴 QUIEBRE",Análisis!F36,""),"—") | G37: =IFERROR(IF(Análisis!$K$36="🔴 QUIEBRE",Análisis!I36,""),"—") | H37: =IFERROR(IF(Análisis!$K$36="🔴 QUIEBRE",Análisis!M36,""),"—") | I37: =IFERROR(IF(Análisis!$K$36="🔴 QUIEBRE",Análisis!H36,""),"—") | J37: =IFERROR(IF(Análisis!$K$36="🔴 QUIEBRE",Análisis!O36,""),"—")
A38: =IFERROR(IF(Análisis!$K$37="🔴 QUIEBRE",Análisis!A37,""),"—") | B38: =IFERROR(IF(Análisis!$K$37="🔴 QUIEBRE",Análisis!B37,""),"—") | C38: =IFERROR(IF(Análisis!$K$37="🔴 QUIEBRE",Análisis!C37,""),"—") | D38: =IFERROR(IF(Análisis!$K$37="🔴 QUIEBRE",Análisis!D37,""),"—") | E38: =IFERROR(IF(Análisis!$K$37="🔴 QUIEBRE",Análisis!E37,""),"—") | F38: =IFERROR(IF(Análisis!$K$37="🔴 QUIEBRE",Análisis!F37,""),"—") | G38: =IFERROR(IF(Análisis!$K$37="🔴 QUIEBRE",Análisis!I37,""),"—") | H38: =IFERROR(IF(Análisis!$K$37="🔴 QUIEBRE",Análisis!M37,""),"—") | I38: =IFERROR(IF(Análisis!$K$37="🔴 QUIEBRE",Análisis!H37,""),"—") | J38: =IFERROR(IF(Análisis!$K$37="🔴 QUIEBRE",Análisis!O37,""),"—")
A39: =IFERROR(IF(Análisis!$K$38="🔴 QUIEBRE",Análisis!A38,""),"—") | B39: =IFERROR(IF(Análisis!$K$38="🔴 QUIEBRE",Análisis!B38,""),"—") | C39: =IFERROR(IF(Análisis!$K$38="🔴 QUIEBRE",Análisis!C38,""),"—") | D39: =IFERROR(IF(Análisis!$K$38="🔴 QUIEBRE",Análisis!D38,""),"—") | E39: =IFERROR(IF(Análisis!$K$38="🔴 QUIEBRE",Análisis!E38,""),"—") | F39: =IFERROR(IF(Análisis!$K$38="🔴 QUIEBRE",Análisis!F38,""),"—") | G39: =IFERROR(IF(Análisis!$K$38="🔴 QUIEBRE",Análisis!I38,""),"—") | H39: =IFERROR(IF(Análisis!$K$38="🔴 QUIEBRE",Análisis!M38,""),"—") | I39: =IFERROR(IF(Análisis!$K$38="🔴 QUIEBRE",Análisis!H38,""),"—") | J39: =IFERROR(IF(Análisis!$K$38="🔴 QUIEBRE",Análisis!O38,""),"—")
A40: =IFERROR(IF(Análisis!$K$39="🔴 QUIEBRE",Análisis!A39,""),"—") | B40: =IFERROR(IF(Análisis!$K$39="🔴 QUIEBRE",Análisis!B39,""),"—") | C40: =IFERROR(IF(Análisis!$K$39="🔴 QUIEBRE",Análisis!C39,""),"—") | D40: =IFERROR(IF(Análisis!$K$39="🔴 QUIEBRE",Análisis!D39,""),"—") | E40: =IFERROR(IF(Análisis!$K$39="🔴 QUIEBRE",Análisis!E39,""),"—") | F40: =IFERROR(IF(Análisis!$K$39="🔴 QUIEBRE",Análisis!F39,""),"—") | G40: =IFERROR(IF(Análisis!$K$39="🔴 QUIEBRE",Análisis!I39,""),"—") | H40: =IFERROR(IF(Análisis!$K$39="🔴 QUIEBRE",Análisis!M39,""),"—") | I40: =IFERROR(IF(Análisis!$K$39="🔴 QUIEBRE",Análisis!H39,""),"—") | J40: =IFERROR(IF(Análisis!$K$39="🔴 QUIEBRE",Análisis!O39,""),"—")
A41: =IFERROR(IF(Análisis!$K$40="🔴 QUIEBRE",Análisis!A40,""),"—") | B41: =IFERROR(IF(Análisis!$K$40="🔴 QUIEBRE",Análisis!B40,""),"—") | C41: =IFERROR(IF(Análisis!$K$40="🔴 QUIEBRE",Análisis!C40,""),"—") | D41: =IFERROR(IF(Análisis!$K$40="🔴 QUIEBRE",Análisis!D40,""),"—") | E41: =IFERROR(IF(Análisis!$K$40="🔴 QUIEBRE",Análisis!E40,""),"—") | F41: =IFERROR(IF(Análisis!$K$40="🔴 QUIEBRE",Análisis!F40,""),"—") | G41: =IFERROR(IF(Análisis!$K$40="🔴 QUIEBRE",Análisis!I40,""),"—") | H41: =IFERROR(IF(Análisis!$K$40="🔴 QUIEBRE",Análisis!M40,""),"—") | I41: =IFERROR(IF(Análisis!$K$40="🔴 QUIEBRE",Análisis!H40,""),"—") | J41: =IFERROR(IF(Análisis!$K$40="🔴 QUIEBRE",Análisis!O40,""),"—")
A42: =IFERROR(IF(Análisis!$K$41="🔴 QUIEBRE",Análisis!A41,""),"—") | B42: =IFERROR(IF(Análisis!$K$41="🔴 QUIEBRE",Análisis!B41,""),"—") | C42: =IFERROR(IF(Análisis!$K$41="🔴 QUIEBRE",Análisis!C41,""),"—") | D42: =IFERROR(IF(Análisis!$K$41="🔴 QUIEBRE",Análisis!D41,""),"—") | E42: =IFERROR(IF(Análisis!$K$41="🔴 QUIEBRE",Análisis!E41,""),"—") | F42: =IFERROR(IF(Análisis!$K$41="🔴 QUIEBRE",Análisis!F41,""),"—") | G42: =IFERROR(IF(Análisis!$K$41="🔴 QUIEBRE",Análisis!I41,""),"—") | H42: =IFERROR(IF(Análisis!$K$41="🔴 QUIEBRE",Análisis!M41,""),"—") | I42: =IFERROR(IF(Análisis!$K$41="🔴 QUIEBRE",Análisis!H41,""),"—") | J42: =IFERROR(IF(Análisis!$K$41="🔴 QUIEBRE",Análisis!O41,""),"—")
A43: =IFERROR(IF(Análisis!$K$42="🔴 QUIEBRE",Análisis!A42,""),"—") | B43: =IFERROR(IF(Análisis!$K$42="🔴 QUIEBRE",Análisis!B42,""),"—") | C43: =IFERROR(IF(Análisis!$K$42="🔴 QUIEBRE",Análisis!C42,""),"—") | D43: =IFERROR(IF(Análisis!$K$42="🔴 QUIEBRE",Análisis!D42,""),"—") | E43: =IFERROR(IF(Análisis!$K$42="🔴 QUIEBRE",Análisis!E42,""),"—") | F43: =IFERROR(IF(Análisis!$K$42="🔴 QUIEBRE",Análisis!F42,""),"—") | G43: =IFERROR(IF(Análisis!$K$42="🔴 QUIEBRE",Análisis!I42,""),"—") | H43: =IFERROR(IF(Análisis!$K$42="🔴 QUIEBRE",Análisis!M42,""),"—") | I43: =IFERROR(IF(Análisis!$K$42="🔴 QUIEBRE",Análisis!H42,""),"—") | J43: =IFERROR(IF(Análisis!$K$42="🔴 QUIEBRE",Análisis!O42,""),"—")
A44: =IFERROR(IF(Análisis!$K$43="🔴 QUIEBRE",Análisis!A43,""),"—") | B44: =IFERROR(IF(Análisis!$K$43="🔴 QUIEBRE",Análisis!B43,""),"—") | C44: =IFERROR(IF(Análisis!$K$43="🔴 QUIEBRE",Análisis!C43,""),"—") | D44: =IFERROR(IF(Análisis!$K$43="🔴 QUIEBRE",Análisis!D43,""),"—") | E44: =IFERROR(IF(Análisis!$K$43="🔴 QUIEBRE",Análisis!E43,""),"—") | F44: =IFERROR(IF(Análisis!$K$43="🔴 QUIEBRE",Análisis!F43,""),"—") | G44: =IFERROR(IF(Análisis!$K$43="🔴 QUIEBRE",Análisis!I43,""),"—") | H44: =IFERROR(IF(Análisis!$K$43="🔴 QUIEBRE",Análisis!M43,""),"—") | I44: =IFERROR(IF(Análisis!$K$43="🔴 QUIEBRE",Análisis!H43,""),"—") | J44: =IFERROR(IF(Análisis!$K$43="🔴 QUIEBRE",Análisis!O43,""),"—")
A45: =IFERROR(IF(Análisis!$K$44="🔴 QUIEBRE",Análisis!A44,""),"—") | B45: =IFERROR(IF(Análisis!$K$44="🔴 QUIEBRE",Análisis!B44,""),"—") | C45: =IFERROR(IF(Análisis!$K$44="🔴 QUIEBRE",Análisis!C44,""),"—") | D45: =IFERROR(IF(Análisis!$K$44="🔴 QUIEBRE",Análisis!D44,""),"—") | E45: =IFERROR(IF(Análisis!$K$44="🔴 QUIEBRE",Análisis!E44,""),"—") | F45: =IFERROR(IF(Análisis!$K$44="🔴 QUIEBRE",Análisis!F44,""),"—") | G45: =IFERROR(IF(Análisis!$K$44="🔴 QUIEBRE",Análisis!I44,""),"—") | H45: =IFERROR(IF(Análisis!$K$44="🔴 QUIEBRE",Análisis!M44,""),"—") | I45: =IFERROR(IF(Análisis!$K$44="🔴 QUIEBRE",Análisis!H44,""),"—") | J45: =IFERROR(IF(Análisis!$K$44="🔴 QUIEBRE",Análisis!O44,""),"—")
A46: =IFERROR(IF(Análisis!$K$45="🔴 QUIEBRE",Análisis!A45,""),"—") | B46: =IFERROR(IF(Análisis!$K$45="🔴 QUIEBRE",Análisis!B45,""),"—") | C46: =IFERROR(IF(Análisis!$K$45="🔴 QUIEBRE",Análisis!C45,""),"—") | D46: =IFERROR(IF(Análisis!$K$45="🔴 QUIEBRE",Análisis!D45,""),"—") | E46: =IFERROR(IF(Análisis!$K$45="🔴 QUIEBRE",Análisis!E45,""),"—") | F46: =IFERROR(IF(Análisis!$K$45="🔴 QUIEBRE",Análisis!F45,""),"—") | G46: =IFERROR(IF(Análisis!$K$45="🔴 QUIEBRE",Análisis!I45,""),"—") | H46: =IFERROR(IF(Análisis!$K$45="🔴 QUIEBRE",Análisis!M45,""),"—") | I46: =IFERROR(IF(Análisis!$K$45="🔴 QUIEBRE",Análisis!H45,""),"—") | J46: =IFERROR(IF(Análisis!$K$45="🔴 QUIEBRE",Análisis!O45,""),"—")
A47: =IFERROR(IF(Análisis!$K$46="🔴 QUIEBRE",Análisis!A46,""),"—") | B47: =IFERROR(IF(Análisis!$K$46="🔴 QUIEBRE",Análisis!B46,""),"—") | C47: =IFERROR(IF(Análisis!$K$46="🔴 QUIEBRE",Análisis!C46,""),"—") | D47: =IFERROR(IF(Análisis!$K$46="🔴 QUIEBRE",Análisis!D46,""),"—") | E47: =IFERROR(IF(Análisis!$K$46="🔴 QUIEBRE",Análisis!E46,""),"—") | F47: =IFERROR(IF(Análisis!$K$46="🔴 QUIEBRE",Análisis!F46,""),"—") | G47: =IFERROR(IF(Análisis!$K$46="🔴 QUIEBRE",Análisis!I46,""),"—") | H47: =IFERROR(IF(Análisis!$K$46="🔴 QUIEBRE",Análisis!M46,""),"—") | I47: =IFERROR(IF(Análisis!$K$46="🔴 QUIEBRE",Análisis!H46,""),"—") | J47: =IFERROR(IF(Análisis!$K$46="🔴 QUIEBRE",Análisis!O46,""),"—")
A48: =IFERROR(IF(Análisis!$K$47="🔴 QUIEBRE",Análisis!A47,""),"—") | B48: =IFERROR(IF(Análisis!$K$47="🔴 QUIEBRE",Análisis!B47,""),"—") | C48: =IFERROR(IF(Análisis!$K$47="🔴 QUIEBRE",Análisis!C47,""),"—") | D48: =IFERROR(IF(Análisis!$K$47="🔴 QUIEBRE",Análisis!D47,""),"—") | E48: =IFERROR(IF(Análisis!$K$47="🔴 QUIEBRE",Análisis!E47,""),"—") | F48: =IFERROR(IF(Análisis!$K$47="🔴 QUIEBRE",Análisis!F47,""),"—") | G48: =IFERROR(IF(Análisis!$K$47="🔴 QUIEBRE",Análisis!I47,""),"—") | H48: =IFERROR(IF(Análisis!$K$47="🔴 QUIEBRE",Análisis!M47,""),"—") | I48: =IFERROR(IF(Análisis!$K$47="🔴 QUIEBRE",Análisis!H47,""),"—") | J48: =IFERROR(IF(Análisis!$K$47="🔴 QUIEBRE",Análisis!O47,""),"—")
A49: =IFERROR(IF(Análisis!$K$48="🔴 QUIEBRE",Análisis!A48,""),"—") -> SKU-044 | B49: =IFERROR(IF(Análisis!$K$48="🔴 QUIEBRE",Análisis!B48,""),"—") -> Papel Higiénico x4 | C49: =IFERROR(IF(Análisis!$K$48="🔴 QUIEBRE",Análisis!C48,""),"—") -> Limpieza del Hogar | D49: =IFERROR(IF(Análisis!$K$48="🔴 QUIEBRE",Análisis!D48,""),"—") -> 20 | E49: =IFERROR(IF(Análisis!$K$48="🔴 QUIEBRE",Análisis!E48,""),"—") -> 279.5 | F49: =IFERROR(IF(Análisis!$K$48="🔴 QUIEBRE",Análisis!F48,""),"—") -> 2.1466905 | G49: =IFERROR(IF(Análisis!$K$48="🔴 QUIEBRE",Análisis!I48,""),"—") -> 47 | H49: =IFERROR(IF(Análisis!$K$48="🔴 QUIEBRE",Análisis!M48,""),"—") -> A | I49: =IFERROR(IF(Análisis!$K$48="🔴 QUIEBRE",Análisis!H48,""),"—") -> 72 | J49: =IFERROR(IF(Análisis!$K$48="🔴 QUIEBRE",Análisis!O48,""),"—") -> REPOSICIÓN URGENTE
A50: =IFERROR(IF(Análisis!$K$49="🔴 QUIEBRE",Análisis!A49,""),"—") | B50: =IFERROR(IF(Análisis!$K$49="🔴 QUIEBRE",Análisis!B49,""),"—") | C50: =IFERROR(IF(Análisis!$K$49="🔴 QUIEBRE",Análisis!C49,""),"—") | D50: =IFERROR(IF(Análisis!$K$49="🔴 QUIEBRE",Análisis!D49,""),"—") | E50: =IFERROR(IF(Análisis!$K$49="🔴 QUIEBRE",Análisis!E49,""),"—") | F50: =IFERROR(IF(Análisis!$K$49="🔴 QUIEBRE",Análisis!F49,""),"—") | G50: =IFERROR(IF(Análisis!$K$49="🔴 QUIEBRE",Análisis!I49,""),"—") | H50: =IFERROR(IF(Análisis!$K$49="🔴 QUIEBRE",Análisis!M49,""),"—") | I50: =IFERROR(IF(Análisis!$K$49="🔴 QUIEBRE",Análisis!H49,""),"—") | J50: =IFERROR(IF(Análisis!$K$49="🔴 QUIEBRE",Análisis!O49,""),"—")
A51: =IFERROR(IF(Análisis!$K$50="🔴 QUIEBRE",Análisis!A50,""),"—") | B51: =IFERROR(IF(Análisis!$K$50="🔴 QUIEBRE",Análisis!B50,""),"—") | C51: =IFERROR(IF(Análisis!$K$50="🔴 QUIEBRE",Análisis!C50,""),"—") | D51: =IFERROR(IF(Análisis!$K$50="🔴 QUIEBRE",Análisis!D50,""),"—") | E51: =IFERROR(IF(Análisis!$K$50="🔴 QUIEBRE",Análisis!E50,""),"—") | F51: =IFERROR(IF(Análisis!$K$50="🔴 QUIEBRE",Análisis!F50,""),"—") | G51: =IFERROR(IF(Análisis!$K$50="🔴 QUIEBRE",Análisis!I50,""),"—") | H51: =IFERROR(IF(Análisis!$K$50="🔴 QUIEBRE",Análisis!M50,""),"—") | I51: =IFERROR(IF(Análisis!$K$50="🔴 QUIEBRE",Análisis!H50,""),"—") | J51: =IFERROR(IF(Análisis!$K$50="🔴 QUIEBRE",Análisis!O50,""),"—")
A52: =IFERROR(IF(Análisis!$K$51="🔴 QUIEBRE",Análisis!A51,""),"—") | B52: =IFERROR(IF(Análisis!$K$51="🔴 QUIEBRE",Análisis!B51,""),"—") | C52: =IFERROR(IF(Análisis!$K$51="🔴 QUIEBRE",Análisis!C51,""),"—") | D52: =IFERROR(IF(Análisis!$K$51="🔴 QUIEBRE",Análisis!D51,""),"—") | E52: =IFERROR(IF(Análisis!$K$51="🔴 QUIEBRE",Análisis!E51,""),"—") | F52: =IFERROR(IF(Análisis!$K$51="🔴 QUIEBRE",Análisis!F51,""),"—") | G52: =IFERROR(IF(Análisis!$K$51="🔴 QUIEBRE",Análisis!I51,""),"—") | H52: =IFERROR(IF(Análisis!$K$51="🔴 QUIEBRE",Análisis!M51,""),"—") | I52: =IFERROR(IF(Análisis!$K$51="🔴 QUIEBRE",Análisis!H51,""),"—") | J52: =IFERROR(IF(Análisis!$K$51="🔴 QUIEBRE",Análisis!O51,""),"—")
A53: =IFERROR(IF(Análisis!$K$52="🔴 QUIEBRE",Análisis!A52,""),"—") | B53: =IFERROR(IF(Análisis!$K$52="🔴 QUIEBRE",Análisis!B52,""),"—") | C53: =IFERROR(IF(Análisis!$K$52="🔴 QUIEBRE",Análisis!C52,""),"—") | D53: =IFERROR(IF(Análisis!$K$52="🔴 QUIEBRE",Análisis!D52,""),"—") | E53: =IFERROR(IF(Análisis!$K$52="🔴 QUIEBRE",Análisis!E52,""),"—") | F53: =IFERROR(IF(Análisis!$K$52="🔴 QUIEBRE",Análisis!F52,""),"—") | G53: =IFERROR(IF(Análisis!$K$52="🔴 QUIEBRE",Análisis!I52,""),"—") | H53: =IFERROR(IF(Análisis!$K$52="🔴 QUIEBRE",Análisis!M52,""),"—") | I53: =IFERROR(IF(Análisis!$K$52="🔴 QUIEBRE",Análisis!H52,""),"—") | J53: =IFERROR(IF(Análisis!$K$52="🔴 QUIEBRE",Análisis!O52,""),"—")
A54: =IFERROR(IF(Análisis!$K$53="🔴 QUIEBRE",Análisis!A53,""),"—") | B54: =IFERROR(IF(Análisis!$K$53="🔴 QUIEBRE",Análisis!B53,""),"—") | C54: =IFERROR(IF(Análisis!$K$53="🔴 QUIEBRE",Análisis!C53,""),"—") | D54: =IFERROR(IF(Análisis!$K$53="🔴 QUIEBRE",Análisis!D53,""),"—") | E54: =IFERROR(IF(Análisis!$K$53="🔴 QUIEBRE",Análisis!E53,""),"—") | F54: =IFERROR(IF(Análisis!$K$53="🔴 QUIEBRE",Análisis!F53,""),"—") | G54: =IFERROR(IF(Análisis!$K$53="🔴 QUIEBRE",Análisis!I53,""),"—") | H54: =IFERROR(IF(Análisis!$K$53="🔴 QUIEBRE",Análisis!M53,""),"—") | I54: =IFERROR(IF(Análisis!$K$53="🔴 QUIEBRE",Análisis!H53,""),"—") | J54: =IFERROR(IF(Análisis!$K$53="🔴 QUIEBRE",Análisis!O53,""),"—")
A55: =IFERROR(IF(Análisis!$K$54="🔴 QUIEBRE",Análisis!A54,""),"—") | B55: =IFERROR(IF(Análisis!$K$54="🔴 QUIEBRE",Análisis!B54,""),"—") | C55: =IFERROR(IF(Análisis!$K$54="🔴 QUIEBRE",Análisis!C54,""),"—") | D55: =IFERROR(IF(Análisis!$K$54="🔴 QUIEBRE",Análisis!D54,""),"—") | E55: =IFERROR(IF(Análisis!$K$54="🔴 QUIEBRE",Análisis!E54,""),"—") | F55: =IFERROR(IF(Análisis!$K$54="🔴 QUIEBRE",Análisis!F54,""),"—") | G55: =IFERROR(IF(Análisis!$K$54="🔴 QUIEBRE",Análisis!I54,""),"—") | H55: =IFERROR(IF(Análisis!$K$54="🔴 QUIEBRE",Análisis!M54,""),"—") | I55: =IFERROR(IF(Análisis!$K$54="🔴 QUIEBRE",Análisis!H54,""),"—") | J55: =IFERROR(IF(Análisis!$K$54="🔴 QUIEBRE",Análisis!O54,""),"—")
A56: =IFERROR(IF(Análisis!$K$55="🔴 QUIEBRE",Análisis!A55,""),"—") | B56: =IFERROR(IF(Análisis!$K$55="🔴 QUIEBRE",Análisis!B55,""),"—") | C56: =IFERROR(IF(Análisis!$K$55="🔴 QUIEBRE",Análisis!C55,""),"—") | D56: =IFERROR(IF(Análisis!$K$55="🔴 QUIEBRE",Análisis!D55,""),"—") | E56: =IFERROR(IF(Análisis!$K$55="🔴 QUIEBRE",Análisis!E55,""),"—") | F56: =IFERROR(IF(Análisis!$K$55="🔴 QUIEBRE",Análisis!F55,""),"—") | G56: =IFERROR(IF(Análisis!$K$55="🔴 QUIEBRE",Análisis!I55,""),"—") | H56: =IFERROR(IF(Análisis!$K$55="🔴 QUIEBRE",Análisis!M55,""),"—") | I56: =IFERROR(IF(Análisis!$K$55="🔴 QUIEBRE",Análisis!H55,""),"—") | J56: =IFERROR(IF(Análisis!$K$55="🔴 QUIEBRE",Análisis!O55,""),"—")
A57: =IFERROR(IF(Análisis!$K$56="🔴 QUIEBRE",Análisis!A56,""),"—") | B57: =IFERROR(IF(Análisis!$K$56="🔴 QUIEBRE",Análisis!B56,""),"—") | C57: =IFERROR(IF(Análisis!$K$56="🔴 QUIEBRE",Análisis!C56,""),"—") | D57: =IFERROR(IF(Análisis!$K$56="🔴 QUIEBRE",Análisis!D56,""),"—") | E57: =IFERROR(IF(Análisis!$K$56="🔴 QUIEBRE",Análisis!E56,""),"—") | F57: =IFERROR(IF(Análisis!$K$56="🔴 QUIEBRE",Análisis!F56,""),"—") | G57: =IFERROR(IF(Análisis!$K$56="🔴 QUIEBRE",Análisis!I56,""),"—") | H57: =IFERROR(IF(Análisis!$K$56="🔴 QUIEBRE",Análisis!M56,""),"—") | I57: =IFERROR(IF(Análisis!$K$56="🔴 QUIEBRE",Análisis!H56,""),"—") | J57: =IFERROR(IF(Análisis!$K$56="🔴 QUIEBRE",Análisis!O56,""),"—")
A58: =IFERROR(IF(Análisis!$K$57="🔴 QUIEBRE",Análisis!A57,""),"—") | B58: =IFERROR(IF(Análisis!$K$57="🔴 QUIEBRE",Análisis!B57,""),"—") | C58: =IFERROR(IF(Análisis!$K$57="🔴 QUIEBRE",Análisis!C57,""),"—") | D58: =IFERROR(IF(Análisis!$K$57="🔴 QUIEBRE",Análisis!D57,""),"—") | E58: =IFERROR(IF(Análisis!$K$57="🔴 QUIEBRE",Análisis!E57,""),"—") | F58: =IFERROR(IF(Análisis!$K$57="🔴 QUIEBRE",Análisis!F57,""),"—") | G58: =IFERROR(IF(Análisis!$K$57="🔴 QUIEBRE",Análisis!I57,""),"—") | H58: =IFERROR(IF(Análisis!$K$57="🔴 QUIEBRE",Análisis!M57,""),"—") | I58: =IFERROR(IF(Análisis!$K$57="🔴 QUIEBRE",Análisis!H57,""),"—") | J58: =IFERROR(IF(Análisis!$K$57="🔴 QUIEBRE",Análisis!O57,""),"—")
A59: =IFERROR(IF(Análisis!$K$58="🔴 QUIEBRE",Análisis!A58,""),"—") | B59: =IFERROR(IF(Análisis!$K$58="🔴 QUIEBRE",Análisis!B58,""),"—") | C59: =IFERROR(IF(Análisis!$K$58="🔴 QUIEBRE",Análisis!C58,""),"—") | D59: =IFERROR(IF(Análisis!$K$58="🔴 QUIEBRE",Análisis!D58,""),"—") | E59: =IFERROR(IF(Análisis!$K$58="🔴 QUIEBRE",Análisis!E58,""),"—") | F59: =IFERROR(IF(Análisis!$K$58="🔴 QUIEBRE",Análisis!F58,""),"—") | G59: =IFERROR(IF(Análisis!$K$58="🔴 QUIEBRE",Análisis!I58,""),"—") | H59: =IFERROR(IF(Análisis!$K$58="🔴 QUIEBRE",Análisis!M58,""),"—") | I59: =IFERROR(IF(Análisis!$K$58="🔴 QUIEBRE",Análisis!H58,""),"—") | J59: =IFERROR(IF(Análisis!$K$58="🔴 QUIEBRE",Análisis!O58,""),"—")
A60: =IFERROR(IF(Análisis!$K$59="🔴 QUIEBRE",Análisis!A59,""),"—") -> SKU-055 | B60: =IFERROR(IF(Análisis!$K$59="🔴 QUIEBRE",Análisis!B59,""),"—") -> Pasta Dental 90g | C60: =IFERROR(IF(Análisis!$K$59="🔴 QUIEBRE",Análisis!C59,""),"—") -> Higiene Personal | D60: =IFERROR(IF(Análisis!$K$59="🔴 QUIEBRE",Análisis!D59,""),"—") -> 20 | E60: =IFERROR(IF(Análisis!$K$59="🔴 QUIEBRE",Análisis!E59,""),"—") -> 307.16667 | F60: =IFERROR(IF(Análisis!$K$59="🔴 QUIEBRE",Análisis!F59,""),"—") -> 1.953337 | G60: =IFERROR(IF(Análisis!$K$59="🔴 QUIEBRE",Análisis!I59,""),"—") -> 77 | H60: =IFERROR(IF(Análisis!$K$59="🔴 QUIEBRE",Análisis!M59,""),"—") -> A | I60: =IFERROR(IF(Análisis!$K$59="🔴 QUIEBRE",Análisis!H59,""),"—") -> 48 | J60: =IFERROR(IF(Análisis!$K$59="🔴 QUIEBRE",Análisis!O59,""),"—") -> REPOSICIÓN URGENTE
A61: =IFERROR(IF(Análisis!$K$60="🔴 QUIEBRE",Análisis!A60,""),"—") | B61: =IFERROR(IF(Análisis!$K$60="🔴 QUIEBRE",Análisis!B60,""),"—") | C61: =IFERROR(IF(Análisis!$K$60="🔴 QUIEBRE",Análisis!C60,""),"—") | D61: =IFERROR(IF(Análisis!$K$60="🔴 QUIEBRE",Análisis!D60,""),"—") | E61: =IFERROR(IF(Análisis!$K$60="🔴 QUIEBRE",Análisis!E60,""),"—") | F61: =IFERROR(IF(Análisis!$K$60="🔴 QUIEBRE",Análisis!F60,""),"—") | G61: =IFERROR(IF(Análisis!$K$60="🔴 QUIEBRE",Análisis!I60,""),"—") | H61: =IFERROR(IF(Análisis!$K$60="🔴 QUIEBRE",Análisis!M60,""),"—") | I61: =IFERROR(IF(Análisis!$K$60="🔴 QUIEBRE",Análisis!H60,""),"—") | J61: =IFERROR(IF(Análisis!$K$60="🔴 QUIEBRE",Análisis!O60,""),"—")
A62: =IFERROR(IF(Análisis!$K$61="🔴 QUIEBRE",Análisis!A61,""),"—") | B62: =IFERROR(IF(Análisis!$K$61="🔴 QUIEBRE",Análisis!B61,""),"—") | C62: =IFERROR(IF(Análisis!$K$61="🔴 QUIEBRE",Análisis!C61,""),"—") | D62: =IFERROR(IF(Análisis!$K$61="🔴 QUIEBRE",Análisis!D61,""),"—") | E62: =IFERROR(IF(Análisis!$K$61="🔴 QUIEBRE",Análisis!E61,""),"—") | F62: =IFERROR(IF(Análisis!$K$61="🔴 QUIEBRE",Análisis!F61,""),"—") | G62: =IFERROR(IF(Análisis!$K$61="🔴 QUIEBRE",Análisis!I61,""),"—") | H62: =IFERROR(IF(Análisis!$K$61="🔴 QUIEBRE",Análisis!M61,""),"—") | I62: =IFERROR(IF(Análisis!$K$61="🔴 QUIEBRE",Análisis!H61,""),"—") | J62: =IFERROR(IF(Análisis!$K$61="🔴 QUIEBRE",Análisis!O61,""),"—")
A63: =IFERROR(IF(Análisis!$K$62="🔴 QUIEBRE",Análisis!A62,""),"—") | B63: =IFERROR(IF(Análisis!$K$62="🔴 QUIEBRE",Análisis!B62,""),"—") | C63: =IFERROR(IF(Análisis!$K$62="🔴 QUIEBRE",Análisis!C62,""),"—") | D63: =IFERROR(IF(Análisis!$K$62="🔴 QUIEBRE",Análisis!D62,""),"—") | E63: =IFERROR(IF(Análisis!$K$62="🔴 QUIEBRE",Análisis!E62,""),"—") | F63: =IFERROR(IF(Análisis!$K$62="🔴 QUIEBRE",Análisis!F62,""),"—") | G63: =IFERROR(IF(Análisis!$K$62="🔴 QUIEBRE",Análisis!I62,""),"—") | H63: =IFERROR(IF(Análisis!$K$62="🔴 QUIEBRE",Análisis!M62,""),"—") | I63: =IFERROR(IF(Análisis!$K$62="🔴 QUIEBRE",Análisis!H62,""),"—") | J63: =IFERROR(IF(Análisis!$K$62="🔴 QUIEBRE",Análisis!O62,""),"—")
A64: =IFERROR(IF(Análisis!$K$63="🔴 QUIEBRE",Análisis!A63,""),"—") | B64: =IFERROR(IF(Análisis!$K$63="🔴 QUIEBRE",Análisis!B63,""),"—") | C64: =IFERROR(IF(Análisis!$K$63="🔴 QUIEBRE",Análisis!C63,""),"—") | D64: =IFERROR(IF(Análisis!$K$63="🔴 QUIEBRE",Análisis!D63,""),"—") | E64: =IFERROR(IF(Análisis!$K$63="🔴 QUIEBRE",Análisis!E63,""),"—") | F64: =IFERROR(IF(Análisis!$K$63="🔴 QUIEBRE",Análisis!F63,""),"—") | G64: =IFERROR(IF(Análisis!$K$63="🔴 QUIEBRE",Análisis!I63,""),"—") | H64: =IFERROR(IF(Análisis!$K$63="🔴 QUIEBRE",Análisis!M63,""),"—") | I64: =IFERROR(IF(Análisis!$K$63="🔴 QUIEBRE",Análisis!H63,""),"—") | J64: =IFERROR(IF(Análisis!$K$63="🔴 QUIEBRE",Análisis!O63,""),"—")
A65: =IFERROR(IF(Análisis!$K$64="🔴 QUIEBRE",Análisis!A64,""),"—") | B65: =IFERROR(IF(Análisis!$K$64="🔴 QUIEBRE",Análisis!B64,""),"—") | C65: =IFERROR(IF(Análisis!$K$64="🔴 QUIEBRE",Análisis!C64,""),"—") | D65: =IFERROR(IF(Análisis!$K$64="🔴 QUIEBRE",Análisis!D64,""),"—") | E65: =IFERROR(IF(Análisis!$K$64="🔴 QUIEBRE",Análisis!E64,""),"—") | F65: =IFERROR(IF(Análisis!$K$64="🔴 QUIEBRE",Análisis!F64,""),"—") | G65: =IFERROR(IF(Análisis!$K$64="🔴 QUIEBRE",Análisis!I64,""),"—") | H65: =IFERROR(IF(Análisis!$K$64="🔴 QUIEBRE",Análisis!M64,""),"—") | I65: =IFERROR(IF(Análisis!$K$64="🔴 QUIEBRE",Análisis!H64,""),"—") | J65: =IFERROR(IF(Análisis!$K$64="🔴 QUIEBRE",Análisis!O64,""),"—")
A66: =IFERROR(IF(Análisis!$K$65="🔴 QUIEBRE",Análisis!A65,""),"—") | B66: =IFERROR(IF(Análisis!$K$65="🔴 QUIEBRE",Análisis!B65,""),"—") | C66: =IFERROR(IF(Análisis!$K$65="🔴 QUIEBRE",Análisis!C65,""),"—") | D66: =IFERROR(IF(Análisis!$K$65="🔴 QUIEBRE",Análisis!D65,""),"—") | E66: =IFERROR(IF(Análisis!$K$65="🔴 QUIEBRE",Análisis!E65,""),"—") | F66: =IFERROR(IF(Análisis!$K$65="🔴 QUIEBRE",Análisis!F65,""),"—") | G66: =IFERROR(IF(Análisis!$K$65="🔴 QUIEBRE",Análisis!I65,""),"—") | H66: =IFERROR(IF(Análisis!$K$65="🔴 QUIEBRE",Análisis!M65,""),"—") | I66: =IFERROR(IF(Análisis!$K$65="🔴 QUIEBRE",Análisis!H65,""),"—") | J66: =IFERROR(IF(Análisis!$K$65="🔴 QUIEBRE",Análisis!O65,""),"—")
A67: =IFERROR(IF(Análisis!$K$66="🔴 QUIEBRE",Análisis!A66,""),"—") | B67: =IFERROR(IF(Análisis!$K$66="🔴 QUIEBRE",Análisis!B66,""),"—") | C67: =IFERROR(IF(Análisis!$K$66="🔴 QUIEBRE",Análisis!C66,""),"—") | D67: =IFERROR(IF(Análisis!$K$66="🔴 QUIEBRE",Análisis!D66,""),"—") | E67: =IFERROR(IF(Análisis!$K$66="🔴 QUIEBRE",Análisis!E66,""),"—") | F67: =IFERROR(IF(Análisis!$K$66="🔴 QUIEBRE",Análisis!F66,""),"—") | G67: =IFERROR(IF(Análisis!$K$66="🔴 QUIEBRE",Análisis!I66,""),"—") | H67: =IFERROR(IF(Análisis!$K$66="🔴 QUIEBRE",Análisis!M66,""),"—") | I67: =IFERROR(IF(Análisis!$K$66="🔴 QUIEBRE",Análisis!H66,""),"—") | J67: =IFERROR(IF(Análisis!$K$66="🔴 QUIEBRE",Análisis!O66,""),"—")
A68: =IFERROR(IF(Análisis!$K$67="🔴 QUIEBRE",Análisis!A67,""),"—") | B68: =IFERROR(IF(Análisis!$K$67="🔴 QUIEBRE",Análisis!B67,""),"—") | C68: =IFERROR(IF(Análisis!$K$67="🔴 QUIEBRE",Análisis!C67,""),"—") | D68: =IFERROR(IF(Análisis!$K$67="🔴 QUIEBRE",Análisis!D67,""),"—") | E68: =IFERROR(IF(Análisis!$K$67="🔴 QUIEBRE",Análisis!E67,""),"—") | F68: =IFERROR(IF(Análisis!$K$67="🔴 QUIEBRE",Análisis!F67,""),"—") | G68: =IFERROR(IF(Análisis!$K$67="🔴 QUIEBRE",Análisis!I67,""),"—") | H68: =IFERROR(IF(Análisis!$K$67="🔴 QUIEBRE",Análisis!M67,""),"—") | I68: =IFERROR(IF(Análisis!$K$67="🔴 QUIEBRE",Análisis!H67,""),"—") | J68: =IFERROR(IF(Análisis!$K$67="🔴 QUIEBRE",Análisis!O67,""),"—")
A69: =IFERROR(IF(Análisis!$K$68="🔴 QUIEBRE",Análisis!A68,""),"—") | B69: =IFERROR(IF(Análisis!$K$68="🔴 QUIEBRE",Análisis!B68,""),"—") | C69: =IFERROR(IF(Análisis!$K$68="🔴 QUIEBRE",Análisis!C68,""),"—") | D69: =IFERROR(IF(Análisis!$K$68="🔴 QUIEBRE",Análisis!D68,""),"—") | E69: =IFERROR(IF(Análisis!$K$68="🔴 QUIEBRE",Análisis!E68,""),"—") | F69: =IFERROR(IF(Análisis!$K$68="🔴 QUIEBRE",Análisis!F68,""),"—") | G69: =IFERROR(IF(Análisis!$K$68="🔴 QUIEBRE",Análisis!I68,""),"—") | H69: =IFERROR(IF(Análisis!$K$68="🔴 QUIEBRE",Análisis!M68,""),"—") | I69: =IFERROR(IF(Análisis!$K$68="🔴 QUIEBRE",Análisis!H68,""),"—") | J69: =IFERROR(IF(Análisis!$K$68="🔴 QUIEBRE",Análisis!O68,""),"—")
A70: =IFERROR(IF(Análisis!$K$69="🔴 QUIEBRE",Análisis!A69,""),"—") | B70: =IFERROR(IF(Análisis!$K$69="🔴 QUIEBRE",Análisis!B69,""),"—") | C70: =IFERROR(IF(Análisis!$K$69="🔴 QUIEBRE",Análisis!C69,""),"—") | D70: =IFERROR(IF(Análisis!$K$69="🔴 QUIEBRE",Análisis!D69,""),"—") | E70: =IFERROR(IF(Análisis!$K$69="🔴 QUIEBRE",Análisis!E69,""),"—") | F70: =IFERROR(IF(Análisis!$K$69="🔴 QUIEBRE",Análisis!F69,""),"—") | G70: =IFERROR(IF(Análisis!$K$69="🔴 QUIEBRE",Análisis!I69,""),"—") | H70: =IFERROR(IF(Análisis!$K$69="🔴 QUIEBRE",Análisis!M69,""),"—") | I70: =IFERROR(IF(Análisis!$K$69="🔴 QUIEBRE",Análisis!H69,""),"—") | J70: =IFERROR(IF(Análisis!$K$69="🔴 QUIEBRE",Análisis!O69,""),"—")
A71: =IFERROR(IF(Análisis!$K$70="🔴 QUIEBRE",Análisis!A70,""),"—") | B71: =IFERROR(IF(Análisis!$K$70="🔴 QUIEBRE",Análisis!B70,""),"—") | C71: =IFERROR(IF(Análisis!$K$70="🔴 QUIEBRE",Análisis!C70,""),"—") | D71: =IFERROR(IF(Análisis!$K$70="🔴 QUIEBRE",Análisis!D70,""),"—") | E71: =IFERROR(IF(Análisis!$K$70="🔴 QUIEBRE",Análisis!E70,""),"—") | F71: =IFERROR(IF(Análisis!$K$70="🔴 QUIEBRE",Análisis!F70,""),"—") | G71: =IFERROR(IF(Análisis!$K$70="🔴 QUIEBRE",Análisis!I70,""),"—") | H71: =IFERROR(IF(Análisis!$K$70="🔴 QUIEBRE",Análisis!M70,""),"—") | I71: =IFERROR(IF(Análisis!$K$70="🔴 QUIEBRE",Análisis!H70,""),"—") | J71: =IFERROR(IF(Análisis!$K$70="🔴 QUIEBRE",Análisis!O70,""),"—")
A72: =IFERROR(IF(Análisis!$K$71="🔴 QUIEBRE",Análisis!A71,""),"—") -> SKU-067 | B72: =IFERROR(IF(Análisis!$K$71="🔴 QUIEBRE",Análisis!B71,""),"—") -> Afeitadora Descartable x5 | C72: =IFERROR(IF(Análisis!$K$71="🔴 QUIEBRE",Análisis!C71,""),"—") -> Higiene Personal | D72: =IFERROR(IF(Análisis!$K$71="🔴 QUIEBRE",Análisis!D71,""),"—") -> 32 | E72: =IFERROR(IF(Análisis!$K$71="🔴 QUIEBRE",Análisis!E71,""),"—") -> 190.5 | F72: =IFERROR(IF(Análisis!$K$71="🔴 QUIEBRE",Análisis!F71,""),"—") -> 5.0393701 | G72: =IFERROR(IF(Análisis!$K$71="🔴 QUIEBRE",Análisis!I71,""),"—") -> 51 | H72: =IFERROR(IF(Análisis!$K$71="🔴 QUIEBRE",Análisis!M71,""),"—") -> A | I72: =IFERROR(IF(Análisis!$K$71="🔴 QUIEBRE",Análisis!H71,""),"—") -> 153.6 | J72: =IFERROR(IF(Análisis!$K$71="🔴 QUIEBRE",Análisis!O71,""),"—") -> REPOSICIÓN URGENTE
A73: =IFERROR(IF(Análisis!$K$72="🔴 QUIEBRE",Análisis!A72,""),"—") | B73: =IFERROR(IF(Análisis!$K$72="🔴 QUIEBRE",Análisis!B72,""),"—") | C73: =IFERROR(IF(Análisis!$K$72="🔴 QUIEBRE",Análisis!C72,""),"—") | D73: =IFERROR(IF(Análisis!$K$72="🔴 QUIEBRE",Análisis!D72,""),"—") | E73: =IFERROR(IF(Análisis!$K$72="🔴 QUIEBRE",Análisis!E72,""),"—") | F73: =IFERROR(IF(Análisis!$K$72="🔴 QUIEBRE",Análisis!F72,""),"—") | G73: =IFERROR(IF(Análisis!$K$72="🔴 QUIEBRE",Análisis!I72,""),"—") | H73: =IFERROR(IF(Análisis!$K$72="🔴 QUIEBRE",Análisis!M72,""),"—") | I73: =IFERROR(IF(Análisis!$K$72="🔴 QUIEBRE",Análisis!H72,""),"—") | J73: =IFERROR(IF(Análisis!$K$72="🔴 QUIEBRE",Análisis!O72,""),"—")
A74: =IFERROR(IF(Análisis!$K$73="🔴 QUIEBRE",Análisis!A73,""),"—") | B74: =IFERROR(IF(Análisis!$K$73="🔴 QUIEBRE",Análisis!B73,""),"—") | C74: =IFERROR(IF(Análisis!$K$73="🔴 QUIEBRE",Análisis!C73,""),"—") | D74: =IFERROR(IF(Análisis!$K$73="🔴 QUIEBRE",Análisis!D73,""),"—") | E74: =IFERROR(IF(Análisis!$K$73="🔴 QUIEBRE",Análisis!E73,""),"—") | F74: =IFERROR(IF(Análisis!$K$73="🔴 QUIEBRE",Análisis!F73,""),"—") | G74: =IFERROR(IF(Análisis!$K$73="🔴 QUIEBRE",Análisis!I73,""),"—") | H74: =IFERROR(IF(Análisis!$K$73="🔴 QUIEBRE",Análisis!M73,""),"—") | I74: =IFERROR(IF(Análisis!$K$73="🔴 QUIEBRE",Análisis!H73,""),"—") | J74: =IFERROR(IF(Análisis!$K$73="🔴 QUIEBRE",Análisis!O73,""),"—")
A75: =IFERROR(IF(Análisis!$K$74="🔴 QUIEBRE",Análisis!A74,""),"—") | B75: =IFERROR(IF(Análisis!$K$74="🔴 QUIEBRE",Análisis!B74,""),"—") | C75: =IFERROR(IF(Análisis!$K$74="🔴 QUIEBRE",Análisis!C74,""),"—") | D75: =IFERROR(IF(Análisis!$K$74="🔴 QUIEBRE",Análisis!D74,""),"—") | E75: =IFERROR(IF(Análisis!$K$74="🔴 QUIEBRE",Análisis!E74,""),"—") | F75: =IFERROR(IF(Análisis!$K$74="🔴 QUIEBRE",Análisis!F74,""),"—") | G75: =IFERROR(IF(Análisis!$K$74="🔴 QUIEBRE",Análisis!I74,""),"—") | H75: =IFERROR(IF(Análisis!$K$74="🔴 QUIEBRE",Análisis!M74,""),"—") | I75: =IFERROR(IF(Análisis!$K$74="🔴 QUIEBRE",Análisis!H74,""),"—") | J75: =IFERROR(IF(Análisis!$K$74="🔴 QUIEBRE",Análisis!O74,""),"—")
A76: =IFERROR(IF(Análisis!$K$75="🔴 QUIEBRE",Análisis!A75,""),"—") | B76: =IFERROR(IF(Análisis!$K$75="🔴 QUIEBRE",Análisis!B75,""),"—") | C76: =IFERROR(IF(Análisis!$K$75="🔴 QUIEBRE",Análisis!C75,""),"—") | D76: =IFERROR(IF(Análisis!$K$75="🔴 QUIEBRE",Análisis!D75,""),"—") | E76: =IFERROR(IF(Análisis!$K$75="🔴 QUIEBRE",Análisis!E75,""),"—") | F76: =IFERROR(IF(Análisis!$K$75="🔴 QUIEBRE",Análisis!F75,""),"—") | G76: =IFERROR(IF(Análisis!$K$75="🔴 QUIEBRE",Análisis!I75,""),"—") | H76: =IFERROR(IF(Análisis!$K$75="🔴 QUIEBRE",Análisis!M75,""),"—") | I76: =IFERROR(IF(Análisis!$K$75="🔴 QUIEBRE",Análisis!H75,""),"—") | J76: =IFERROR(IF(Análisis!$K$75="🔴 QUIEBRE",Análisis!O75,""),"—")
A77: =IFERROR(IF(Análisis!$K$76="🔴 QUIEBRE",Análisis!A76,""),"—") | B77: =IFERROR(IF(Análisis!$K$76="🔴 QUIEBRE",Análisis!B76,""),"—") | C77: =IFERROR(IF(Análisis!$K$76="🔴 QUIEBRE",Análisis!C76,""),"—") | D77: =IFERROR(IF(Análisis!$K$76="🔴 QUIEBRE",Análisis!D76,""),"—") | E77: =IFERROR(IF(Análisis!$K$76="🔴 QUIEBRE",Análisis!E76,""),"—") | F77: =IFERROR(IF(Análisis!$K$76="🔴 QUIEBRE",Análisis!F76,""),"—") | G77: =IFERROR(IF(Análisis!$K$76="🔴 QUIEBRE",Análisis!I76,""),"—") | H77: =IFERROR(IF(Análisis!$K$76="🔴 QUIEBRE",Análisis!M76,""),"—") | I77: =IFERROR(IF(Análisis!$K$76="🔴 QUIEBRE",Análisis!H76,""),"—") | J77: =IFERROR(IF(Análisis!$K$76="🔴 QUIEBRE",Análisis!O76,""),"—")
A78: =IFERROR(IF(Análisis!$K$77="🔴 QUIEBRE",Análisis!A77,""),"—") -> SKU-073 | B78: =IFERROR(IF(Análisis!$K$77="🔴 QUIEBRE",Análisis!B77,""),"—") -> Loción After Shave 100ml | C78: =IFERROR(IF(Análisis!$K$77="🔴 QUIEBRE",Análisis!C77,""),"—") -> Higiene Personal | D78: =IFERROR(IF(Análisis!$K$77="🔴 QUIEBRE",Análisis!D77,""),"—") -> 36 | E78: =IFERROR(IF(Análisis!$K$77="🔴 QUIEBRE",Análisis!E77,""),"—") -> 166 | F78: =IFERROR(IF(Análisis!$K$77="🔴 QUIEBRE",Análisis!F77,""),"—") -> 6.5060241 | G78: =IFERROR(IF(Análisis!$K$77="🔴 QUIEBRE",Análisis!I77,""),"—") -> 39 | H78: =IFERROR(IF(Análisis!$K$77="🔴 QUIEBRE",Análisis!M77,""),"—") -> A | I78: =IFERROR(IF(Análisis!$K$77="🔴 QUIEBRE",Análisis!H77,""),"—") -> 244.8 | J78: =IFERROR(IF(Análisis!$K$77="🔴 QUIEBRE",Análisis!O77,""),"—") -> REPOSICIÓN URGENTE
A79: =IFERROR(IF(Análisis!$K$78="🔴 QUIEBRE",Análisis!A78,""),"—") | B79: =IFERROR(IF(Análisis!$K$78="🔴 QUIEBRE",Análisis!B78,""),"—") | C79: =IFERROR(IF(Análisis!$K$78="🔴 QUIEBRE",Análisis!C78,""),"—") | D79: =IFERROR(IF(Análisis!$K$78="🔴 QUIEBRE",Análisis!D78,""),"—") | E79: =IFERROR(IF(Análisis!$K$78="🔴 QUIEBRE",Análisis!E78,""),"—") | F79: =IFERROR(IF(Análisis!$K$78="🔴 QUIEBRE",Análisis!F78,""),"—") | G79: =IFERROR(IF(Análisis!$K$78="🔴 QUIEBRE",Análisis!I78,""),"—") | H79: =IFERROR(IF(Análisis!$K$78="🔴 QUIEBRE",Análisis!M78,""),"—") | I79: =IFERROR(IF(Análisis!$K$78="🔴 QUIEBRE",Análisis!H78,""),"—") | J79: =IFERROR(IF(Análisis!$K$78="🔴 QUIEBRE",Análisis!O78,""),"—")
A80: =IFERROR(IF(Análisis!$K$79="🔴 QUIEBRE",Análisis!A79,""),"—") | B80: =IFERROR(IF(Análisis!$K$79="🔴 QUIEBRE",Análisis!B79,""),"—") | C80: =IFERROR(IF(Análisis!$K$79="🔴 QUIEBRE",Análisis!C79,""),"—") | D80: =IFERROR(IF(Análisis!$K$79="🔴 QUIEBRE",Análisis!D79,""),"—") | E80: =IFERROR(IF(Análisis!$K$79="🔴 QUIEBRE",Análisis!E79,""),"—") | F80: =IFERROR(IF(Análisis!$K$79="🔴 QUIEBRE",Análisis!F79,""),"—") | G80: =IFERROR(IF(Análisis!$K$79="🔴 QUIEBRE",Análisis!I79,""),"—") | H80: =IFERROR(IF(Análisis!$K$79="🔴 QUIEBRE",Análisis!M79,""),"—") | I80: =IFERROR(IF(Análisis!$K$79="🔴 QUIEBRE",Análisis!H79,""),"—") | J80: =IFERROR(IF(Análisis!$K$79="🔴 QUIEBRE",Análisis!O79,""),"—")
A83: 🔴 STOCK MUERTO — Sin movimiento >60 días y cobertura >180 días
A84: SKU ID | B84: Descripción | C84: Categoría | D84: Stock Actual | E84: Venta Prom. Mensual | F84: Días Cobertura | G84: Stock Mínimo | H84: ABC | I84: Capital Inmov. | J84: Acción
A85: =IFERROR(IF(Análisis!$K$5="🔴 STOCK MUERTO",Análisis!A5,""),"—") | B85: =IFERROR(IF(Análisis!$K$5="🔴 STOCK MUERTO",Análisis!B5,""),"—") | C85: =IFERROR(IF(Análisis!$K$5="🔴 STOCK MUERTO",Análisis!C5,""),"—") | D85: =IFERROR(IF(Análisis!$K$5="🔴 STOCK MUERTO",Análisis!D5,""),"—") | E85: =IFERROR(IF(Análisis!$K$5="🔴 STOCK MUERTO",Análisis!E5,""),"—") | F85: =IFERROR(IF(Análisis!$K$5="🔴 STOCK MUERTO",Análisis!F5,""),"—") | G85: =IFERROR(IF(Análisis!$K$5="🔴 STOCK MUERTO",Análisis!I5,""),"—") | H85: =IFERROR(IF(Análisis!$K$5="🔴 STOCK MUERTO",Análisis!M5,""),"—") | I85: =IFERROR(IF(Análisis!$K$5="🔴 STOCK MUERTO",Análisis!H5,""),"—") | J85: =IFERROR(IF(Análisis!$K$5="🔴 STOCK MUERTO",Análisis!O5,""),"—")
A86: =IFERROR(IF(Análisis!$K$6="🔴 STOCK MUERTO",Análisis!A6,""),"—") | B86: =IFERROR(IF(Análisis!$K$6="🔴 STOCK MUERTO",Análisis!B6,""),"—") | C86: =IFERROR(IF(Análisis!$K$6="🔴 STOCK MUERTO",Análisis!C6,""),"—") | D86: =IFERROR(IF(Análisis!$K$6="🔴 STOCK MUERTO",Análisis!D6,""),"—") | E86: =IFERROR(IF(Análisis!$K$6="🔴 STOCK MUERTO",Análisis!E6,""),"—") | F86: =IFERROR(IF(Análisis!$K$6="🔴 STOCK MUERTO",Análisis!F6,""),"—") | G86: =IFERROR(IF(Análisis!$K$6="🔴 STOCK MUERTO",Análisis!I6,""),"—") | H86: =IFERROR(IF(Análisis!$K$6="🔴 STOCK MUERTO",Análisis!M6,""),"—") | I86: =IFERROR(IF(Análisis!$K$6="🔴 STOCK MUERTO",Análisis!H6,""),"—") | J86: =IFERROR(IF(Análisis!$K$6="🔴 STOCK MUERTO",Análisis!O6,""),"—")
A87: =IFERROR(IF(Análisis!$K$7="🔴 STOCK MUERTO",Análisis!A7,""),"—") | B87: =IFERROR(IF(Análisis!$K$7="🔴 STOCK MUERTO",Análisis!B7,""),"—") | C87: =IFERROR(IF(Análisis!$K$7="🔴 STOCK MUERTO",Análisis!C7,""),"—") | D87: =IFERROR(IF(Análisis!$K$7="🔴 STOCK MUERTO",Análisis!D7,""),"—") | E87: =IFERROR(IF(Análisis!$K$7="🔴 STOCK MUERTO",Análisis!E7,""),"—") | F87: =IFERROR(IF(Análisis!$K$7="🔴 STOCK MUERTO",Análisis!F7,""),"—") | G87: =IFERROR(IF(Análisis!$K$7="🔴 STOCK MUERTO",Análisis!I7,""),"—") | H87: =IFERROR(IF(Análisis!$K$7="🔴 STOCK MUERTO",Análisis!M7,""),"—") | I87: =IFERROR(IF(Análisis!$K$7="🔴 STOCK MUERTO",Análisis!H7,""),"—") | J87: =IFERROR(IF(Análisis!$K$7="🔴 STOCK MUERTO",Análisis!O7,""),"—")
A88: =IFERROR(IF(Análisis!$K$8="🔴 STOCK MUERTO",Análisis!A8,""),"—") | B88: =IFERROR(IF(Análisis!$K$8="🔴 STOCK MUERTO",Análisis!B8,""),"—") | C88: =IFERROR(IF(Análisis!$K$8="🔴 STOCK MUERTO",Análisis!C8,""),"—") | D88: =IFERROR(IF(Análisis!$K$8="🔴 STOCK MUERTO",Análisis!D8,""),"—") | E88: =IFERROR(IF(Análisis!$K$8="🔴 STOCK MUERTO",Análisis!E8,""),"—") | F88: =IFERROR(IF(Análisis!$K$8="🔴 STOCK MUERTO",Análisis!F8,""),"—") | G88: =IFERROR(IF(Análisis!$K$8="🔴 STOCK MUERTO",Análisis!I8,""),"—") | H88: =IFERROR(IF(Análisis!$K$8="🔴 STOCK MUERTO",Análisis!M8,""),"—") | I88: =IFERROR(IF(Análisis!$K$8="🔴 STOCK MUERTO",Análisis!H8,""),"—") | J88: =IFERROR(IF(Análisis!$K$8="🔴 STOCK MUERTO",Análisis!O8,""),"—")
A89: =IFERROR(IF(Análisis!$K$9="🔴 STOCK MUERTO",Análisis!A9,""),"—") | B89: =IFERROR(IF(Análisis!$K$9="🔴 STOCK MUERTO",Análisis!B9,""),"—") | C89: =IFERROR(IF(Análisis!$K$9="🔴 STOCK MUERTO",Análisis!C9,""),"—") | D89: =IFERROR(IF(Análisis!$K$9="🔴 STOCK MUERTO",Análisis!D9,""),"—") | E89: =IFERROR(IF(Análisis!$K$9="🔴 STOCK MUERTO",Análisis!E9,""),"—") | F89: =IFERROR(IF(Análisis!$K$9="🔴 STOCK MUERTO",Análisis!F9,""),"—") | G89: =IFERROR(IF(Análisis!$K$9="🔴 STOCK MUERTO",Análisis!I9,""),"—") | H89: =IFERROR(IF(Análisis!$K$9="🔴 STOCK MUERTO",Análisis!M9,""),"—") | I89: =IFERROR(IF(Análisis!$K$9="🔴 STOCK MUERTO",Análisis!H9,""),"—") | J89: =IFERROR(IF(Análisis!$K$9="🔴 STOCK MUERTO",Análisis!O9,""),"—")
A90: =IFERROR(IF(Análisis!$K$10="🔴 STOCK MUERTO",Análisis!A10,""),"—") | B90: =IFERROR(IF(Análisis!$K$10="🔴 STOCK MUERTO",Análisis!B10,""),"—") | C90: =IFERROR(IF(Análisis!$K$10="🔴 STOCK MUERTO",Análisis!C10,""),"—") | D90: =IFERROR(IF(Análisis!$K$10="🔴 STOCK MUERTO",Análisis!D10,""),"—") | E90: =IFERROR(IF(Análisis!$K$10="🔴 STOCK MUERTO",Análisis!E10,""),"—") | F90: =IFERROR(IF(Análisis!$K$10="🔴 STOCK MUERTO",Análisis!F10,""),"—") | G90: =IFERROR(IF(Análisis!$K$10="🔴 STOCK MUERTO",Análisis!I10,""),"—") | H90: =IFERROR(IF(Análisis!$K$10="🔴 STOCK MUERTO",Análisis!M10,""),"—") | I90: =IFERROR(IF(Análisis!$K$10="🔴 STOCK MUERTO",Análisis!H10,""),"—") | J90: =IFERROR(IF(Análisis!$K$10="🔴 STOCK MUERTO",Análisis!O10,""),"—")
A91: =IFERROR(IF(Análisis!$K$11="🔴 STOCK MUERTO",Análisis!A11,""),"—") | B91: =IFERROR(IF(Análisis!$K$11="🔴 STOCK MUERTO",Análisis!B11,""),"—") | C91: =IFERROR(IF(Análisis!$K$11="🔴 STOCK MUERTO",Análisis!C11,""),"—") | D91: =IFERROR(IF(Análisis!$K$11="🔴 STOCK MUERTO",Análisis!D11,""),"—") | E91: =IFERROR(IF(Análisis!$K$11="🔴 STOCK MUERTO",Análisis!E11,""),"—") | F91: =IFERROR(IF(Análisis!$K$11="🔴 STOCK MUERTO",Análisis!F11,""),"—") | G91: =IFERROR(IF(Análisis!$K$11="🔴 STOCK MUERTO",Análisis!I11,""),"—") | H91: =IFERROR(IF(Análisis!$K$11="🔴 STOCK MUERTO",Análisis!M11,""),"—") | I91: =IFERROR(IF(Análisis!$K$11="🔴 STOCK MUERTO",Análisis!H11,""),"—") | J91: =IFERROR(IF(Análisis!$K$11="🔴 STOCK MUERTO",Análisis!O11,""),"—")
A92: =IFERROR(IF(Análisis!$K$12="🔴 STOCK MUERTO",Análisis!A12,""),"—") -> SKU-008 | B92: =IFERROR(IF(Análisis!$K$12="🔴 STOCK MUERTO",Análisis!B12,""),"—") -> Azúcar Morena 1kg | C92: =IFERROR(IF(Análisis!$K$12="🔴 STOCK MUERTO",Análisis!C12,""),"—") -> Alimentos Secos | D92: =IFERROR(IF(Análisis!$K$12="🔴 STOCK MUERTO",Análisis!D12,""),"—") -> 333 | E92: =IFERROR(IF(Análisis!$K$12="🔴 STOCK MUERTO",Análisis!E12,""),"—") -> 49.833333 | F92: =IFERROR(IF(Análisis!$K$12="🔴 STOCK MUERTO",Análisis!F12,""),"—") -> 200.46823 | G92: =IFERROR(IF(Análisis!$K$12="🔴 STOCK MUERTO",Análisis!I12,""),"—") -> 9 | H92: =IFERROR(IF(Análisis!$K$12="🔴 STOCK MUERTO",Análisis!M12,""),"—") -> C | I92: =IFERROR(IF(Análisis!$K$12="🔴 STOCK MUERTO",Análisis!H12,""),"—") -> 532.8 | J92: =IFERROR(IF(Análisis!$K$12="🔴 STOCK MUERTO",Análisis!O12,""),"—") -> Reducir próxima compra
A93: =IFERROR(IF(Análisis!$K$13="🔴 STOCK MUERTO",Análisis!A13,""),"—") | B93: =IFERROR(IF(Análisis!$K$13="🔴 STOCK MUERTO",Análisis!B13,""),"—") | C93: =IFERROR(IF(Análisis!$K$13="🔴 STOCK MUERTO",Análisis!C13,""),"—") | D93: =IFERROR(IF(Análisis!$K$13="🔴 STOCK MUERTO",Análisis!D13,""),"—") | E93: =IFERROR(IF(Análisis!$K$13="🔴 STOCK MUERTO",Análisis!E13,""),"—") | F93: =IFERROR(IF(Análisis!$K$13="🔴 STOCK MUERTO",Análisis!F13,""),"—") | G93: =IFERROR(IF(Análisis!$K$13="🔴 STOCK MUERTO",Análisis!I13,""),"—") | H93: =IFERROR(IF(Análisis!$K$13="🔴 STOCK MUERTO",Análisis!M13,""),"—") | I93: =IFERROR(IF(Análisis!$K$13="🔴 STOCK MUERTO",Análisis!H13,""),"—") | J93: =IFERROR(IF(Análisis!$K$13="🔴 STOCK MUERTO",Análisis!O13,""),"—")
A94: =IFERROR(IF(Análisis!$K$14="🔴 STOCK MUERTO",Análisis!A14,""),"—") | B94: =IFERROR(IF(Análisis!$K$14="🔴 STOCK MUERTO",Análisis!B14,""),"—") | C94: =IFERROR(IF(Análisis!$K$14="🔴 STOCK MUERTO",Análisis!C14,""),"—") | D94: =IFERROR(IF(Análisis!$K$14="🔴 STOCK MUERTO",Análisis!D14,""),"—") | E94: =IFERROR(IF(Análisis!$K$14="🔴 STOCK MUERTO",Análisis!E14,""),"—") | F94: =IFERROR(IF(Análisis!$K$14="🔴 STOCK MUERTO",Análisis!F14,""),"—") | G94: =IFERROR(IF(Análisis!$K$14="🔴 STOCK MUERTO",Análisis!I14,""),"—") | H94: =IFERROR(IF(Análisis!$K$14="🔴 STOCK MUERTO",Análisis!M14,""),"—") | I94: =IFERROR(IF(Análisis!$K$14="🔴 STOCK MUERTO",Análisis!H14,""),"—") | J94: =IFERROR(IF(Análisis!$K$14="🔴 STOCK MUERTO",Análisis!O14,""),"—")
A95: =IFERROR(IF(Análisis!$K$15="🔴 STOCK MUERTO",Análisis!A15,""),"—") -> SKU-011 | B95: =IFERROR(IF(Análisis!$K$15="🔴 STOCK MUERTO",Análisis!B15,""),"—") -> Aceite de Maíz 900cc | C95: =IFERROR(IF(Análisis!$K$15="🔴 STOCK MUERTO",Análisis!C15,""),"—") -> Alimentos Secos | D95: =IFERROR(IF(Análisis!$K$15="🔴 STOCK MUERTO",Análisis!D15,""),"—") -> 109 | E95: =IFERROR(IF(Análisis!$K$15="🔴 STOCK MUERTO",Análisis!E15,""),"—") -> 1.6666667 | F95: =IFERROR(IF(Análisis!$K$15="🔴 STOCK MUERTO",Análisis!F15,""),"—") -> 1962 | G95: =IFERROR(IF(Análisis!$K$15="🔴 STOCK MUERTO",Análisis!I15,""),"—") -> 5 | H95: =IFERROR(IF(Análisis!$K$15="🔴 STOCK MUERTO",Análisis!M15,""),"—") -> C | I95: =IFERROR(IF(Análisis!$K$15="🔴 STOCK MUERTO",Análisis!H15,""),"—") -> 348.8 | J95: =IFERROR(IF(Análisis!$K$15="🔴 STOCK MUERTO",Análisis!O15,""),"—") -> LIQUIDAR / DEVOLVER
A96: =IFERROR(IF(Análisis!$K$16="🔴 STOCK MUERTO",Análisis!A16,""),"—") | B96: =IFERROR(IF(Análisis!$K$16="🔴 STOCK MUERTO",Análisis!B16,""),"—") | C96: =IFERROR(IF(Análisis!$K$16="🔴 STOCK MUERTO",Análisis!C16,""),"—") | D96: =IFERROR(IF(Análisis!$K$16="🔴 STOCK MUERTO",Análisis!D16,""),"—") | E96: =IFERROR(IF(Análisis!$K$16="🔴 STOCK MUERTO",Análisis!E16,""),"—") | F96: =IFERROR(IF(Análisis!$K$16="🔴 STOCK MUERTO",Análisis!F16,""),"—") | G96: =IFERROR(IF(Análisis!$K$16="🔴 STOCK MUERTO",Análisis!I16,""),"—") | H96: =IFERROR(IF(Análisis!$K$16="🔴 STOCK MUERTO",Análisis!M16,""),"—") | I96: =IFERROR(IF(Análisis!$K$16="🔴 STOCK MUERTO",Análisis!H16,""),"—") | J96: =IFERROR(IF(Análisis!$K$16="🔴 STOCK MUERTO",Análisis!O16,""),"—")
A97: =IFERROR(IF(Análisis!$K$17="🔴 STOCK MUERTO",Análisis!A17,""),"—") | B97: =IFERROR(IF(Análisis!$K$17="🔴 STOCK MUERTO",Análisis!B17,""),"—") | C97: =IFERROR(IF(Análisis!$K$17="🔴 STOCK MUERTO",Análisis!C17,""),"—") | D97: =IFERROR(IF(Análisis!$K$17="🔴 STOCK MUERTO",Análisis!D17,""),"—") | E97: =IFERROR(IF(Análisis!$K$17="🔴 STOCK MUERTO",Análisis!E17,""),"—") | F97: =IFERROR(IF(Análisis!$K$17="🔴 STOCK MUERTO",Análisis!F17,""),"—") | G97: =IFERROR(IF(Análisis!$K$17="🔴 STOCK MUERTO",Análisis!I17,""),"—") | H97: =IFERROR(IF(Análisis!$K$17="🔴 STOCK MUERTO",Análisis!M17,""),"—") | I97: =IFERROR(IF(Análisis!$K$17="🔴 STOCK MUERTO",Análisis!H17,""),"—") | J97: =IFERROR(IF(Análisis!$K$17="🔴 STOCK MUERTO",Análisis!O17,""),"—")
A98: =IFERROR(IF(Análisis!$K$18="🔴 STOCK MUERTO",Análisis!A18,""),"—") | B98: =IFERROR(IF(Análisis!$K$18="🔴 STOCK MUERTO",Análisis!B18,""),"—") | C98: =IFERROR(IF(Análisis!$K$18="🔴 STOCK MUERTO",Análisis!C18,""),"—") | D98: =IFERROR(IF(Análisis!$K$18="🔴 STOCK MUERTO",Análisis!D18,""),"—") | E98: =IFERROR(IF(Análisis!$K$18="🔴 STOCK MUERTO",Análisis!E18,""),"—") | F98: =IFERROR(IF(Análisis!$K$18="🔴 STOCK MUERTO",Análisis!F18,""),"—") | G98: =IFERROR(IF(Análisis!$K$18="🔴 STOCK MUERTO",Análisis!I18,""),"—") | H98: =IFERROR(IF(Análisis!$K$18="🔴 STOCK MUERTO",Análisis!M18,""),"—") | I98: =IFERROR(IF(Análisis!$K$18="🔴 STOCK MUERTO",Análisis!H18,""),"—") | J98: =IFERROR(IF(Análisis!$K$18="🔴 STOCK MUERTO",Análisis!O18,""),"—")
A99: =IFERROR(IF(Análisis!$K$19="🔴 STOCK MUERTO",Análisis!A19,""),"—") -> SKU-015 | B99: =IFERROR(IF(Análisis!$K$19="🔴 STOCK MUERTO",Análisis!B19,""),"—") -> Yerba Mate 1kg | C99: =IFERROR(IF(Análisis!$K$19="🔴 STOCK MUERTO",Análisis!C19,""),"—") -> Alimentos Secos | D99: =IFERROR(IF(Análisis!$K$19="🔴 STOCK MUERTO",Análisis!D19,""),"—") -> 540 | E99: =IFERROR(IF(Análisis!$K$19="🔴 STOCK MUERTO",Análisis!E19,""),"—") -> 79.166667 | F99: =IFERROR(IF(Análisis!$K$19="🔴 STOCK MUERTO",Análisis!F19,""),"—") -> 204.63158 | G99: =IFERROR(IF(Análisis!$K$19="🔴 STOCK MUERTO",Análisis!I19,""),"—") -> 20 | H99: =IFERROR(IF(Análisis!$K$19="🔴 STOCK MUERTO",Análisis!M19,""),"—") -> C | I99: =IFERROR(IF(Análisis!$K$19="🔴 STOCK MUERTO",Análisis!H19,""),"—") -> 3888 | J99: =IFERROR(IF(Análisis!$K$19="🔴 STOCK MUERTO",Análisis!O19,""),"—") -> Reducir próxima compra
A100: =IFERROR(IF(Análisis!$K$20="🔴 STOCK MUERTO",Análisis!A20,""),"—") | B100: =IFERROR(IF(Análisis!$K$20="🔴 STOCK MUERTO",Análisis!B20,""),"—") | C100: =IFERROR(IF(Análisis!$K$20="🔴 STOCK MUERTO",Análisis!C20,""),"—") | D100: =IFERROR(IF(Análisis!$K$20="🔴 STOCK MUERTO",Análisis!D20,""),"—") | E100: =IFERROR(IF(Análisis!$K$20="🔴 STOCK MUERTO",Análisis!E20,""),"—") | F100: =IFERROR(IF(Análisis!$K$20="🔴 STOCK MUERTO",Análisis!F20,""),"—") | G100: =IFERROR(IF(Análisis!$K$20="🔴 STOCK MUERTO",Análisis!I20,""),"—") | H100: =IFERROR(IF(Análisis!$K$20="🔴 STOCK MUERTO",Análisis!M20,""),"—") | I100: =IFERROR(IF(Análisis!$K$20="🔴 STOCK MUERTO",Análisis!H20,""),"—") | J100: =IFERROR(IF(Análisis!$K$20="🔴 STOCK MUERTO",Análisis!O20,""),"—")
A101: =IFERROR(IF(Análisis!$K$21="🔴 STOCK MUERTO",Análisis!A21,""),"—") | B101: =IFERROR(IF(Análisis!$K$21="🔴 STOCK MUERTO",Análisis!B21,""),"—") | C101: =IFERROR(IF(Análisis!$K$21="🔴 STOCK MUERTO",Análisis!C21,""),"—") | D101: =IFERROR(IF(Análisis!$K$21="🔴 STOCK MUERTO",Análisis!D21,""),"—") | E101: =IFERROR(IF(Análisis!$K$21="🔴 STOCK MUERTO",Análisis!E21,""),"—") | F101: =IFERROR(IF(Análisis!$K$21="🔴 STOCK MUERTO",Análisis!F21,""),"—") | G101: =IFERROR(IF(Análisis!$K$21="🔴 STOCK MUERTO",Análisis!I21,""),"—") | H101: =IFERROR(IF(Análisis!$K$21="🔴 STOCK MUERTO",Análisis!M21,""),"—") | I101: =IFERROR(IF(Análisis!$K$21="🔴 STOCK MUERTO",Análisis!H21,""),"—") | J101: =IFERROR(IF(Análisis!$K$21="🔴 STOCK MUERTO",Análisis!O21,""),"—")
A102: =IFERROR(IF(Análisis!$K$22="🔴 STOCK MUERTO",Análisis!A22,""),"—") | B102: =IFERROR(IF(Análisis!$K$22="🔴 STOCK MUERTO",Análisis!B22,""),"—") | C102: =IFERROR(IF(Análisis!$K$22="🔴 STOCK MUERTO",Análisis!C22,""),"—") | D102: =IFERROR(IF(Análisis!$K$22="🔴 STOCK MUERTO",Análisis!D22,""),"—") | E102: =IFERROR(IF(Análisis!$K$22="🔴 STOCK MUERTO",Análisis!E22,""),"—") | F102: =IFERROR(IF(Análisis!$K$22="🔴 STOCK MUERTO",Análisis!F22,""),"—") | G102: =IFERROR(IF(Análisis!$K$22="🔴 STOCK MUERTO",Análisis!I22,""),"—") | H102: =IFERROR(IF(Análisis!$K$22="🔴 STOCK MUERTO",Análisis!M22,""),"—") | I102: =IFERROR(IF(Análisis!$K$22="🔴 STOCK MUERTO",Análisis!H22,""),"—") | J102: =IFERROR(IF(Análisis!$K$22="🔴 STOCK MUERTO",Análisis!O22,""),"—")
A103: =IFERROR(IF(Análisis!$K$23="🔴 STOCK MUERTO",Análisis!A23,""),"—") | B103: =IFERROR(IF(Análisis!$K$23="🔴 STOCK MUERTO",Análisis!B23,""),"—") | C103: =IFERROR(IF(Análisis!$K$23="🔴 STOCK MUERTO",Análisis!C23,""),"—") | D103: =IFERROR(IF(Análisis!$K$23="🔴 STOCK MUERTO",Análisis!D23,""),"—") | E103: =IFERROR(IF(Análisis!$K$23="🔴 STOCK MUERTO",Análisis!E23,""),"—") | F103: =IFERROR(IF(Análisis!$K$23="🔴 STOCK MUERTO",Análisis!F23,""),"—") | G103: =IFERROR(IF(Análisis!$K$23="🔴 STOCK MUERTO",Análisis!I23,""),"—") | H103: =IFERROR(IF(Análisis!$K$23="🔴 STOCK MUERTO",Análisis!M23,""),"—") | I103: =IFERROR(IF(Análisis!$K$23="🔴 STOCK MUERTO",Análisis!H23,""),"—") | J103: =IFERROR(IF(Análisis!$K$23="🔴 STOCK MUERTO",Análisis!O23,""),"—")
...

Sheet Dashboard
A1: ⏳ Esta hoja se completará en la Fase siguiente. | R1: Estado | S1: Cantidad
B2: DASHBOARD EJECUTIVO — SISTEMA DE CONTROL DE INVENTARIO · DISTRIBUIDORA FMCG | R2: 🟢 Normal | S2: =COUNTIF(Análisis!K5:K79,"🟢 NORMAL") -> 49
B3: Período analizado: Enero – Junio 2025 · 75 SKUs activos · 3 categorías · Datos actualizados automáticamente desde Base_Datos | R3: 🔴 Quiebre | S3: =COUNTIF(Análisis!K5:K79,"🔴 QUIEBRE") -> 7
R4: 🔴 Stock Muerto | S4: =COUNTIF(Análisis!K5:K79,"🔴 STOCK MUERTO") -> 12
B5: CAPITAL TOTAL INMOVILIZADO | G5: CAPITAL EN STOCK MUERTO | L5: SKUs POR ESTADO | R5: 🟡 Sobrestock | S5: =COUNTIF(Análisis!K5:K79,"🟡 SOBRESTOCK") -> 6
B6: =SUM(Análisis!H5:H79) -> 64825.2 | G6: =SUMIF(Análisis!K5:K79,"🔴 STOCK MUERTO",Análisis!H5:H79) -> 22472.7 | L6: =COUNTIF(Análisis!K5:K79,"🟢 NORMAL") -> 49 | R6: 🟡 Crítico | S6: =COUNTIF(Análisis!K5:K79,"🟡 CRÍTICO") -> 1
B7: Stock valorizado a precio costo | G7: 34.7% del capital total · 12 SKUs | L7: de 75 SKUs totales analizados
B8: ▶ Visibilidad completa por 1ª vez | G8: ▶ Recuperable con liquidación | L8: ▶ 7 en quiebre · 12 sin rotación | R8: Categoría | S8: Capital ($)
R9: Alimentos Secos | S9: =SUMIF(Análisis!C5:C79,"Alimentos Secos",Análisis!H5:H79) -> 13815.4
B10: DISTRIBUCIÓN DE ESTADOS | G10: CAPITAL INMOVILIZADO POR CATEGORÍA (USD) | L10: EVOLUCIÓN DE VENTAS MENSUALES (Unidades) | R10: Limpieza del Hogar | S10: =SUMIF(Análisis!C5:C79,"Limpieza del Hogar",Análisis!H5:H79) -> 25493
R11: Higiene Personal | S11: =SUMIF(Análisis!C5:C79,"Higiene Personal",Análisis!H5:H79) -> 25516.8
R13: Mes | S13: Unidades
R14: Ene-25 | S14: 8141
R15: Feb-25 | S15: 8507
R16: Mar-25 | S16: 8406
R17: Abr-25 | S17: 7999
R18: May-25 | S18: 7879
R19: Jun-25 | S19: 8391
R21: Clase | S21: SKUs
R22: A | S22: =COUNTIF(Análisis!M5:M79,"A") -> 15
R23: B | S23: =COUNTIF(Análisis!M5:M79,"B") -> 23
R24: C | S24: =COUNTIF(Análisis!M5:M79,"C") -> 37
B25: CLASIFICACIÓN ABC DE SKUs | G25: TOP 10 — MAYOR CAPITAL INMOVILIZADO | L25: IMPACTO DEL SISTEMA — ANTES vs. DESPUÉS
G26: # | H26: SKU | I26: Producto | J26: Capital | L26: Métrica | M26: Antes | N26: Después | O26: Δ | P26: Resultado | R26: Métrica | S26: ANTES | T26: DESPUÉS
G27: 1 | H27: SKU-031 | I27: Jabón en Polvo 3kg | J27: 6912 | L27: Quiebres de stock detectados | M27: 0 | N27: 7 | O27: 🔴 | P27: 100% visibilidad | R27: Quiebres detectados | S27: 0 | T27: =COUNTIF(Análisis!K5:K79,"🔴 QUIEBRE") -> 7
G28: 2 | H28: SKU-015 | I28: Yerba Mate 1kg | J28: 3888 | L28: Capital en stock muerto | M28: $0 | N28: $22.473 | O28: 🔴 | P28: Identificado y accionable | R28: Stock muerto identificado | S28: 0 | T28: =SUMIF(Análisis!K5:K79,"🔴 STOCK MUERTO",Análisis!H5:H79) -> 22472.7
G29: 3 | H29: SKU-074 | I29: Maquinilla Afeit. Reca | J29: 3362.5 | L29: Tiempo reportería mensual | M29: 270 min | N29: 20 min | O29: 🟢 | P29: -93% tiempo operativo | R29: Tiempo reportería (min) | S29: 270 | T29: 20
G30: 4 | H30: SKU-045 | I30: Papel Higiénico x12 | J30: 3361.4 | L30: SKUs sin visibilidad de estado | M30: 75 | N30: 0 | O30: 🟢 | P30: Panel completo automatizado | R30: SKUs sin visibilidad | S30: 75 | T30: 0
G31: 5 | H31: SKU-051 | I31: Jabón de Tocador x3 | J31: 2713.6 | L31: Alertas automáticas activas | M31: 0 | N31: 4 tipos | O31: 🟢 | P31: Quiebre/Muerto/Sobre/Crítico
G32: 6 | H32: SKU-057 | I32: Cepillo de Dientes x2 | J32: 2440.8 | L32: Clasificación ABC disponible | M32: No | N32: Sí | O32: 🟢 | P32: Priorización automática
G33: 7 | H33: SKU-041 | I33: Cesto de Residuos 20L | J33: 2400
G34: 8 | H34: SKU-063 | I34: Papel Higiénico Húmedo | J34: 2091.6
G35: 9 | H35: SKU-054 | I35: Acondicionador 400ml | J35: 2082.2
G36: 10 | H36: SKU-075 | I36: Repuestos Maquinilla x | J36: 2018.8
B39: 🔴 ACCIÓN URGENTE — SKUs EN QUIEBRE DE STOCK (cobertura < 7 días) · Reposición inmediata requerida
B40: SKU ID | C40: Descripción | D40: Categoría | E40: Stock Actual | F40: Venta Prom. /Mes | G40: Días Cob. | H40: Stock Mínimo | I40: ABC | J40: Capital Inmov. | K40: Días sin Movimiento | L40: Estado | M40: Acción
B41: =Análisis!A9 -> SKU-005 | C41: =Análisis!B9 -> Harina 000 1kg | D41: =Análisis!C9 -> Alimentos Secos | E41: =Análisis!D9 -> 24 | F41: =Análisis!E9 -> 374.83333 | G41: =Análisis!F9 -> 1.9208537 | H41: =Análisis!I9 -> 69 | I41: =Análisis!M9 -> A | J41: =Análisis!H9 -> 36 | K41: =Análisis!J9 -> 4 | L41: =Análisis!K9 -> 🔴 QUIEBRE | M41: =Análisis!O9 -> REPOSICIÓN URGENTE
B42: =Análisis!A16 -> SKU-012 | C42: =Análisis!B16 -> Sal Fina 1kg | D42: =Análisis!C16 -> Alimentos Secos | E42: =Análisis!D16 -> 88 | F42: =Análisis!E16 -> 406.66667 | G42: =Análisis!F16 -> 6.4918033 | H42: =Análisis!I16 -> 91 | I42: =Análisis!M16 -> A | J42: =Análisis!H16 -> 74.8 | K42: =Análisis!J16 -> 7 | L42: =Análisis!K16 -> 🔴 QUIEBRE | M42: =Análisis!O16 -> REPOSICIÓN URGENTE
B43: =Análisis!A26 -> SKU-022 | C43: =Análisis!B26 -> Mayonesa 500g | D43: =Análisis!C26 -> Alimentos Secos | E43: =Análisis!D26 -> 25 | F43: =Análisis!E26 -> 406.83333 | G43: =Análisis!F26 -> 1.8435068 | H43: =Análisis!I26 -> 105 | I43: =Análisis!M26 -> A | J43: =Análisis!H26 -> 85 | K43: =Análisis!J26 -> 2 | L43: =Análisis!K26 -> 🔴 QUIEBRE | M43: =Análisis!O26 -> REPOSICIÓN URGENTE
B44: =Análisis!A48 -> SKU-044 | C44: =Análisis!B48 -> Papel Higiénico x4 | D44: =Análisis!C48 -> Limpieza del Hogar | E44: =Análisis!D48 -> 20 | F44: =Análisis!E48 -> 279.5 | G44: =Análisis!F48 -> 2.1466905 | H44: =Análisis!I48 -> 47 | I44: =Análisis!M48 -> A | J44: =Análisis!H48 -> 72 | K44: =Análisis!J48 -> 15 | L44: =Análisis!K48 -> 🔴 QUIEBRE | M44: =Análisis!O48 -> REPOSICIÓN URGENTE
B45: =Análisis!A59 -> SKU-055 | C45: =Análisis!B59 -> Pasta Dental 90g | D45: =Análisis!C59 -> Higiene Personal | E45: =Análisis!D59 -> 20 | F45: =Análisis!E59 -> 307.16667 | G45: =Análisis!F59 -> 1.953337 | H45: =Análisis!I59 -> 77 | I45: =Análisis!M59 -> A | J45: =Análisis!H59 -> 48 | K45: =Análisis!J59 -> 21 | L45: =Análisis!K59 -> 🔴 QUIEBRE | M45: =Análisis!O59 -> REPOSICIÓN URGENTE
B46: =Análisis!A71 -> SKU-067 | C46: =Análisis!B71 -> Afeitadora Descartable x5 | D46: =Análisis!C71 -> Higiene Personal | E46: =Análisis!D71 -> 32 | F46: =Análisis!E71 -> 190.5 | G46: =Análisis!F71 -> 5.0393701 | H46: =Análisis!I71 -> 51 | I46: =Análisis!M71 -> A | J46: =Análisis!H71 -> 153.6 | K46: =Análisis!J71 -> 8 | L46: =Análisis!K71 -> 🔴 QUIEBRE | M46: =Análisis!O71 -> REPOSICIÓN URGENTE
B47: =Análisis!A77 -> SKU-073 | C47: =Análisis!B77 -> Loción After Shave 100ml | D47: =Análisis!C77 -> Higiene Personal | E47: =Análisis!D77 -> 36 | F47: =Análisis!E77 -> 166 | G47: =Análisis!F77 -> 6.5060241 | H47: =Análisis!I77 -> 39 | I47: =Análisis!M77 -> A | J47: =Análisis!H77 -> 244.8 | K47: =Análisis!J77 -> 1 | L47: =Análisis!K77 -> 🔴 QUIEBRE | M47: =Análisis!O77 -> REPOSICIÓN URGENTE
B50: Sistema de Control de Inventario · Desarrollado en Microsoft Excel · Portfolio de Logística & Supply Chain Analytics · Datos simulados con distribuciones FMCG reales
